Workbook

Sheet Overview
A2: Galicia options: what the data says
A4: 21 Aug–16 Sep 2026. October expiry. ARS per share unless stated. Historical estimates, not executable quotes.
A6: Latest date | B6: GGAL spot | C6: ATM strike | D6: ATM IV | E6: 20-day RV | F6: IV / RV20
A7: ='Daily volatility'!A25 -> 46281 | B7: ='Daily volatility'!B25 -> 6760 | C7: ='Daily volatility'!C25 -> 6800 | D7: ='Daily volatility'!F25 -> 0.43336755 | E7: ='Daily volatility'!H25 -> 0.29834284 | F7: ='Daily volatility'!K25 -> 1.4525824
A10: Coverage | B10: 920 observations, 50 series, 19 dates. Calls and puts share one expiry.
A11: Closing-price problem | B11: The added Closing price column refers to next-row openingPrice. It is excluded.
A12: Data screening | B12: 658 IV estimates retained. Zero-volume and inconsistent-range rows are excluded.
A13: Model uncertainty | B13: 30% continuous rate and zero dividends are assumptions. Daily table includes 20% / 40% rate checks.
A14: Put/call ratio | B14: Raw-volume ratio measures this file only. Volume units and market-wide coverage are unverified.
A15: Strategy use | B15: Compare historical costs and payoff shapes. Negative butterfly costs are data flags, not proven arbitrage.
A16: Missing context | B16: No bid/ask, OI or second expiry. Nineteen dates cannot support a 1-year IV rank.
A20: Date | B20: ATM IV | C20: 20-day RV
A21: =TEXT('Daily volatility'!A7,"dd-mmm") -> 21-ago | B21: ='Daily volatility'!F7 -> 0.46627794 | C21: ='Daily volatility'!H7 -> 0.30430091
A22: =TEXT('Daily volatility'!A8,"dd-mmm") -> 24-ago | B22: ='Daily volatility'!F8 -> 0.44626193 | C22: ='Daily volatility'!H8 -> 0.36708143
A23: =TEXT('Daily volatility'!A9,"dd-mmm") -> 25-ago | B23: ='Daily volatility'!F9 -> 0.4152837 | C23: ='Daily volatility'!H9 -> 0.37334688
A24: =TEXT('Daily volatility'!A10,"dd-mmm") -> 26-ago | B24: ='Daily volatility'!F10 -> 0.41015452 | C24: ='Daily volatility'!H10 -> 0.37235223
A25: =TEXT('Daily volatility'!A11,"dd-mmm") -> 27-ago | B25: ='Daily volatility'!F11 -> 0.42210478 | C25: ='Daily volatility'!H11 -> 0.37793027
A26: =TEXT('Daily volatility'!A12,"dd-mmm") -> 28-ago | B26: ='Daily volatility'!F12 -> 0.41442294 | C26: ='Daily volatility'!H12 -> 0.35592248
A27: =TEXT('Daily volatility'!A13,"dd-mmm") -> 31-ago | B27: ='Daily volatility'!F13 -> 0.43406968 | C27: ='Daily volatility'!H13 -> 0.3788277
A28: =TEXT('Daily volatility'!A14,"dd-mmm") -> 01-sep | B28: ='Daily volatility'!F14 -> 0.43289966 | C28: ='Daily volatility'!H14 -> 0.3769853
A29: =TEXT('Daily volatility'!A15,"dd-mmm") -> 02-sep | B29: ='Daily volatility'!F15 -> 0.42512126 | C29: ='Daily volatility'!H15 -> 0.37387495
A30: =TEXT('Daily volatility'!A16,"dd-mmm") -> 03-sep | B30: ='Daily volatility'!F16 -> 0.42328256 | C30: ='Daily volatility'!H16 -> 0.37398562
A31: =TEXT('Daily volatility'!A17,"dd-mmm") -> 04-sep | B31: ='Daily volatility'!F17 -> 0.41549357 | C31: ='Daily volatility'!H17 -> 0.35609757
A32: =TEXT('Daily volatility'!A18,"dd-mmm") -> 07-sep | B32: ='Daily volatility'!F18 -> 0.42889257 | C32: ='Daily volatility'!H18 -> 0.35655003
... A39: =TEXT('Daily volatility'!A25,"dd-mmm") -> 16-sep | B39: ='Daily volatility'!F25 -> 0.43336755 | C39: ='Daily volatility'!H25 -> 0.29834284
A43: Quality check | B43: Count
A44: Zero reported volume | B44: 88
A45: Price outside range | B45: 120
A46: Below intrinsic | B46: 68
A47: Model-bound failure | B47: 54
A48: Duplicate date / ticker | B48: 0
A50: Quality counts overlap. Screened prices can still be stale or asynchronous.
A53: How to read the measures
A55: IV vs. RV | B55: IV describes model-implied future uncertainty; RV measures past share-price variability.
A57: Butterfly | B57: Buy the two wings and sell two middle-strike options. Peak expiration P&L is at the middle strike.
A59: 1x2 ratio | B59: Buy one option and sell two further out-of-the-money options. Premium income adds tail exposure.
A65: Example: 6,600 / 6,800 / 7,000 call butterfly
A66: 16 Sep prices. Buy 1 call at 6,600, sell 2 at 6,800, buy 1 at 7,000. All expiration outcomes exclude costs.
A68: Debit / share | B68: Max profit / share | C68: Max loss / share | D68: Lower breakeven | E68: Upper breakeven | F68: Debit / 100 shares
A69: =Strategies!J7 -> 15.01 | B69: =Strategies!L7 -> 184.99 | C69: =Strategies!M7 -> 15.01 | D69: =Strategies!N7 -> 6615.01 | E69: =Strategies!O7 -> 6984.99 | F69: =Strategies!Q7 -> 1501
A72: GGAL at expiry | B72: P&L / share
A73: 6200 | B73: =MAX(A73-Strategies!D7,0)-2*MAX(A73-Strategies!E7,0)+MAX(A73-Strategies!F7,0)-$A$69 -> -15.01
A74: 6250 | B74: =MAX(A74-Strategies!D7,0)-2*MAX(A74-Strategies!E7,0)+MAX(A74-Strategies!F7,0)-$A$69 -> -15.01
A75: 6300 | B75: =MAX(A75-Strategies!D7,0)-2*MAX(A75-Strategies!E7,0)+MAX(A75-Strategies!F7,0)-$A$69 -> -15.01
A76: 6350 | B76: =MAX(A76-Strategies!D7,0)-2*MAX(A76-Strategies!E7,0)+MAX(A76-Strategies!F7,0)-$A$69 -> -15.01
A77: 6400 | B77: =MAX(A77-Strategies!D7,0)-2*MAX(A77-Strategies!E7,0)+MAX(A77-Strategies!F7,0)-$A$69 -> -15.01
A78: 6450 | B78: =MAX(A78-Strategies!D7,0)-2*MAX(A78-Strategies!E7,0)+MAX(A78-Strategies!F7,0)-$A$69 -> -15.01
A79: 6500 | B79: =MAX(A79-Strategies!D7,0)-2*MAX(A79-Strategies!E7,0)+MAX(A79-Strategies!F7,0)-$A$69 -> -15.01
A80: 6550 | B80: =MAX(A80-Strategies!D7,0)-2*MAX(A80-Strategies!E7,0)+MAX(A80-Strategies!F7,0)-$A$69 -> -15.01
A81: 6600 | B81: =MAX(A81-Strategies!D7,0)-2*MAX(A81-Strategies!E7,0)+MAX(A81-Strategies!F7,0)-$A$69 -> -15.01
A82: 6650 | B82: =MAX(A82-Strategies!D7,0)-2*MAX(A82-Strategies!E7,0)+MAX(A82-Strategies!F7,0)-$A$69 -> 34.99
A83: 6700 | B83: =MAX(A83-Strategies!D7,0)-2*MAX(A83-Strategies!E7,0)+MAX(A83-Strategies!F7,0)-$A$69 -> 84.99
A84: 6750 | B84: =MAX(A84-Strategies!D7,0)-2*MAX(A84-Strategies!E7,0)+MAX(A84-Strategies!F7,0)-$A$69 -> 134.99
A85: 6800 | B85: =MAX(A85-Strategies!D7,0)-2*MAX(A85-Strategies!E7,0)+MAX(A85-Strategies!F7,0)-$A$69 -> 184.99
A86: 6850 | B86: =MAX(A86-Strategies!D7,0)-2*MAX(A86-Strategies!E7,0)+MAX(A86-Strategies!F7,0)-$A$69 -> 134.99
A87: 6900 | B87: =MAX(A87-Strategies!D7,0)-2*MAX(A87-Strategies!E7,0)+MAX(A87-Strategies!F7,0)-$A$69 -> 84.99
A88: 6950 | B88: =MAX(A88-Strategies!D7,0)-2*MAX(A88-Strategies!E7,0)+MAX(A88-Strategies!F7,0)-$A$69 -> 34.99
A89: 7000 | B89: =MAX(A89-Strategies!D7,0)-2*MAX(A89-Strategies!E7,0)+MAX(A89-Strategies!F7,0)-$A$69 -> -15.01
A90: 7050 | B90: =MAX(A90-Strategies!D7,0)-2*MAX(A90-Strategies!E7,0)+MAX(A90-Strategies!F7,0)-$A$69 -> -15.01
A91: 7100 | B91: =MAX(A91-Strategies!D7,0)-2*MAX(A91-Strategies!E7,0)+MAX(A91-Strategies!F7,0)-$A$69 -> -15.01
A92: 7150 | B92: =MAX(A92-Strategies!D7,0)-2*MAX(A92-Strategies!E7,0)+MAX(A92-Strategies!F7,0)-$A$69 -> -15.01
A93: 7200 | B93: =MAX(A93-Strategies!D7,0)-2*MAX(A93-Strategies!E7,0)+MAX(A93-Strategies!F7,0)-$A$69 -> -15.01
A94: 7250 | B94: =MAX(A94-Strategies!D7,0)-2*MAX(A94-Strategies!E7,0)+MAX(A94-Strategies!F7,0)-$A$69 -> -15.01
A95: 7300 | B95: =MAX(A95-Strategies!D7,0)-2*MAX(A95-Strategies!E7,0)+MAX(A95-Strategies!F7,0)-$A$69 -> -15.01
A96: 7350 | B96: =MAX(A96-Strategies!D7,0)-2*MAX(A96-Strategies!E7,0)+MAX(A96-Strategies!F7,0)-$A$69 -> -15.01
A97: 7400 | B97: =MAX(A97-Strategies!D7,0)-2*MAX(A97-Strategies!E7,0)+MAX(A97-Strategies!F7,0)-$A$69 -> -15.01

Sheet Daily volatility
A2: Daily volatility and market ratios
A4: P/C volume uses the raw API field. IV uses the same October expiry each day, not a constant-maturity series.
A6: Date | B6: GGAL spot | C6: ATM strike | D6: Call IV | E6: Put IV | F6: ATM IV avg | G6: RV 10d | H6: RV 20d | I6: RV 60d | J6: IV − RV20 | K6: IV / RV20 | L6: P/C IV | M6: Call raw volume | N6: Put raw volume | O6: P/C raw volume | P6: 25d call IV | Q6: 25d put IV | R6: 25d skew | S6: Vol butterfly | T6: IV at 20% rate | U6: IV at 40% rate | V6: Valid IV rows
A7: 46255 | B7: 6620 | C7: 6600 | D7: 0.4503744 | E7: 0.48218149 | F7: 0.46627794 | G7: 0.32282221 | H7: 0.30430091 | J7: =IF(F7="","n.a.",F7-H7) -> 0.16197703 | K7: =IF(F7="","n.a.",F7/H7) -> 1.5322923 | L7: =IF(D7="","n.a.",E7/D7) -> 1.0706237 | M7: =SUMIFS('IV history'!$N$7:$N$926,'IV history'!$A$7:$A$926,A7,'IV history'!$C$7:$C$926,"call") -> 1.0705902e+09 | N7: =SUMIFS('IV history'!$N$7:$N$926,'IV history'!$A$7:$A$926,A7,'IV history'!$C$7:$C$926,"put") -> 3.8548392e+08 | O7: =IF(M7=0,"n.a.",N7/M7) -> 0.36006675 | P7: 0.44361666 | Q7: 0.46679113 | R7: =IF(OR(P7="",Q7=""),"n.a.",Q7-P7) -> 0.023174478 | S7: =IF(OR(P7="",Q7="",F7=""),"n.a.",(P7+Q7)/2-F7) -> -0.011074046 | T7: 0.47717652 | U7: 0.45077854 | V7: 31
A8: 46258 | B8: 6950 | C8: 7000 | D8: 0.42841322 | E8: 0.46411065 | F8: 0.44626193 | G8: 0.44037522 | H8: 0.36708143 | J8: =IF(F8="","n.a.",F8-H8) -> 0.079180506 | K8: =IF(F8="","n.a.",F8/H8) -> 1.2157028 | L8: =IF(D8="","n.a.",E8/D8) -> 1.0833248 | M8: =SUMIFS('IV history'!$N$7:$N$926,'IV history'!$A$7:$A$926,A8,'IV history'!$C$7:$C$926,"call") -> 3.6754384e+09 | N8: =SUMIFS('IV history'!$N$7:$N$926,'IV history'!$A$7:$A$926,A8,'IV history'!$C$7:$C$926,"put") -> 1.7203605e+09 | O8: =IF(M8=0,"n.a.",N8/M8) -> 0.46806948 | P8: 0.42823892 | Q8: 0.46651876 | R8: =IF(OR(P8="",Q8=""),"n.a.",Q8-P8) -> 0.038279838 | S8: =IF(OR(P8="",Q8="",F8=""),"n.a.",(P8+Q8)/2-F8) -> 0.0011169024 | T8: 0.45550845 | U8: 0.43283677 | V8: 34
A9: 46259 | B9: 7075 | C9: 7000 | D9: 0.37980973 | E9: 0.45075767 | F9: 0.4152837 | G9: 0.45248561 | H9: 0.37334688 | J9: =IF(F9="","n.a.",F9-H9) -> 0.041936826 | K9: =IF(F9="","n.a.",F9/H9) -> 1.1123267 | L9: =IF(D9="","n.a.",E9/D9) -> 1.1867986 | M9: =SUMIFS('IV history'!$N$7:$N$926,'IV history'!$A$7:$A$926,A9,'IV history'!$C$7:$C$926,"call") -> 2.7577191e+09 | N9: =SUMIFS('IV history'!$N$7:$N$926,'IV history'!$A$7:$A$926,A9,'IV history'!$C$7:$C$926,"put") -> 907131131 | O9: =IF(M9=0,"n.a.",N9/M9) -> 0.32894254 | P9: 0.4120431 | Q9: 0.45138373 | R9: =IF(OR(P9="",Q9=""),"n.a.",Q9-P9) -> 0.039340631 | S9: =IF(OR(P9="",Q9="",F9=""),"n.a.",(P9+Q9)/2-F9) -> 0.016429712 | T9: 0.42859688 | U9: 0.39586637 | V9: 34
A10: 46260 | B10: 7045 | C10: 7000 | D10: 0.36729783 | E10: 0.45301122 | F10: 0.41015452 | G10: 0.39051326 | H10: 0.37235223 | J10: =IF(F10="","n.a.",F10-H10) -> 0.037802291 | K10: =IF(F10="","n.a.",F10/H10) -> 1.1015229 | L10: =IF(D10="","n.a.",E10/D10) -> 1.2333621 | M10: =SUMIFS('IV history'!$N$7:$N$926,'IV history'!$A$7:$A$926,A10,'IV history'!$C$7:$C$926,"call") -> 2.0727826e+09 | N10: =SUMIFS('IV history'!$N$7:$N$926,'IV history'!$A$7:$A$926,A10,'IV history'!$C$7:$C$926,"put") -> 6.9325327e+08 | O10: =IF(M10=0,"n.a.",N10/M10) -> 0.33445536 | P10: 0.41021052 | Q10: 0.45375423 | R10: =IF(OR(P10="",Q10=""),"n.a.",Q10-P10) -> 0.043543707 | S10: =IF(OR(P10="",Q10="",F10=""),"n.a.",(P10+Q10)/2-F10) -> 0.02182785 | T10: 0.42267352 | U10: 0.39169758 | V10: 35
A11: 46261 | B11: 6880 | C11: 6800 | D11: 0.38954597 | E11: 0.45466358 | F11: 0.42210478 | G11: 0.40861851 | H11: 0.37793027 | I11: 0.43844102 | J11: =IF(F11="","n.a.",F11-H11) -> 0.044174503 | K11: =IF(F11="","n.a.",F11/H11) -> 1.1168853 | L11: =IF(D11="","n.a.",E11/D11) -> 1.1671628 | M11: =SUMIFS('IV history'!$N$7:$N$926,'IV history'!$A$7:$A$926,A11,'IV history'!$C$7:$C$926,"call") -> 2.4476718e+09 | N11: =SUMIFS('IV history'!$N$7:$N$926,'IV history'!$A$7:$A$926,A11,'IV history'!$C$7:$C$926,"put") -> 8.6417165e+08 | O11: =IF(M11=0,"n.a.",N11/M11) -> 0.35305863 | P11: 0.41036126 | Q11: 0.45239012 | R11: =IF(OR(P11="",Q11=""),"n.a.",Q11-P11) -> 0.042028859 | S11: =IF(OR(P11="",Q11="",F11=""),"n.a.",(P11+Q11)/2-F11) -> 0.0092709125 | T11: 0.43503069 | U11: 0.40353587 | V11: 37
A12: 46262 | B12: 6810 | C12: 6800 | D12: 0.38728894 | E12: 0.44155693 | F12: 0.41442294 | G12: 0.40393696 | H12: 0.35592248 | I12: 0.43864432 | J12: =IF(F12="","n.a.",F12-H12) -> 0.058500454 | K12: =IF(F12="","n.a.",F12/H12) -> 1.1643629 | L12: =IF(D12="","n.a.",E12/D12) -> 1.1401227 | M12: =SUMIFS('IV history'!$N$7:$N$926,'IV history'!$A$7:$A$926,A12,'IV history'!$C$7:$C$926,"call") -> 1.7405878e+09 | N12: =SUMIFS('IV history'!$N$7:$N$926,'IV history'!$A$7:$A$926,A12,'IV history'!$C$7:$C$926,"put") -> 1.0211673e+09 | O12: =IF(M12=0,"n.a.",N12/M12) -> 0.58667959 | P12: 0.40920858 | Q12: 0.44212028 | R12: =IF(OR(P12="",Q12=""),"n.a.",Q12-P12) -> 0.032911696 | S12: =IF(OR(P12="",Q12="",F12=""),"n.a.",(P12+Q12)/2-F12) -> 0.011241494 | T12: 0.42537899 | U12: 0.39864621 | V12: 34
A13: 46265 | B13: 7015 | C13: 7000 | D13: 0.41152443 | E13: 0.45661493 | F13: 0.43406968 | G13: 0.39539428 | H13: 0.3788277 | I13: 0.4388705 | J13: =IF(F13="","n.a.",F13-H13) -> 0.055241975 | K13: =IF(F13="","n.a.",F13/H13) -> 1.1458235 | L13: =IF(D13="","n.a.",E13/D13) -> 1.1095695 | M13: =SUMIFS('IV history'!$N$7:$N$926,'IV history'!$A$7:$A$926,A13,'IV history'!$C$7:$C$926,"call") -> 2837380990 | N13: =SUMIFS('IV history'!$N$7:$N$926,'IV history'!$A$7:$A$926,A13,'IV history'!$C$7:$C$926,"put") -> 7.5490269e+08 | O13: =IF(M13=0,"n.a.",N13/M13) -> 0.26605616 | P13: 0.41895923 | Q13: 0.45887837 | R13: =IF(OR(P13="",Q13=""),"n.a.",Q13-P13) -> 0.03991914 | S13: =IF(OR(P13="",Q13="",F13=""),"n.a.",(P13+Q13)/2-F13) -> 0.0048491232 | T13: 0.44411373 | U13: 0.4199053 | V13: 35
A14: 46266 | B14: 7060 | C14: 7000 | D14: 0.3990126 | E14: 0.46678672 | F14: 0.43289966 | G14: 0.3527892 | H14: 0.3769853 | I14: 0.43911418 | J14: =IF(F14="","n.a.",F14-H14) -> 0.055914361 | K14: =IF(F14="","n.a.",F14/H14) -> 1.1483197 | L14: =IF(D14="","n.a.",E14/D14) -> 1.1698546 | M14: =SUMIFS('IV history'!$N$7:$N$926,'IV history'!$A$7:$A$926,A14,'IV history'!$C$7:$C$926,"call") -> 3640294763 | N14: =SUMIFS('IV history'!$N$7:$N$926,'IV history'!$A$7:$A$926,A14,'IV history'!$C$7:$C$926,"put") -> 7.4706757e+08 | O14: =IF(M14=0,"n.a.",N14/M14) -> 0.20522172 | P14: 0.41483887 | Q14: 0.46070565 | R14: =IF(OR(P14="",Q14=""),"n.a.",Q14-P14) -> 0.045866783 | S14: =IF(OR(P14="",Q14="",F14=""),"n.a.",(P14+Q14)/2-F14) -> 0.0048726016 | T14: 0.44405228 | U14: 0.41718277 | V14: 35
A15: 46267 | B15: 7170 | C15: 7200 | D15: 0.39360067 | E15: 0.45664186 | F15: 0.42512126 | G15: 0.33443184 | H15: 0.37387495 | I15: 0.43872123 | J15: =IF(F15="","n.a.",F15-H15) -> 0.05124631 | K15: =IF(F15="","n.a.",F15/H15) -> 1.137068 | L15: =IF(D15="","n.a.",E15/D15) -> 1.1601654 | M15: =SUMIFS('IV history'!$N$7:$N$926,'IV history'!$A$7:$A$926,A15,'IV history'!$C$7:$C$926,"call") -> 2.6939953e+09 | N15: =SUMIFS('IV history'!$N$7:$N$926,'IV history'!$A$7:$A$926,A15,'IV history'!$C$7:$C$926,"put") -> 6.919505e+08 | O15: =IF(M15=0,"n.a.",N15/M15) -> 0.25684918 | P15: 0.40423199 | Q15: 0.45854063 | R15: =IF(OR(P15="",Q15=""),"n.a.",Q15-P15) -> 0.054308645 | S15: =IF(OR(P15="",Q15="",F15=""),"n.a.",(P15+Q15)/2-F15) -> 0.0062650487 | T15: 0.433909 | U15: 0.4124856 | V15: 34
A16: 46268 | B16: 7075 | C16: 7000 | D16: 0.38797271 | E16: 0.45859241 | F16: 0.42328256 | G16: 0.34624524 | H16: 0.37398562 | I16: 0.43780104 | J16: =IF(F16="","n.a.",F16-H16) -> 0.049296938 | K16: =IF(F16="","n.a.",F16/H16) -> 1.1318151 | L16: =IF(D16="","n.a.",E16/D16) -> 1.1820223 | M16: =SUMIFS('IV history'!$N$7:$N$926,'IV history'!$A$7:$A$926,A16,'IV history'!$C$7:$C$926,"call") -> 3.6394143e+09 | N16: =SUMIFS('IV history'!$N$7:$N$926,'IV history'!$A$7:$A$926,A16,'IV history'!$C$7:$C$926,"put") -> 9.4090421e+08 | O16: =IF(M16=0,"n.a.",N16/M16) -> 0.25853177 | P16: 0.41161777 | Q16: 0.45768114 | R16: =IF(OR(P16="",Q16=""),"n.a.",Q16-P16) -> 0.046063372 | S16: =IF(OR(P16="",Q16="",F16=""),"n.a.",(P16+Q16)/2-F16) -> 0.011366898 | T16: 0.43480202 | U16: 0.40708164 | V16: 36
A17: 46269 | B17: 7005 | C17: 7000 | D17: 0.39497486 | E17: 0.43601228 | F17: 0.41549357 | G17: 0.35438455 | H17: 0.35609757 | I17: 0.43422892 | J17: =IF(F17="","n.a.",F17-H17) -> 0.059396002 | K17: =IF(F17="","n.a.",F17/H17) -> 1.166797 | L17: =IF(D17="","n.a.",E17/D17) -> 1.1038988 | M17: =SUMIFS('IV history'!$N$7:$N$926,'IV history'!$A$7:$A$926,A17,'IV history'!$C$7:$C$926,"call") -> 1.8612115e+09 | N17: =SUMIFS('IV history'!$N$7:$N$926,'IV history'!$A$7:$A$926,A17,'IV history'!$C$7:$C$926,"put") -> 4.7550423e+08 | O17: =IF(M17=0,"n.a.",N17/M17) -> 0.25548103 | P17: 0.40887654 | Q17: 0.43863357 | R17: =IF(OR(P17="",Q17=""),"n.a.",Q17-P17) -> 0.02975703 | S17: =IF(OR(P17="",Q17="",F17=""),"n.a.",(P17+Q17)/2-F17) -> 0.0082614824 | T17: 0.42503132 | U17: 0.40209519 | V17: 34
A18: 46272 | B18: 6935 | C18: 7000 | D18: 0.42273407 | E18: 0.43505107 | F18: 0.42889257 | G18: 0.26661964 | H18: 0.35655003 | I18: 0.43438604 | J18: =IF(F18="","n.a.",F18-H18) -> 0.072342544 | K18: =IF(F18="","n.a.",F18/H18) -> 1.2028959 | L18: =IF(D18="","n.a.",E18/D18) -> 1.0291365 | M18: =SUMIFS('IV history'!$N$7:$N$926,'IV history'!$A$7:$A$926,A18,'IV history'!$C$7:$C$926,"call") -> 3.579335e+08 | N18: =SUMIFS('IV history'!$N$7:$N$926,'IV history'!$A$7:$A$926,A18,'IV history'!$C$7:$C$926,"put") -> 1.2392328e+08 | O18: =IF(M18=0,"n.a.",N18/M18) -> 0.34621873 | P18: 0.43464811 | Q18: 0.43933024 | R18: =IF(OR(P18="",Q18=""),"n.a.",Q18-P18) -> 0.0046821267 | S18: =IF(OR(P18="",Q18="",F18=""),"n.a.",(P18+Q18)/2-F18) -> 0.008096604 | T18: 0.43581917 | U18: 0.41902083 | V18: 37
A19: 46273 | B19: 7015 | C19: 7000 | D19: 0.40410199 | E19: 0.45187481 | F19: 0.4279884 | G19: 0.25628549 | H19: 0.35879323 | I19: 0.3811233 | J19: =IF(F19="","n.a.",F19-H19) -> 0.069195178 | K19: =IF(F19="","n.a.",F19/H19) -> 1.1928553 | L19: =IF(D19="","n.a.",E19/D19) -> 1.1182197 | M19: =SUMIFS('IV history'!$N$7:$N$926,'IV history'!$A$7:$A$926,A19,'IV history'!$C$7:$C$926,"call") -> 2.0581124e+09 | N19: =SUMIFS('IV history'!$N$7:$N$926,'IV history'!$A$7:$A$926,A19,'IV history'!$C$7:$C$926,"put") -> 5.233237e+08 | O19: =IF(M19=0,"n.a.",N19/M19) -> 0.25427363 | P19: 0.41343696 | Q19: 0.45011605 | R19: =IF(OR(P19="",Q19=""),"n.a.",Q19-P19) -> 0.036679094 | S19: =IF(OR(P19="",Q19="",F19=""),"n.a.",(P19+Q19)/2-F19) -> 0.0037881001 | T19: 0.43681577 | U19: 0.41576458 | V19: 34
A20: 46274 | B20: 7085 | C20: 7000 | D20: 0.40296012 | E20: 0.44401835 | F20: 0.42348924 | G20: 0.26086488 | H20: 0.32323908 | I20: 0.38187929 | J20: =IF(F20="","n.a.",F20-H20) -> 0.10025016 | K20: =IF(F20="","n.a.",F20/H20) -> 1.3101425 | L20: =IF(D20="","n.a.",E20/D20) -> 1.1018915 | M20: =SUMIFS('IV history'!$N$7:$N$926,'IV history'!$A$7:$A$926,A20,'IV history'!$C$7:$C$926,"call") -> 1.9194413e+09 | N20: =SUMIFS('IV history'!$N$7:$N$926,'IV history'!$A$7:$A$926,A20,'IV history'!$C$7:$C$926,"put") -> 7.6649495e+08 | O20: =IF(M20=0,"n.a.",N20/M20) -> 0.39933233 | P20: 0.41373337 | Q20: 0.4368229 | R20: =IF(OR(P20="",Q20=""),"n.a.",Q20-P20) -> 0.023089535 | S20: =IF(OR(P20="",Q20="",F20=""),"n.a.",(P20+Q20)/2-F20) -> 0.0017888977 | T20: 0.43414016 | U20: 0.40905446 | V20: 33
A21: 46275 | B21: 7145 | C21: 7200 | D21: 0.38460585 | E21: 0.4446759 | F21: 0.41464087 | G21: 0.2245112 | H21: 0.32433464 | I21: 0.38244765 | J21: =IF(F21="","n.a.",F21-H21) -> 0.090306233 | K21: =IF(F21="","n.a.",F21/H21) -> 1.2784354 | L21: =IF(D21="","n.a.",E21/D21) -> 1.156186 | M21: =SUMIFS('IV history'!$N$7:$N$926,'IV history'!$A$7:$A$926,A21,'IV history'!$C$7:$C$926,"call") -> 2.9871927e+09 | N21: =SUMIFS('IV history'!$N$7:$N$926,'IV history'!$A$7:$A$926,A21,'IV history'!$C$7:$C$926,"put") -> 7.0780402e+08 | O21: =IF(M21=0,"n.a.",N21/M21) -> 0.23694622 | P21: 0.4076178 | Q21: 0.44284128 | R21: =IF(OR(P21="",Q21=""),"n.a.",Q21-P21) -> 0.035223483 | S21: =IF(OR(P21="",Q21="",F21=""),"n.a.",(P21+Q21)/2-F21) -> 0.010588666 | T21: 0.42154701 | U21: 0.40473147 | V21: 35
A22: 46276 | B22: 7000 | C22: 7000 | D22: 0.38691221 | E22: 0.44654618 | F22: 0.41672919 | G22: 0.2472373 | H22: 0.33069086 | I22: 0.3800381 | J22: =IF(F22="","n.a.",F22-H22) -> 0.086038332 | K22: =IF(F22="","n.a.",F22/H22) -> 1.2601775 | L22: =IF(D22="","n.a.",E22/D22) -> 1.1541279 | M22: =SUMIFS('IV history'!$N$7:$N$926,'IV history'!$A$7:$A$926,A22,'IV history'!$C$7:$C$926,"call") -> 2.1745863e+09 | N22: =SUMIFS('IV history'!$N$7:$N$926,'IV history'!$A$7:$A$926,A22,'IV history'!$C$7:$C$926,"put") -> 6.6986775e+08 | O22: =IF(M22=0,"n.a.",N22/M22) -> 0.30804376 | P22: 0.41012208 | Q22: 0.44259785 | R22: =IF(OR(P22="",Q22=""),"n.a.",Q22-P22) -> 0.032475769 | S22: =IF(OR(P22="",Q22="",F22=""),"n.a.",(P22+Q22)/2-F22) -> 0.0096307677 | T22: 0.4248847 | U22: 0.40539512 | V22: 34
... A25: 46281 | B25: 6760 | C25: 6800 | D25: 0.4043901 | E25: 0.462345 | F25: 0.43336755 | G25: 0.21176785 | H25: 0.29834284 | I25: 0.37763241 | J25: =IF(F25="","n.a.",F25-H25) -> 0.13502471 | K25: =IF(F25="","n.a.",F25/H25) -> 1.4525824 | L25: =IF(D25="","n.a.",E25/D25) -> 1.1433143 | M25: =SUMIFS('IV history'!$N$7:$N$926,'IV history'!$A$7:$A$926,A25,'IV history'!$C$7:$C$926,"call") -> 1.2163219e+09 | N25: =SUMIFS('IV history'!$N$7:$N$926,'IV history'!$A$7:$A$926,A25,'IV history'!$C$7:$C$926,"put") -> 4.9613355e+08 | O25: =IF(M25=0,"n.a.",N25/M25) -> 0.40789659 | P25: 0.4196761 | Q25: 0.45951091 | R25: =IF(OR(P25="",Q25=""),"n.a.",Q25-P25) -> 0.039834806 | S25: =IF(OR(P25="",Q25="",F25=""),"n.a.",(P25+Q25)/2-F25) -> 0.0062259547 | T25: 0.43922104 | U25: 0.42514605 | V25: 34

Sheet IV history
A2: Historical implied volatility estimates
A4: Model snapshot: 30% rate, zero dividends. Conditional on ticker strikes and PPI prices. See Model inputs.
A6: Date | B6: Ticker | C6: Type | D6: Strike | E6: PPI price | F6: GGAL spot | G6: Days to expiry | H6: Intrinsic | I6: Time value | J6: K / spot | K6: IV estimate | L6: BS delta | M6: BS vega / 1pp | N6: Raw volume | O6: Low | P6: High | Q6: Data status | R6: Source row
A7: 46281 | B7: GFGC6800OC | C7: call | D7: 6800 | E7: ='Option source'!B258 -> 376.43 | F7: 6760 | G7: 30 | H7: =MAX(IF(C7="call",F7-D7,D7-F7),0) -> 0 | I7: =E7-H7 -> 376.43 | J7: =D7/F7 -> 1.0059172 | K7: 0.4043901 | L7: 0.58697229 | M7: 7.5471612 | N7: ='Option source'!C258 -> 100339456 | O7: ='Option source'!G258 -> 330 | P7: ='Option source'!F258 -> 429.88 | Q7: Screen passed; indicative | R7: 253
A8: 46281 | B8: GFGV6800OC | C8: put | D8: 6800 | E8: ='Option source'!B752 -> 312.15 | F8: 6760 | G8: 30 | H8: =MAX(IF(C8="call",F8-D8,D8-F8),0) -> 40 | I8: =E8-H8 -> 272.15 | J8: =D8/F8 -> 1.0059172 | K8: 0.462345 | L8: -0.41769652 | M8: 7.5665041 | N8: ='Option source'!C752 -> 81244632 | O8: ='Option source'!G752 -> 285 | P8: ='Option source'!F752 -> 345 | Q8: Screen passed; indicative | R8: 747
A9: 46281 | B9: GFGC6600OC | C9: call | D9: 6600 | E9: ='Option source'!B239 -> 478.22 | F9: 6760 | G9: 30 | H9: =MAX(IF(C9="call",F9-D9,D9-F9),0) -> 160 | I9: =E9-H9 -> 318.22 | J9: =D9/F9 -> 0.97633136 | K9: 0.38456052 | L9: 0.69006648 | M9: 6.8366115 | N9: ='Option source'!C239 -> 55284376 | O9: ='Option source'!G239 -> 435 | P9: ='Option source'!F239 -> 540 | Q9: Screen passed; indicative | R9: 234
A10: 46281 | B10: GFGV6600OC | C10: put | D10: 6600 | E10: ='Option source'!B733 -> 222.45 | F10: 6760 | G10: 30 | H10: =MAX(IF(C10="call",F10-D10,D10-F10),0) -> 0 | I10: =E10-H10 -> 222.45 | J10: =D10/F10 -> 0.97633136 | K10: 0.46193164 | L10: -0.33240609 | M10: 7.0389159 | N10: ='Option source'!C733 -> 124328488 | O10: ='Option source'!G733 -> 198.18 | P10: ='Option source'!F733 -> 249 | Q10: Screen passed; indicative | R10: 728
A11: 46281 | B11: GFGC7000OC | C11: call | D11: 7000 | E11: ='Option source'!B277 -> 289.65 | F11: 6760 | G11: 30 | H11: =MAX(IF(C11="call",F11-D11,D11-F11),0) -> 0 | I11: =E11-H11 -> 289.65 | J11: =D11/F11 -> 1.035503 | K11: 0.41615491 | L11: 0.48959347 | M11: 7.7289975 | N11: ='Option source'!C277 -> 223562320 | O11: ='Option source'!G277 -> 237 | P11: ='Option source'!F277 -> 329.06 | Q11: Screen passed; indicative | R11: 272
A12: 46281 | B12: GFGV7000OC | C12: put | D12: 7000 | E12: ='Option source'!B771 -> 427.03 | F12: 6760 | G12: 30 | H12: =MAX(IF(C12="call",F12-D12,D12-F12),0) -> 240 | I12: =E12-H12 -> 187.03 | J12: =D12/F12 -> 1.035503 | K12: 0.47075019 | L12: -0.50331849 | M12: 7.7313606 | N12: ='Option source'!C771 -> 45682320 | O12: ='Option source'!G771 -> 385 | P12: ='Option source'!F771 -> 465 | Q12: Screen passed; indicative | R12: 766
A13: 46281 | B13: GFGC6400OC | C13: call | D13: 6400 | E13: ='Option source'!B220 -> 616.1 | F13: 6760 | G13: 30 | H13: =MAX(IF(C13="call",F13-D13,D13-F13),0) -> 360 | I13: =E13-H13 -> 256.1 | J13: =D13/F13 -> 0.94674556 | K13: 0.38698396 | L13: 0.77964208 | M13: 5.7437399 | N13: ='Option source'!C220 -> 27128652 | O13: ='Option source'!G220 -> 570 | P13: ='Option source'!F220 -> 670 | Q13: Screen passed; indicative | R13: 215
A14: 46281 | B14: GFGV6400OC | C14: put | D14: 6400 | E14: ='Option source'!B714 -> 150.25 | F14: 6760 | G14: 30 | H14: =MAX(IF(C14="call",F14-D14,D14-F14),0) -> 0 | I14: =E14-H14 -> 150.25 | J14: =D14/F14 -> 0.94674556 | K14: 0.4595281 | L14: -0.25193011 | M14: 6.1837276 | N14: ='Option source'!C714 -> 109657352 | O14: ='Option source'!G714 -> 132.99 | P14: ='Option source'!F714 -> 171 | Q14: Screen passed; indicative | R14: 709
A15: 46281 | B15: GFGC7200OC | C15: call | D15: 7200 | E15: ='Option source'!B296 -> 213.18 | F15: 6760 | G15: 30 | H15: =MAX(IF(C15="call",F15-D15,D15-F15),0) -> 0 | I15: =E15-H15 -> 213.18 | J15: =D15/F15 -> 1.0650888 | K15: 0.4172588 | L15: 0.39697005 | M15: 7.4723337 | N15: ='Option source'!C296 -> 147861040 | O15: ='Option source'!G296 -> 181 | P15: ='Option source'!F296 -> 245 | Q15: Screen passed; indicative | R15: 291
A16: 46281 | B16: GFGV7200OC | C16: put | D16: 7200 | E16: ='Option source'!B790 -> 550.35 | F16: 6760 | G16: 30 | H16: =MAX(IF(C16="call",F16-D16,D16-F16),0) -> 440 | I16: =E16-H16 -> 110.35 | J16: =D16/F16 -> 1.0650888 | K16: 0.46356595 | L16: -0.58803493 | M16: 7.5426072 | N16: ='Option source'!C790 -> 10836713 | O16: ='Option source'!G790 -> 521 | P16: ='Option source'!F790 -> 590 | Q16: Screen passed; indicative | R16: 785
A17: 46281 | B17: GFGC6200OC | C17: call | D17: 6200 | E17: ='Option source'!B201 -> 704.74 | F17: 6760 | G17: 30 | H17: =MAX(IF(C17="call",F17-D17,D17-F17),0) -> 560 | I17: =E17-H17 -> 144.74 | J17: =D17/F17 -> 0.91715976 | N17: ='Option source'!C201 -> 13875889 | O17: ='Option source'!G201 -> 700 | P17: ='Option source'!F201 -> 810 | Q17: No stable model IV | R17: 196
A18: 46281 | B18: GFGV6200OC | C18: put | D18: 6200 | E18: ='Option source'!B695 -> 97.41 | F18: 6760 | G18: 30 | H18: =MAX(IF(C18="call",F18-D18,D18-F18),0) -> 0 | I18: =E18-H18 -> 97.41 | J18: =D18/F18 -> 0.91715976 | K18: 0.45889878 | L18: -0.18128332 | M18: 5.1081012 | N18: ='Option source'!C695 -> 54669212 | O18: ='Option source'!G695 -> 83.05 | P18: ='Option source'!F695 -> 117.6 | Q18: Screen passed; indicative | R18: 690
A19: 46281 | B19: GFGC7400OC | C19: call | D19: 7400 | E19: ='Option source'!B315 -> 157.14 | F19: 6760 | G19: 30 | H19: =MAX(IF(C19="call",F19-D19,D19-F19),0) -> 0 | I19: =E19-H19 -> 157.14 | J19: =D19/F19 -> 1.0946746 | K19: 0.42384091 | L19: 0.31534577 | M19: 6.887839 | N19: ='Option source'!C315 -> 192882096 | O19: ='Option source'!G315 -> 111 | P19: ='Option source'!F315 -> 177.99 | Q19: Screen passed; indicative | R19: 310
A20: 46281 | B20: GFGV7400OC | C20: put | D20: 7400 | E20: ='Option source'!B809 -> 677.83 | F20: 6760 | G20: 30 | H20: =MAX(IF(C20="call",F20-D20,D20-F20),0) -> 640 | I20: =E20-H20 -> 37.83 | J20: =D20/F20 -> 1.0946746 | K20: 0.42688101 | L20: -0.68312718 | M20: 6.9020032 | N20: ='Option source'!C809 -> 6190239 | O20: ='Option source'!G809 -> 630.55 | P20: ='Option source'!F809 -> 715.55 | Q20: Screen passed; indicative | R20: 804
A21: 46281 | B21: GFGC6000OC | C21: call | D21: 6000 | E21: ='Option source'!B182 -> 916.41 | F21: 6760 | G21: 30 | H21: =MAX(IF(C21="call",F21-D21,D21-F21),0) -> 760 | I21: =E21-H21 -> 156.41 | J21: =D21/F21 -> 0.88757396 | K21: 0.2984427 | L21: 0.95772446 | M21: 1.746708 | N21: ='Option source'!C182 -> 11611929 | O21: ='Option source'!G182 -> 856.28 | P21: ='Option source'!F182 -> 946.54 | Q21: Screen passed; indicative | R21: 177
A22: 46281 | B22: GFGV6000OC | C22: put | D22: 6000 | E22: ='Option source'!B676 -> 56.82 | F22: 6760 | G22: 30 | H22: =MAX(IF(C22="call",F22-D22,D22-F22),0) -> 0 | I22: =E22-H22 -> 56.82 | J22: =D22/F22 -> 0.88757396 | K22: 0.45172074 | L22: -0.11978268 | M22: 3.871897 | N22: ='Option source'!C676 -> 31602294 | O22: ='Option source'!G676 -> 48.93 | P22: ='Option source'!F676 -> 69.71 | Q22: Screen passed; indicative | R22: 671
A23: 46281 | B23: GFGC7600OC | C23: call | D23: 7600 | E23: ='Option source'!B334 -> 107.66 | F23: 6760 | G23: 30 | H23: =MAX(IF(C23="call",F23-D23,D23-F23),0) -> 0 | I23: =E23-H23 -> 107.66 | J23: =D23/F23 -> 1.1242604 | K23: 0.41897014 | L23: 0.23892342 | M23: 6.0100484 | N23: ='Option source'!C334 -> 235477376 | O23: ='Option source'!G334 -> 95 | P23: ='Option source'!F334 -> 127 | Q23: Screen passed; indicative | R23: 329
A24: 46281 | B24: GFGV7600OC | C24: put | D24: 7600 | E24: ='Option source'!B828 -> 857 | F24: 6760 | G24: 30 | H24: =MAX(IF(C24="call",F24-D24,D24-F24),0) -> 840 | I24: =E24-H24 -> 17 | J24: =D24/F24 -> 1.1242604 | K24: 0.4489615 | L24: -0.74345861 | M24: 6.24282 | N24: ='Option source'!C828 -> 4665704 | O24: ='Option source'!G828 -> 753.12 | P24: ='Option source'!F828 -> 916 | Q24: Screen passed; indicative | R24: 823
A25: 46281 | B25: GFGC5800OC | C25: call | D25: 5800 | E25: ='Option source'!B163 -> 1049.9 | F25: 6760 | G25: 30 | H25: =MAX(IF(C25="call",F25-D25,D25-F25),0) -> 960 | I25: =E25-H25 -> 89.9 | J25: =D25/F25 -> 0.85798817 | N25: ='Option source'!C163 -> 1980739.2 | O25: ='Option source'!G163 -> 1059.3 | P25: ='Option source'!F163 -> 1142.92 | Q25: Price outside daily range | R25: 158
A26: 46281 | B26: GFGV5800OC | C26: put | D26: 5800 | E26: ='Option source'!B657 -> 31.98 | F26: 6760 | G26: 30 | H26: =MAX(IF(C26="call",F26-D26,D26-F26),0) -> 0 | I26: =E26-H26 -> 31.98 | J26: =D26/F26 -> 0.85798817 | K26: 0.45084665 | L26: -0.07487854 | M26: 2.7399995 | N26: ='Option source'!C657 -> 14883324 | O26: ='Option source'!G657 -> 26.55 | P26: ='Option source'!F657 -> 37.89 | Q26: Screen passed; indicative | R26: 652
A27: 46281 | B27: GFGC7800OC | C27: call | D27: 7800 | E27: ='Option source'!B353 -> 75.86 | F27: 6760 | G27: 30 | H27: =MAX(IF(C27="call",F27-D27,D27-F27),0) -> 0 | I27: =E27-H27 -> 75.86 | J27: =D27/F27 -> 1.1538462 | K27: 0.42340313 | L27: 0.18007865 | M27: 5.0867907 | N27: ='Option source'!C353 -> 97534584 | O27: ='Option source'!G353 -> 67.01 | P27: ='Option source'!F353 -> 89.99 | Q27: Screen passed; indicative | R27: 348
A28: 46281 | B28: GFGV7800OC | C28: put | D28: 7800 | E28: ='Option source'!B847 -> 1000 | F28: 6760 | G28: 30 | H28: =MAX(IF(C28="call",F28-D28,D28-F28),0) -> 1040 | I28: =E28-H28 -> -40 | J28: =D28/F28 -> 1.1538462 | N28: ='Option source'!C847 -> 302000 | O28: ='Option source'!G847 -> 1020 | P28: ='Option source'!F847 -> 1020 | Q28: Price outside daily range; Below intrinsic value | R28: 842
A29: 46281 | B29: GFGC5600OC | C29: call | D29: 5600 | E29: ='Option source'!B153 -> 1233.13 | F29: 6760 | G29: 30 | H29: =MAX(IF(C29="call",F29-D29,D29-F29),0) -> 1160 | I29: =E29-H29 -> 73.13 | J29: =D29/F29 -> 0.82840237 | N29: ='Option source'!C153 -> 1870673.8 | O29: ='Option source'!G153 -> 1227.44 | P29: ='Option source'!F153 -> 1335.39 | Q29: No stable model IV | R29: 148
A30: 46281 | B30: GFGV5600OC | C30: put | D30: 5600 | E30: ='Option source'!B638 -> 17.15 | F30: 6760 | G30: 30 | H30: =MAX(IF(C30="call",F30-D30,D30-F30),0) -> 0 | I30: =E30-H30 -> 17.15 | J30: =D30/F30 -> 0.82840237 | K30: 0.45291432 | L30: -0.044129109 | M30: 1.808305 | N30: ='Option source'!C638 -> 7799133.5 | O30: ='Option source'!G638 -> 14.36 | P30: ='Option source'!F638 -> 22.99 | Q30: Screen passed; indicative | R30: 633
A31: 46281 | B31: GFGC8000OC | C31: call | D31: 8000 | E31: ='Option source'!B372 -> 54.71 | F31: 6760 | G31: 30 | H31: =MAX(IF(C31="call",F31-D31,D31-F31),0) -> 0 | I31: =E31-H31 -> 54.71 | J31: =D31/F31 -> 1.183432 | K31: 0.43226054 | L31: 0.13608028 | M31: 4.2308673 | N31: ='Option source'!C372 -> 66091964 | O31: ='Option source'!G372 -> 46.6 | P31: ='Option source'!F372 -> 62.99 | Q31: Screen passed; indicative | R31: 367
A32: 46281 | B32: GFGV8000OC | C32: put | D32: 8000 | E32: ='Option source'!B866 -> 1230 | F32: 6760 | G32: 30 | H32: =MAX(IF(C32="call",F32-D32,D32-F32),0) -> 1240 | I32: =E32-H32 -> -10 | J32: =D32/F32 -> 1.183432 | N32: ='Option source'!C866 -> 0 | O32: ='Option source'!G866 -> 1109 | P32: ='Option source'!F866 -> 1250 | Q32: Zero reported volume; Below intrinsic value | R32: 861
A33: 46281 | B33: GFGC5400OC | C33: call | D33: 5400 | E33: ='Option source'!B135 -> 1470 | F33: 6760 | G33: 30 | H33: =MAX(IF(C33="call",F33-D33,D33-F33),0) -> 1360 | I33: =E33-H33 -> 110 | J33: =D33/F33 -> 0.79881657 | N33: ='Option source'!C135 -> 0 | O33: ='Option source'!G135 -> 1424.19 | P33: ='Option source'!F135 -> 1532.25 | Q33: Zero reported volume | R33: 130
A34: 46281 | B34: GFGV5400OC | C34: put | D34: 5400 | E34: ='Option source'!B619 -> 9.02 | F34: 6760 | G34: 30 | H34: =MAX(IF(C34="call",F34-D34,D34-F34),0) -> 0 | I34: =E34-H34 -> 9.02 | J34: =D34/F34 -> 0.79881657 | K34: 0.45968663 | L34: -0.025148639 | M34: 1.1383264 | N34: ='Option source'!C619 -> 1795599.1 | O34: ='Option source'!G619 -> 7.3 | P34: ='Option source'!F619 -> 12.63 | Q34: Screen passed; indicative | R34: 614
A35: 46281 | B35: GFGC8300OC | C35: call | D35: 8300 | E35: ='Option source'!B391 -> 32.2 | F35: 6760 | G35: 30 | H35: =MAX(IF(C35="call",F35-D35,D35-F35),0) -> 0 | I35: =E35-H35 -> 32.2 | J35: =D35/F35 -> 1.2278107 | K35: 0.44108035 | L35: 0.086163364 | M35: 3.046602 | N35: ='Option source'!C391 -> 26771796 | O35: ='Option source'!G391 -> 27 | P35: ='Option source'!F391 -> 38 | Q35: Screen passed; indicative | R35: 386
A36: 46281 | B36: GFGV8300OC | C36: put | D36: 8300 | E36: ='Option source'!B885 -> 1520 | F36: 6760 | G36: 30 | H36: =MAX(IF(C36="call",F36-D36,D36-F36),0) -> 1540 | I36: =E36-H36 -> -20 | J36: =D36/F36 -> 1.2278107 | N36: ='Option source'!C885 -> 0 | O36: ='Option source'!G885 -> 1520 | P36: ='Option source'!F885 -> 1520 | Q36: Zero reported volume; Below intrinsic value | R36: 880
A37: 46281 | B37: GFGC5200OC | C37: call | D37: 5200 | E37: ='Option source'!B116 -> 1678.07 | F37: 6760 | G37: 30 | H37: =MAX(IF(C37="call",F37-D37,D37-F37),0) -> 1560 | I37: =E37-H37 -> 118.07 | J37: =D37/F37 -> 0.76923077 | N37: ='Option source'!C116 -> 0 | O37: ='Option source'!G116 -> 1653.01 | P37: ='Option source'!F116 -> 1700 | Q37: Zero reported volume | R37: 111
A38: 46281 | B38: GFGV5200OC | C38: put | D38: 5200 | E38: ='Option source'!B600 -> 6.01 | F38: 6760 | G38: 30 | H38: =MAX(IF(C38="call",F38-D38,D38-F38),0) -> 0 | I38: =E38-H38 -> 6.01 | J38: =D38/F38 -> 0.76923077 | K38: 0.48616181 | L38: -0.016627535 | M38: 0.80173253 | N38: ='Option source'!C600 -> 533764.69 | O38: ='Option source'!G600 -> 3.59 | P38: ='Option source'!F600 -> 7.7 | Q38: Screen passed; indicative | R38: 595
A39: 46281 | B39: GFGC5000OC | C39: call | D39: 5000 | E39: ='Option source'!B97 -> 1808.85 | F39: 6760 | G39: 30 | H39: =MAX(IF(C39="call",F39-D39,D39-F39),0) -> 1760 | I39: =E39-H39 -> 48.85 | J39: =D39/F39 -> 0.73964497 | N39: ='Option source'!C97 -> 361770.59 | O39: ='Option source'!G97 -> 0 | P39: ='Option source'!F97 -> 0 | Q39: Price outside daily range | R39: 92
A40: 46281 | B40: GFGV5000OC | C40: put | D40: 5000 | E40: ='Option source'!B581 -> 3.18 | F40: 6760 | G40: 30 | H40: =MAX(IF(C40="call",F40-D40,D40-F40),0) -> 0 | I40: =E40-H40 -> 3.18 | J40: =D40/F40 -> 0.73964497 | K40: 0.49860677 | L40: -0.0092925735 | M40: 0.48444657 | N40: ='Option source'!C581 -> 745490.69 | O40: ='Option source'!G581 -> 2 | P40: ='Option source'!F581 -> 3.99 | Q40: Screen passed; indicative | R40: 576
A41: 46281 | B41: GFGC8600OC | C41: call | D41: 8600 | E41: ='Option source'!B410 -> 17.94 | F41: 6760 | G41: 30 | H41: =MAX(IF(C41="call",F41-D41,D41-F41),0) -> 0 | I41: =E41-H41 -> 17.94 | J41: =D41/F41 -> 1.2721893 | K41: 0.44561207 | L41: 0.051812702 | M41: 2.0562806 | N41: ='Option source'!C410 -> 7674966 | O41: ='Option source'!G410 -> 16 | P41: ='Option source'!F410 -> 24 | Q41: Screen passed; indicative | R41: 405
A42: 46281 | B42: GFGV8600OC | C42: put | D42: 8600 | E42: ='Option source'!B904 -> 1648.65 | F42: 6760 | G42: 30 | H42: =MAX(IF(C42="call",F42-D42,D42-F42),0) -> 1840 | I42: =E42-H42 -> -191.35 | J42: =D42/F42 -> 1.2721893 | N42: ='Option source'!C904 -> 0 | O42: ='Option source'!G904 -> 1648.65 | P42: ='Option source'!F904 -> 1648.65 | Q42: Zero reported volume; Below intrinsic value | R42: 899
A43: 46281 | B43: GFGC4800OC | C43: call | D43: 4800 | E43: ='Option source'!B80 -> 2084.21 | F43: 6760 | G43: 30 | H43: =MAX(IF(C43="call",F43-D43,D43-F43),0) -> 1960 | I43: =E43-H43 -> 124.21 | J43: =D43/F43 -> 0.71005917 | N43: ='Option source'!C80 -> 0 | O43: ='Option source'!G80 -> 2009.47 | P43: ='Option source'!F80 -> 2064.28 | Q43: Zero reported volume; Price outside daily range | R43: 75
A44: 46281 | B44: GFGV4800OC | C44: put | D44: 4800 | E44: ='Option source'!B562 -> 1.93 | F44: 6760 | G44: 30 | H44: =MAX(IF(C44="call",F44-D44,D44-F44),0) -> 0 | I44: =E44-H44 -> 1.93 | J44: =D44/F44 -> 0.71005917 | K44: 0.52122828 | L44: -0.0056849117 | M44: 0.31412311 | N44: ='Option source'!C562 -> 271169.31 | O44: ='Option source'!G562 -> 1.75 | P44: ='Option source'!F562 -> 2.9 | Q44: Screen passed; indicative | R44: 557
A45: 46281 | B45: GFGC8900OC | C45: call | D45: 8900 | E45: ='Option source'!B429 -> 9.99 | F45: 6760 | G45: 30 | H45: =MAX(IF(C45="call",F45-D45,D45-F45),0) -> 0 | I45: =E45-H45 -> 9.99 | J45: =D45/F45 -> 1.316568 | K45: 0.45136295 | L45: 0.030732679 | M45: 1.3453051 | N45: ='Option source'!C429 -> 1861800.1 | O45: ='Option source'!G429 -> 8.01 | P45: ='Option source'!F429 -> 11 | Q45: Screen passed; indicative | R45: 424
A46: 46281 | B46: GFGV8900OC | C46: put | D46: 8900 | E46: ='Option source'!B919 -> 2022.5 | F46: 6760 | G46: 30 | H46: =MAX(IF(C46="call",F46-D46,D46-F46),0) -> 2140 | I46: =E46-H46 -> -117.5 | J46: =D46/F46 -> 1.316568 | N46: ='Option source'!C919 -> 0 | O46: ='Option source'!G919 -> 2022.5 | P46: ='Option source'!F919 -> 2037.67 | Q46: Zero reported volume; Below intrinsic value | R46: 914
A47: 46281 | B47: GFGC4600OC | C47: call | D47: 4600 | E47: ='Option source'!B63 -> 2280.1 | F47: 6760 | G47: 30 | H47: =MAX(IF(C47="call",F47-D47,D47-F47),0) -> 2160 | I47: =E47-H47 -> 120.1 | J47: =D47/F47 -> 0.68047337 | N47: ='Option source'!C63 -> 0 | O47: ='Option source'!G63 -> 2200.39 | P47: ='Option source'!F63 -> 2265.16 | Q47: Zero reported volume; Price outside daily range | R47: 58
A48: 46281 | B48: GFGV4600OC | C48: put | D48: 4600 | E48: ='Option source'!B543 -> 1.62 | F48: 6760 | G48: 30 | H48: =MAX(IF(C48="call",F48-D48,D48-F48),0) -> 0 | I48: =E48-H48 -> 1.62 | J48: =D48/F48 -> 0.68047337 | K48: 0.56450649 | L48: -0.0045009867 | M48: 0.2551514 | N48: ='Option source'!C543 -> 59280.8 | O48: ='Option source'!G543 -> 1.11 | P48: ='Option source'!F543 -> 2.6 | Q48: Screen passed; indicative | R48: 538
A49: 46281 | B49: GFGC4400OC | C49: call | D49: 4400 | E49: ='Option source'!B44 -> 2422 | F49: 6760 | G49: 30 | H49: =MAX(IF(C49="call",F49-D49,D49-F49),0) -> 2360 | I49: =E49-H49 -> 62 | J49: =D49/F49 -> 0.65088757 | N49: ='Option source'!C44 -> 0 | O49: ='Option source'!G44 -> 2391.3 | P49: ='Option source'!F44 -> 2418.17 | Q49: Zero reported volume; Price outside daily range | R49: 39
A50: 46281 | B50: GFGV4400OC | C50: put | D50: 4400 | E50: ='Option source'!B524 -> 0.91 | F50: 6760 | G50: 30 | H50: =MAX(IF(C50="call",F50-D50,D50-F50),0) -> 0 | I50: =E50-H50 -> 0.91 | J50: =D50/F50 -> 0.65088757 | K50: 0.58433588 | L50: -0.0026008019 | M50: 0.15587979 | N50: ='Option source'!C524 -> 174142.09 | O50: ='Option source'!G524 -> 0.9 | P50: ='Option source'!F524 -> 2 | Q50: Screen passed; indicative | R50: 519
A51: 46281 | B51: GFGC9200OC | C51: call | D51: 9200 | E51: ='Option source'!B448 -> 3.53 | F51: 6760 | G51: 30 | H51: =MAX(IF(C51="call",F51-D51,D51-F51),0) -> 0 | I51: =E51-H51 -> 3.53 | J51: =D51/F51 -> 1.3609467 | K51: 0.43028625 | L51: 0.012653848 | M51: 0.63379205 | N51: ='Option source'!C448 -> 825675.38 | O51: ='Option source'!G448 -> 3 | P51: ='Option source'!F448 -> 6.99 | Q51: Screen passed; indicative | R51: 443
A52: 46281 | B52: GFGV9200OC | C52: put | D52: 9200 | E52: ='Option source'!B926 -> 2268.51 | F52: 6760 | G52: 30 | H52: =MAX(IF(C52="call",F52-D52,D52-F52),0) -> 2440 | I52: =E52-H52 -> -171.49 | J52: =D52/F52 -> 1.3609467 | N52: ='Option source'!C926 -> 660601 | O52: ='Option source'!G926 -> 2168.75 | P52: ='Option source'!F926 -> 2168.75 | Q52: Price outside daily range; Below intrinsic value | R52: 921
A53: 46281 | B53: GFGC4200OC | C53: call | D53: 4200 | E53: ='Option source'!B25 -> 2587.49 | F53: 6760 | G53: 30 | H53: =MAX(IF(C53="call",F53-D53,D53-F53),0) -> 2560 | I53: =E53-H53 -> 27.49 | J53: =D53/F53 -> 0.62130178 | N53: ='Option source'!C25 -> 258749 | O53: ='Option source'!G25 -> 0 | P53: ='Option source'!F25 -> 0 | Q53: Price outside daily range | R53: 20
A54: 46281 | B54: GFGV4200OC | C54: put | D54: 4200 | E54: ='Option source'!B505 -> 1.21 | F54: 6760 | G54: 30 | H54: =MAX(IF(C54="call",F54-D54,D54-F54),0) -> 0 | I54: =E54-H54 -> 1.21 | J54: =D54/F54 -> 0.62130178 | K54: 0.65798905 | L54: -0.0029976742 | M54: 0.17719037 | N54: ='Option source'!C505 -> 32093.2 | O54: ='Option source'!G505 -> 0.67 | P54: ='Option source'!F505 -> 1.59 | Q54: Screen passed; indicative | R54: 500
A55: 46281 | B55: GFGC9500OC | C55: call | D55: 9500 | E55: ='Option source'!B467 -> 3.44 | F55: 6760 | G55: 30 | H55: =MAX(IF(C55="call",F55-D55,D55-F55),0) -> 0 | I55: =E55-H55 -> 3.44 | J55: =D55/F55 -> 1.4053254 | K55: 0.46997575 | L55: 0.011451719 | M55: 0.58124231 | N55: ='Option source'!C467 -> 1701123.5 | O55: ='Option source'!G467 -> 3.05 | P55: ='Option source'!F467 -> 4.95 | Q55: Screen passed; indicative | R55: 462
A56: 46281 | B56: GFGC9900OC | C56: call | D56: 9900 | E56: ='Option source'!B486 -> 2.06 | F56: 6760 | G56: 30 | H56: =MAX(IF(C56="call",F56-D56,D56-F56),0) -> 0 | I56: =E56-H56 -> 2.06 | J56: =D56/F56 -> 1.464497 | K56: 0.49155384 | L56: 0.0069124191 | M56: 0.37348865 | N56: ='Option source'!C486 -> 1364921.2 | O56: ='Option source'!G486 -> 1.82 | P56: ='Option source'!F486 -> 2.7 | Q56: Screen passed; indicative | R56: 481
A57: 46280 | B57: GFGC6800OC | C57: call | D57: 6800 | E57: ='Option source'!B257 -> 380.09 | F57: 6725 | G57: 31 | H57: =MAX(IF(C57="call",F57-D57,D57-F57),0) -> 0 | I57: =E57-H57 -> 380.09 | J57: =D57/F57 -> 1.0111524 | K57: 0.42515928 | L57: 0.57067002 | M57: 7.6957415 | N57: ='Option source'!C257 -> 189504416 | O57: ='Option source'!G257 -> 350 | P57: ='Option source'!F257 -> 419.9 | Q57: Screen passed; indicative | R57: 252
A58: 46280 | B58: GFGV6800OC | C58: put | D58: 6800 | E58: ='Option source'!B751 -> 311.72 | F58: 6725 | G58: 31 | H58: =MAX(IF(C58="call",F58-D58,D58-F58),0) -> 75 | I58: =E58-H58 -> 236.72 | J58: =D58/F58 -> 1.0111524 | K58: 0.43554011 | L58: -0.42982291 | M58: 7.6974558 | N58: ='Option source'!C751 -> 177815008 | O58: ='Option source'!G751 -> 286 | P58: ='Option source'!F751 -> 340 | Q58: Screen passed; indicative | R58: 746
A59: 46280 | B59: GFGC6600OC | C59: call | D59: 6600 | E59: ='Option source'!B238 -> 490 | F59: 6725 | G59: 31 | H59: =MAX(IF(C59="call",F59-D59,D59-F59),0) -> 125 | I59: =E59-H59 -> 365 | J59: =D59/F59 -> 0.98141264 | K59: 0.42374678 | L59: 0.66275744 | M59: 7.1586629 | N59: ='Option source'!C238 -> 51367756 | O59: ='Option source'!G238 -> 450 | P59: ='Option source'!F238 -> 536.65 | Q59: Screen passed; indicative | R59: 233
A60: 46280 | B60: GFGV6600OC | C60: put | D60: 6600 | E60: ='Option source'!B732 -> 220.68 | F60: 6725 | G60: 31 | H60: =MAX(IF(C60="call",F60-D60,D60-F60),0) -> 0 | I60: =E60-H60 -> 220.68 | J60: =D60/F60 -> 0.98141264 | K60: 0.43720596 | L60: -0.34056084 | M60: 7.1856821 | N60: ='Option source'!C732 -> 232898432 | O60: ='Option source'!G732 -> 184.95 | P60: ='Option source'!F732 -> 249 | Q60: Screen passed; indicative | R60: 727
A61: 46280 | B61: GFGC7000OC | C61: call | D61: 7000 | E61: ='Option source'!B276 -> 277.07 | F61: 6725 | G61: 31 | H61: =MAX(IF(C61="call",F61-D61,D61-F61),0) -> 0 | I61: =E61-H61 -> 277.07 | J61: =D61/F61 -> 1.0408922 | K61: 0.411771 | L61: 0.47541971 | M61: 7.8038943 | N61: ='Option source'!C276 -> 418205024 | O61: ='Option source'!G276 -> 260 | P61: ='Option source'!F276 -> 315 | Q61: Screen passed; indicative | R61: 271
A62: 46280 | B62: GFGV7000OC | C62: put | D62: 7000 | E62: ='Option source'!B770 -> 418.29 | F62: 6725 | G62: 31 | H62: =MAX(IF(C62="call",F62-D62,D62-F62),0) -> 275 | I62: =E62-H62 -> 143.29 | J62: =D62/F62 -> 1.0408922 | K62: 0.42724476 | L62: -0.52192755 | M62: 7.8069265 | N62: ='Option source'!C770 -> 127203152 | O62: ='Option source'!G770 -> 382.99 | P62: ='Option source'!F770 -> 453.97 | Q62: Screen passed; indicative | R62: 765
A63: 46280 | B63: GFGC6400OC | C63: call | D63: 6400 | E63: ='Option source'!B219 -> 600.2 | F63: 6725 | G63: 31 | H63: =MAX(IF(C63="call",F63-D63,D63-F63),0) -> 325 | I63: =E63-H63 -> 275.2 | J63: =D63/F63 -> 0.95167286 | K63: 0.39295603 | L63: 0.7618569 | M63: 6.0668894 | N63: ='Option source'!C219 -> 52725424 | O63: ='Option source'!G219 -> 580 | P63: ='Option source'!F219 -> 675.13 | Q63: Screen passed; indicative | R63: 214
A64: 46280 | B64: GFGV6400OC | C64: put | D64: 6400 | E64: ='Option source'!B713 -> 151.43 | F64: 6725 | G64: 31 | H64: =MAX(IF(C64="call",F64-D64,D64-F64),0) -> 0 | I64: =E64-H64 -> 151.43 | J64: =D64/F64 -> 0.95167286 | K64: 0.44063737 | L64: -0.25837746 | M64: 6.3365906 | N64: ='Option source'!C713 -> 154461408 | O64: ='Option source'!G713 -> 130.15 | P64: ='Option source'!F713 -> 172 | Q64: Screen passed; indicative | R64: 708
A65: 46280 | B65: GFGC7200OC | C65: call | D65: 7200 | E65: ='Option source'!B295 -> 205.53 | F65: 6725 | G65: 31 | H65: =MAX(IF(C65="call",F65-D65,D65-F65),0) -> 0 | I65: =E65-H65 -> 205.53 | J65: =D65/F65 -> 1.070632 | K65: 0.41582764 | L65: 0.38501444 | M65: 7.4916788 | N65: ='Option source'!C295 -> 191148784 | O65: ='Option source'!G295 -> 187.08 | P65: ='Option source'!F295 -> 260 | Q65: Screen passed; indicative | R65: 290
A66: 46280 | B66: GFGV7200OC | C66: put | D66: 7200 | E66: ='Option source'!B789 -> 542 | F66: 6725 | G66: 31 | H66: =MAX(IF(C66="call",F66-D66,D66-F66),0) -> 475 | I66: =E66-H66 -> 67 | J66: =D66/F66 -> 1.070632 | K66: 0.41087568 | L66: -0.61688594 | M66: 7.4806981 | N66: ='Option source'!C789 -> 51121128 | O66: ='Option source'!G789 -> 495 | P66: ='Option source'!F789 -> 590 | Q66: Screen passed; indicative | R66: 784
A67: 46280 | B67: GFGC6200OC | C67: call | D67: 6200 | E67: ='Option source'!B200 -> 757.6 | F67: 6725 | G67: 31 | H67: =MAX(IF(C67="call",F67-D67,D67-F67),0) -> 525 | I67: =E67-H67 -> 232.6 | J67: =D67/F67 -> 0.92193309 | K67: 0.40856139 | L67: 0.83051147 | M67: 4.9499391 | N67: ='Option source'!C200 -> 13415150 | O67: ='Option source'!G200 -> 730 | P67: ='Option source'!F200 -> 822.13 | Q67: Screen passed; indicative | R67: 195
A68: 46280 | B68: GFGV6200OC | C68: put | D68: 6200 | E68: ='Option source'!B694 -> 97.24 | F68: 6725 | G68: 31 | H68: =MAX(IF(C68="call",F68-D68,D68-F68),0) -> 0 | I68: =E68-H68 -> 97.24 | J68: =D68/F68 -> 0.92193309 | K68: 0.44021782 | L68: -0.1850404 | M68: 5.2321737 | N68: ='Option source'!C694 -> 62372620 | O68: ='Option source'!G694 -> 80 | P68: ='Option source'!F694 -> 112 | Q68: Screen passed; indicative | R68: 689
A69: 46280 | B69: GFGC7400OC | C69: call | D69: 7400 | E69: ='Option source'!B314 -> 148.96 | F69: 6725 | G69: 31 | H69: =MAX(IF(C69="call",F69-D69,D69-F69),0) -> 0 | I69: =E69-H69 -> 148.96 | J69: =D69/F69 -> 1.1003717 | K69: 0.41847946 | L69: 0.30349518 | M69: 6.8498926 | N69: ='Option source'!C314 -> 138135056 | O69: ='Option source'!G314 -> 134.4 | P69: ='Option source'!F314 -> 180 | Q69: Screen passed; indicative | R69: 309
A70: 46280 | B70: GFGV7400OC | C70: put | D70: 7400 | E70: ='Option source'!B808 -> 663.54 | F70: 6725 | G70: 31 | H70: =MAX(IF(C70="call",F70-D70,D70-F70),0) -> 675 | I70: =E70-H70 -> -11.46 | J70: =D70/F70 -> 1.1003717 | N70: ='Option source'!C808 -> 42596096 | O70: ='Option source'!G808 -> 649.5 | P70: ='Option source'!F808 -> 721.1 | Q70: Below intrinsic value | R70: 803
A71: 46280 | B71: GFGC6000OC | C71: call | D71: 6000 | E71: ='Option source'!B181 -> 930 | F71: 6725 | G71: 31 | H71: =MAX(IF(C71="call",F71-D71,D71-F71),0) -> 725 | I71: =E71-H71 -> 205 | J71: =D71/F71 -> 0.89219331 | K71: 0.43413027 | L71: 0.87824816 | M71: 3.9607202 | N71: ='Option source'!C181 -> 2821693.2 | O71: ='Option source'!G181 -> 890 | P71: ='Option source'!F181 -> 990 | Q71: Screen passed; indicative | R71: 176
A72: 46280 | B72: GFGV6000OC | C72: put | D72: 6000 | E72: ='Option source'!B675 -> 59.49 | F72: 6725 | G72: 31 | H72: =MAX(IF(C72="call",F72-D72,D72-F72),0) -> 0 | I72: =E72-H72 -> 59.49 | J72: =D72/F72 -> 0.89219331 | K72: 0.44176461 | L72: -0.12541727 | M72: 4.0438555 | N72: ='Option source'!C675 -> 67548216 | O72: ='Option source'!G675 -> 47 | P72: ='Option source'!F675 -> 68 | Q72: Screen passed; indicative | R72: 670
A73: 46280 | B73: GFGC7600OC | C73: call | D73: 7600 | E73: ='Option source'!B333 -> 106.1 | F73: 6725 | G73: 31 | H73: =MAX(IF(C73="call",F73-D73,D73-F73),0) -> 0 | I73: =E73-H73 -> 106.1 | J73: =D73/F73 -> 1.1301115 | K73: 0.42121599 | L73: 0.23346436 | M73: 6.0008791 | N73: ='Option source'!C333 -> 340337472 | O73: ='Option source'!G333 -> 95.1 | P73: ='Option source'!F333 -> 130 | Q73: Screen passed; indicative | R73: 328
A74: 46280 | B74: GFGV7600OC | C74: put | D74: 7600 | E74: ='Option source'!B827 -> 860.85 | F74: 6725 | G74: 31 | H74: =MAX(IF(C74="call",F74-D74,D74-F74),0) -> 875 | I74: =E74-H74 -> -14.15 | J74: =D74/F74 -> 1.1301115 | N74: ='Option source'!C827 -> 1079927 | O74: ='Option source'!G827 -> 799.5 | P74: ='Option source'!F827 -> 879.55 | Q74: Below intrinsic value | R74: 822
A75: 46280 | B75: GFGC5800OC | C75: call | D75: 5800 | E75: ='Option source'!B162 -> 1198.65 | F75: 6725 | G75: 31 | H75: =MAX(IF(C75="call",F75-D75,D75-F75),0) -> 925 | I75: =E75-H75 -> 273.65 | J75: =D75/F75 -> 0.86245353 | N75: ='Option source'!C162 -> 0 | O75: ='Option source'!G162 -> 1163.54 | P75: ='Option source'!F162 -> 1337.15 | Q75: Zero reported volume | R75: 157
A76: 46280 | B76: GFGV5800OC | C76: put | D76: 5800 | E76: ='Option source'!B656 -> 32.86 | F76: 6725 | G76: 31 | H76: =MAX(IF(C76="call",F76-D76,D76-F76),0) -> 0 | I76: =E76-H76 -> 32.86 | J76: =D76/F76 -> 0.86245353 | K76: 0.43872429 | L76: -0.077724605 | M76: 2.8506585 | N76: ='Option source'!C656 -> 20763368 | O76: ='Option source'!G656 -> 28 | P76: ='Option source'!F656 -> 39.5 | Q76: Screen passed; indicative | R76: 651
A77: 46280 | B77: GFGC7800OC | C77: call | D77: 7800 | E77: ='Option source'!B352 -> 74.96 | F77: 6725 | G77: 31 | H77: =MAX(IF(C77="call",F77-D77,D77-F77),0) -> 0 | I77: =E77-H77 -> 74.96 | J77: =D77/F77 -> 1.1598513 | K77: 0.42512836 | L77: 0.17636361 | M77: 5.07696 | N77: ='Option source'!C352 -> 103323992 | O77: ='Option source'!G352 -> 67.03 | P77: ='Option source'!F352 -> 95 | Q77: Screen passed; indicative | R77: 347
A78: 46280 | B78: GFGV7800OC | C78: put | D78: 7800 | E78: ='Option source'!B846 -> 1064.72 | F78: 6725 | G78: 31 | H78: =MAX(IF(C78="call",F78-D78,D78-F78),0) -> 1075 | I78: =E78-H78 -> -10.28 | J78: =D78/F78 -> 1.1598513 | N78: ='Option source'!C846 -> 2107901.5 | O78: ='Option source'!G846 -> 967.62 | P78: ='Option source'!F846 -> 1088.22 | Q78: Below intrinsic value | R78: 841
A79: 46280 | B79: GFGC5600OC | C79: call | D79: 5600 | E79: ='Option source'!B152 -> 1455 | F79: 6725 | G79: 31 | H79: =MAX(IF(C79="call",F79-D79,D79-F79),0) -> 1125 | I79: =E79-H79 -> 330 | J79: =D79/F79 -> 0.83271375 | N79: ='Option source'!C152 -> 0 | O79: ='Option source'!G152 -> 1455 | P79: ='Option source'!F152 -> 1455 | Q79: Zero reported volume | R79: 147
A80: 46280 | B80: GFGV5600OC | C80: put | D80: 5600 | E80: ='Option source'!B637 -> 17.76 | F80: 6725 | G80: 31 | H80: =MAX(IF(C80="call",F80-D80,D80-F80),0) -> 0 | I80: =E80-H80 -> 17.76 | J80: =D80/F80 -> 0.83271375 | K80: 0.44199418 | L80: -0.046147794 | M80: 1.8956985 | N80: ='Option source'!C637 -> 6115640 | O80: ='Option source'!G637 -> 15 | P80: ='Option source'!F637 -> 21.42 | Q80: Screen passed; indicative | R80: 632
A81: 46280 | B81: GFGC8000OC | C81: call | D81: 8000 | E81: ='Option source'!B371 -> 53.36 | F81: 6725 | G81: 31 | H81: =MAX(IF(C81="call",F81-D81,D81-F81),0) -> 0 | I81: =E81-H81 -> 53.36 | J81: =D81/F81 -> 1.1895911 | K81: 0.43146371 | L81: 0.13238617 | M81: 4.1984177 | N81: ='Option source'!C371 -> 111552832 | O81: ='Option source'!G371 -> 48.9 | P81: ='Option source'!F371 -> 72.1 | Q81: Screen passed; indicative | R81: 366
A82: 46280 | B82: GFGV8000OC | C82: put | D82: 8000 | E82: ='Option source'!B865 -> 1230 | F82: 6725 | G82: 31 | H82: =MAX(IF(C82="call",F82-D82,D82-F82),0) -> 1275 | I82: =E82-H82 -> -45 | J82: =D82/F82 -> 1.1895911 | N82: ='Option source'!C865 -> 21339940 | O82: ='Option source'!G865 -> 1109 | P82: ='Option source'!F865 -> 1250 | Q82: Below intrinsic value | R82: 860
A83: 46280 | B83: GFGC5400OC | C83: call | D83: 5400 | E83: ='Option source'!B134 -> 1470 | F83: 6725 | G83: 31 | H83: =MAX(IF(C83="call",F83-D83,D83-F83),0) -> 1325 | I83: =E83-H83 -> 145 | J83: =D83/F83 -> 0.80297398 | K83: 0.4481931 | L83: 0.97383151 | M83: 1.1901049 | N83: ='Option source'!C134 -> 11837598 | O83: ='Option source'!G134 -> 1424.19 | P83: ='Option source'!F134 -> 1532.25 | Q83: Screen passed; indicative | R83: 129
A84: 46280 | B84: GFGV5400OC | C84: put | D84: 5400 | E84: ='Option source'!B618 -> 9.9 | F84: 6725 | G84: 31 | H84: =MAX(IF(C84="call",F84-D84,D84-F84),0) -> 0 | I84: =E84-H84 -> 9.9 | J84: =D84/F84 -> 0.80297398 | K84: 0.45224757 | L84: -0.027169005 | M84: 1.2279928 | N84: ='Option source'!C618 -> 1908707.1 | O84: ='Option source'!G618 -> 8 | P84: ='Option source'!F618 -> 11.38 | Q84: Screen passed; indicative | R84: 613
A85: 46280 | B85: GFGC5200OC | C85: call | D85: 5200 | E85: ='Option source'!B115 -> 1678.07 | F85: 6725 | G85: 31 | H85: =MAX(IF(C85="call",F85-D85,D85-F85),0) -> 1525 | I85: =E85-H85 -> 153.07 | J85: =D85/F85 -> 0.7732342 | K85: 0.59721135 | L85: 0.95646317 | M85: 1.8088547 | N85: ='Option source'!C115 -> 503108.09 | O85: ='Option source'!G115 -> 1653.01 | P85: ='Option source'!F115 -> 1700 | Q85: Screen passed; indicative | R85: 110
A86: 46280 | B86: GFGV5200OC | C86: put | D86: 5200 | E86: ='Option source'!B599 -> 5.46 | F86: 6725 | G86: 31 | H86: =MAX(IF(C86="call",F86-D86,D86-F86),0) -> 0 | I86: =E86-H86 -> 5.46 | J86: =D86/F86 -> 0.7732342 | K86: 0.46526349 | L86: -0.015683641 | M86: 0.77116674 | N86: ='Option source'!C599 -> 812441.62 | O86: ='Option source'!G599 -> 3.7 | P86: ='Option source'!F599 -> 6.64 | Q86: Screen passed; indicative | R86: 594
A87: 46280 | B87: GFGC8300OC | C87: call | D87: 8300 | E87: ='Option source'!B390 -> 31.45 | F87: 6725 | G87: 31 | H87: =MAX(IF(C87="call",F87-D87,D87-F87),0) -> 0 | I87: =E87-H87 -> 31.45 | J87: =D87/F87 -> 1.2342007 | K87: 0.43973148 | L87: 0.083932242 | M87: 3.0209384 | N87: ='Option source'!C390 -> 22569552 | O87: ='Option source'!G390 -> 27.21 | P87: ='Option source'!F390 -> 47 | Q87: Screen passed; indicative | R87: 385
A88: 46280 | B88: GFGV8300OC | C88: put | D88: 8300 | E88: ='Option source'!B884 -> 1520 | F88: 6725 | G88: 31 | H88: =MAX(IF(C88="call",F88-D88,D88-F88),0) -> 1575 | I88: =E88-H88 -> -55 | J88: =D88/F88 -> 1.2342007 | N88: ='Option source'!C884 -> 760000 | O88: ='Option source'!G884 -> 1520 | P88: ='Option source'!F884 -> 1520 | Q88: Below intrinsic value | R88: 879
A89: 46280 | B89: GFGC5000OC | C89: call | D89: 5000 | E89: ='Option source'!B96 -> 1851 | F89: 6725 | G89: 31 | H89: =MAX(IF(C89="call",F89-D89,D89-F89),0) -> 1725 | I89: =E89-H89 -> 126 | J89: =D89/F89 -> 0.74349442 | N89: ='Option source'!C96 -> 2212747.2 | O89: ='Option source'!G96 -> 1840.71 | P89: ='Option source'!F96 -> 1848.45 | Q89: Price outside daily range | R89: 91
A90: 46280 | B90: GFGV5000OC | C90: put | D90: 5000 | E90: ='Option source'!B580 -> 3.46 | F90: 6725 | G90: 31 | H90: =MAX(IF(C90="call",F90-D90,D90-F90),0) -> 0 | I90: =E90-H90 -> 3.46 | J90: =D90/F90 -> 0.74349442 | K90: 0.48967189 | L90: -0.0099861757 | M90: 0.5217163 | N90: ='Option source'!C580 -> 1247591.5 | O90: ='Option source'!G580 -> 2.42 | P90: ='Option source'!F580 -> 4.35 | Q90: Screen passed; indicative | R90: 575
A91: 46280 | B91: GFGC8600OC | C91: call | D91: 8600 | E91: ='Option source'!B409 -> 19.15 | F91: 6725 | G91: 31 | H91: =MAX(IF(C91="call",F91-D91,D91-F91),0) -> 0 | I91: =E91-H91 -> 19.15 | J91: =D91/F91 -> 1.2788104 | K91: 0.45150603 | L91: 0.053743648 | M91: 2.1406997 | N91: ='Option source'!C409 -> 16742308 | O91: ='Option source'!G409 -> 17 | P91: ='Option source'!F409 -> 25 | Q91: Screen passed; indicative | R91: 404
A92: 46280 | B92: GFGV8600OC | C92: put | D92: 8600 | E92: ='Option source'!B903 -> 1648.65 | F92: 6725 | G92: 31 | H92: =MAX(IF(C92="call",F92-D92,D92-F92),0) -> 1875 | I92: =E92-H92 -> -226.35 | J92: =D92/F92 -> 1.2788104 | N92: ='Option source'!C903 -> 164865 | O92: ='Option source'!G903 -> 0 | P92: ='Option source'!F903 -> 0 | Q92: Price outside daily range; Below intrinsic value | R92: 898
A93: 46280 | B93: GFGC4800OC | C93: call | D93: 4800 | E93: ='Option source'!B79 -> 2084.21 | F93: 6725 | G93: 31 | H93: =MAX(IF(C93="call",F93-D93,D93-F93),0) -> 1925 | I93: =E93-H93 -> 159.21 | J93: =D93/F93 -> 0.71375465 | N93: ='Option source'!C79 -> 18354320 | O93: ='Option source'!G79 -> 2009.47 | P93: ='Option source'!F79 -> 2064.28 | Q93: Price outside daily range | R93: 74
A94: 46280 | B94: GFGV4800OC | C94: put | D94: 4800 | E94: ='Option source'!B561 -> 2.64 | F94: 6725 | G94: 31 | H94: =MAX(IF(C94="call",F94-D94,D94-F94),0) -> 0 | I94: =E94-H94 -> 2.64 | J94: =D94/F94 -> 0.71375465 | K94: 0.52642344 | L94: -0.0073264921 | M94: 0.39758909 | N94: ='Option source'!C561 -> 235711.3 | O94: ='Option source'!G561 -> 1.5 | P94: ='Option source'!F561 -> 3.7 | Q94: Screen passed; indicative | R94: 556
A95: 46280 | B95: GFGC4600OC | C95: call | D95: 4600 | E95: ='Option source'!B62 -> 2280.1 | F95: 6725 | G95: 31 | H95: =MAX(IF(C95="call",F95-D95,D95-F95),0) -> 2125 | I95: =E95-H95 -> 155.1 | J95: =D95/F95 -> 0.68401487 | N95: ='Option source'!C62 -> 27287726 | O95: ='Option source'!G62 -> 2200.39 | P95: ='Option source'!F62 -> 2265.16 | Q95: Price outside daily range | R95: 57
A96: 46280 | B96: GFGV4600OC | C96: put | D96: 4600 | E96: ='Option source'!B542 -> 1.8 | F96: 6725 | G96: 31 | H96: =MAX(IF(C96="call",F96-D96,D96-F96),0) -> 0 | I96: =E96-H96 -> 1.8 | J96: =D96/F96 -> 0.68401487 | K96: 0.55632046 | L96: -0.004930645 | M96: 0.27988729 | N96: ='Option source'!C542 -> 192004.59 | O96: ='Option source'!G542 -> 1 | P96: ='Option source'!F542 -> 2 | Q96: Screen passed; indicative | R96: 537
A97: 46280 | B97: GFGC8900OC | C97: call | D97: 8900 | E97: ='Option source'!B428 -> 9.81 | F97: 6725 | G97: 31 | H97: =MAX(IF(C97="call",F97-D97,D97-F97),0) -> 0 | I97: =E97-H97 -> 9.81 | J97: =D97/F97 -> 1.3234201 | K97: 0.44937696 | L97: 0.030077009 | M97: 1.3363699 | N97: ='Option source'!C428 -> 3391931.8 | O97: ='Option source'!G428 -> 9 | P97: ='Option source'!F428 -> 13 | Q97: Screen passed; indicative | R97: 423
A98: 46280 | B98: GFGV8900OC | C98: put | D98: 8900 | E98: ='Option source'!B918 -> 2022.5 | F98: 6725 | G98: 31 | H98: =MAX(IF(C98="call",F98-D98,D98-F98),0) -> 2175 | I98: =E98-H98 -> -152.5 | J98: =D98/F98 -> 1.3234201 | N98: ='Option source'!C918 -> 0 | O98: ='Option source'!G918 -> 2022.5 | P98: ='Option source'!F918 -> 2037.67 | Q98: Zero reported volume; Below intrinsic value | R98: 913
A99: 46280 | B99: GFGC4400OC | C99: call | D99: 4400 | E99: ='Option source'!B43 -> 2422 | F99: 6725 | G99: 31 | H99: =MAX(IF(C99="call",F99-D99,D99-F99),0) -> 2325 | I99: =E99-H99 -> 97 | J99: =D99/F99 -> 0.65427509 | N99: ='Option source'!C43 -> 1446295 | O99: ='Option source'!G43 -> 2391.3 | P99: ='Option source'!F43 -> 2418.17 | Q99: Price outside daily range | R99: 38
A100: 46280 | B100: GFGV4400OC | C100: put | D100: 4400 | E100: ='Option source'!B523 -> 1.71 | F100: 6725 | G100: 31 | H100: =MAX(IF(C100="call",F100-D100,D100-F100),0) -> 0 | I100: =E100-H100 -> 1.71 | J100: =D100/F100 -> 0.65427509 | N100: ='Option source'!C523 -> 288556.09 | O100: ='Option source'!G523 -> 0.71 | P100: ='Option source'!F523 -> 1.7 | Q100: Price outside daily range | R100: 518
A101: 46280 | B101: GFGC9200OC | C101: call | D101: 9200 | E101: ='Option source'!B447 -> 5.93 | F101: 6725 | G101: 31 | H101: =MAX(IF(C101="call",F101-D101,D101-F101),0) -> 0 | I101: =E101-H101 -> 5.93 | J101: =D101/F101 -> 1.3680297 | K101: 0.4604464 | L101: 0.018838775 | M101: 0.90191359 | N101: ='Option source'!C447 -> 1086758.4 | O101: ='Option source'!G447 -> 5.8 | P101: ='Option source'!F447 -> 7.9 | Q101: Screen passed; indicative | R101: 442
A102: 46280 | B102: GFGV9200OC | C102: put | D102: 9200 | E102: ='Option source'!B925 -> 2041.57 | F102: 6725 | G102: 31 | H102: =MAX(IF(C102="call",F102-D102,D102-F102),0) -> 2475 | I102: =E102-H102 -> -433.43 | J102: =D102/F102 -> 1.3680297 | N102: ='Option source'!C925 -> 0 | O102: ='Option source'!G925 -> 2041.57 | P102: ='Option source'!F925 -> 2041.57 | Q102: Zero reported volume; Below intrinsic value | R102: 920
A103: 46280 | B103: GFGC4200OC | C103: call | D103: 4200 | E103: ='Option source'!B24 -> 2597.16 | F103: 6725 | G103: 31 | H103: =MAX(IF(C103="call",F103-D103,D103-F103),0) -> 2525 | I103: =E103-H103 -> 72.16 | J103: =D103/F103 -> 0.62453532 | N103: ='Option source'!C24 -> 2869639.2 | O103: ='Option source'!G24 -> 2597.16 | P103: ='Option source'!F24 -> 2663.71 | Q103: No stable model IV | R103: 19
...

Sheet Strategies
A2: Butterflies and 1x2 ratio spreads
A4: Indicative PPI prices only. Expiration P&L excludes costs and early assignment. 1x2 calls have unlimited upside loss.
A6: Date | B6: Strategy | C6: Type | D6: Long strike 1 | E6: Short strike 2 (x2) | F6: Long strike 3 | G6: Premium 1 | H6: Premium 2 | I6: Premium 3 | J6: Net debit / share | K6: Strike width | L6: Peak P&L / share | M6: Max loss / share | N6: Lower breakeven | O6: Upper breakeven | P6: Peak / debit | Q6: Net debit / set | R6: Data status | S6: Long leg source | T6: Short leg source
A7: 46281 | B7: Butterfly | C7: call | D7: 6600 | E7: 6800 | F7: 7000 | G7: ='Option source'!B239 -> 478.22 | H7: ='Option source'!B258 -> 376.43 | I7: ='Option source'!B277 -> 289.65 | J7: =G7-2*H7+IF(B7="Butterfly",I7,0) -> 15.01 | K7: =ABS(E7-D7) -> 200 | L7: =K7-J7 -> 184.99 | M7: =IF(B7="Butterfly",MAX(J7,0),IF(C7="call","Unlimited",MAX(2*E7-D7+J7,J7,0))) -> 15.01 | N7: =IF(B7="Butterfly",IF(AND(J7>0,J7<K7),D7+J7,"n.a."),IF(C7="call",IF(AND(J7>0,J7<K7),D7+J7,"n.a."),IF(AND(K7>J7,2*E7-D7+J7>=0),2*E7-D7+J7,"n.a."))) -> 6615.01 | O7: =IF(B7="Butterfly",IF(AND(J7>0,J7<K7),F7-J7,"n.a."),IF(C7="call",IF(K7>J7,2*E7-D7-J7,"n.a."),IF(AND(J7>0,J7<K7),D7-J7,"n.a."))) -> 6984.99 | P7: =IF(AND(B7="Butterfly",J7>0,J7<K7),L7/J7,"n.a.") -> 12.32445 | Q7: =J7*'Model inputs'!$B$8 -> 1501 | R7: Indicative only | S7: 234 | T7: 253
A8: 46281 | B8: Butterfly | C8: put | D8: 6600 | E8: 6800 | F8: 7000 | G8: ='Option source'!B733 -> 222.45 | H8: ='Option source'!B752 -> 312.15 | I8: ='Option source'!B771 -> 427.03 | J8: =G8-2*H8+IF(B8="Butterfly",I8,0) -> 25.18 | K8: =ABS(E8-D8) -> 200 | L8: =K8-J8 -> 174.82 | M8: =IF(B8="Butterfly",MAX(J8,0),IF(C8="call","Unlimited",MAX(2*E8-D8+J8,J8,0))) -> 25.18 | N8: =IF(B8="Butterfly",IF(AND(J8>0,J8<K8),D8+J8,"n.a."),IF(C8="call",IF(AND(J8>0,J8<K8),D8+J8,"n.a."),IF(AND(K8>J8,2*E8-D8+J8>=0),2*E8-D8+J8,"n.a."))) -> 6625.18 | O8: =IF(B8="Butterfly",IF(AND(J8>0,J8<K8),F8-J8,"n.a."),IF(C8="call",IF(K8>J8,2*E8-D8-J8,"n.a."),IF(AND(J8>0,J8<K8),D8-J8,"n.a."))) -> 6974.82 | P8: =IF(AND(B8="Butterfly",J8>0,J8<K8),L8/J8,"n.a.") -> 6.9428118 | Q8: =J8*'Model inputs'!$B$8 -> 2518 | R8: Indicative only | S8: 728 | T8: 747
A9: 46281 | B9: Butterfly | C9: call | D9: 6400 | E9: 6600 | F9: 6800 | G9: ='Option source'!B220 -> 616.1 | H9: ='Option source'!B239 -> 478.22 | I9: ='Option source'!B258 -> 376.43 | J9: =G9-2*H9+IF(B9="Butterfly",I9,0) -> 36.09 | K9: =ABS(E9-D9) -> 200 | L9: =K9-J9 -> 163.91 | M9: =IF(B9="Butterfly",MAX(J9,0),IF(C9="call","Unlimited",MAX(2*E9-D9+J9,J9,0))) -> 36.09 | N9: =IF(B9="Butterfly",IF(AND(J9>0,J9<K9),D9+J9,"n.a."),IF(C9="call",IF(AND(J9>0,J9<K9),D9+J9,"n.a."),IF(AND(K9>J9,2*E9-D9+J9>=0),2*E9-D9+J9,"n.a."))) -> 6436.09 | O9: =IF(B9="Butterfly",IF(AND(J9>0,J9<K9),F9-J9,"n.a."),IF(C9="call",IF(K9>J9,2*E9-D9-J9,"n.a."),IF(AND(J9>0,J9<K9),D9-J9,"n.a."))) -> 6763.91 | P9: =IF(AND(B9="Butterfly",J9>0,J9<K9),L9/J9,"n.a.") -> 4.5417013 | Q9: =J9*'Model inputs'!$B$8 -> 3609 | R9: Indicative only | S9: 215 | T9: 234
A10: 46281 | B10: Butterfly | C10: put | D10: 6400 | E10: 6600 | F10: 6800 | G10: ='Option source'!B714 -> 150.25 | H10: ='Option source'!B733 -> 222.45 | I10: ='Option source'!B752 -> 312.15 | J10: =G10-2*H10+IF(B10="Butterfly",I10,0) -> 17.5 | K10: =ABS(E10-D10) -> 200 | L10: =K10-J10 -> 182.5 | M10: =IF(B10="Butterfly",MAX(J10,0),IF(C10="call","Unlimited",MAX(2*E10-D10+J10,J10,0))) -> 17.5 | N10: =IF(B10="Butterfly",IF(AND(J10>0,J10<K10),D10+J10,"n.a."),IF(C10="call",IF(AND(J10>0,J10<K10),D10+J10,"n.a."),IF(AND(K10>J10,2*E10-D10+J10>=0),2*E10-D10+J10,"n.a."))) -> 6417.5 | O10: =IF(B10="Butterfly",IF(AND(J10>0,J10<K10),F10-J10,"n.a."),IF(C10="call",IF(K10>J10,2*E10-D10-J10,"n.a."),IF(AND(J10>0,J10<K10),D10-J10,"n.a."))) -> 6782.5 | P10: =IF(AND(B10="Butterfly",J10>0,J10<K10),L10/J10,"n.a.") -> 10.428571 | Q10: =J10*'Model inputs'!$B$8 -> 1750 | R10: Indicative only | S10: 709 | T10: 728
A11: 46281 | B11: Butterfly | C11: call | D11: 6800 | E11: 7000 | F11: 7200 | G11: ='Option source'!B258 -> 376.43 | H11: ='Option source'!B277 -> 289.65 | I11: ='Option source'!B296 -> 213.18 | J11: =G11-2*H11+IF(B11="Butterfly",I11,0) -> 10.31 | K11: =ABS(E11-D11) -> 200 | L11: =K11-J11 -> 189.69 | M11: =IF(B11="Butterfly",MAX(J11,0),IF(C11="call","Unlimited",MAX(2*E11-D11+J11,J11,0))) -> 10.31 | N11: =IF(B11="Butterfly",IF(AND(J11>0,J11<K11),D11+J11,"n.a."),IF(C11="call",IF(AND(J11>0,J11<K11),D11+J11,"n.a."),IF(AND(K11>J11,2*E11-D11+J11>=0),2*E11-D11+J11,"n.a."))) -> 6810.31 | O11: =IF(B11="Butterfly",IF(AND(J11>0,J11<K11),F11-J11,"n.a."),IF(C11="call",IF(K11>J11,2*E11-D11-J11,"n.a."),IF(AND(J11>0,J11<K11),D11-J11,"n.a."))) -> 7189.69 | P11: =IF(AND(B11="Butterfly",J11>0,J11<K11),L11/J11,"n.a.") -> 18.398642 | Q11: =J11*'Model inputs'!$B$8 -> 1031 | R11: Indicative only | S11: 253 | T11: 272
A12: 46281 | B12: Butterfly | C12: put | D12: 6800 | E12: 7000 | F12: 7200 | G12: ='Option source'!B752 -> 312.15 | H12: ='Option source'!B771 -> 427.03 | I12: ='Option source'!B790 -> 550.35 | J12: =G12-2*H12+IF(B12="Butterfly",I12,0) -> 8.44 | K12: =ABS(E12-D12) -> 200 | L12: =K12-J12 -> 191.56 | M12: =IF(B12="Butterfly",MAX(J12,0),IF(C12="call","Unlimited",MAX(2*E12-D12+J12,J12,0))) -> 8.44 | N12: =IF(B12="Butterfly",IF(AND(J12>0,J12<K12),D12+J12,"n.a."),IF(C12="call",IF(AND(J12>0,J12<K12),D12+J12,"n.a."),IF(AND(K12>J12,2*E12-D12+J12>=0),2*E12-D12+J12,"n.a."))) -> 6808.44 | O12: =IF(B12="Butterfly",IF(AND(J12>0,J12<K12),F12-J12,"n.a."),IF(C12="call",IF(K12>J12,2*E12-D12-J12,"n.a."),IF(AND(J12>0,J12<K12),D12-J12,"n.a."))) -> 7191.56 | P12: =IF(AND(B12="Butterfly",J12>0,J12<K12),L12/J12,"n.a.") -> 22.696682 | Q12: =J12*'Model inputs'!$B$8 -> 844 | R12: Indicative only | S12: 747 | T12: 766
A13: 46281 | B13: Butterfly | C13: put | D13: 6200 | E13: 6400 | F13: 6600 | G13: ='Option source'!B695 -> 97.41 | H13: ='Option source'!B714 -> 150.25 | I13: ='Option source'!B733 -> 222.45 | J13: =G13-2*H13+IF(B13="Butterfly",I13,0) -> 19.36 | K13: =ABS(E13-D13) -> 200 | L13: =K13-J13 -> 180.64 | M13: =IF(B13="Butterfly",MAX(J13,0),IF(C13="call","Unlimited",MAX(2*E13-D13+J13,J13,0))) -> 19.36 | N13: =IF(B13="Butterfly",IF(AND(J13>0,J13<K13),D13+J13,"n.a."),IF(C13="call",IF(AND(J13>0,J13<K13),D13+J13,"n.a."),IF(AND(K13>J13,2*E13-D13+J13>=0),2*E13-D13+J13,"n.a."))) -> 6219.36 | O13: =IF(B13="Butterfly",IF(AND(J13>0,J13<K13),F13-J13,"n.a."),IF(C13="call",IF(K13>J13,2*E13-D13-J13,"n.a."),IF(AND(J13>0,J13<K13),D13-J13,"n.a."))) -> 6580.64 | P13: =IF(AND(B13="Butterfly",J13>0,J13<K13),L13/J13,"n.a.") -> 9.3305785 | Q13: =J13*'Model inputs'!$B$8 -> 1936 | R13: Indicative only | S13: 690 | T13: 709
A14: 46281 | B14: Butterfly | C14: call | D14: 7000 | E14: 7200 | F14: 7400 | G14: ='Option source'!B277 -> 289.65 | H14: ='Option source'!B296 -> 213.18 | I14: ='Option source'!B315 -> 157.14 | J14: =G14-2*H14+IF(B14="Butterfly",I14,0) -> 20.43 | K14: =ABS(E14-D14) -> 200 | L14: =K14-J14 -> 179.57 | M14: =IF(B14="Butterfly",MAX(J14,0),IF(C14="call","Unlimited",MAX(2*E14-D14+J14,J14,0))) -> 20.43 | N14: =IF(B14="Butterfly",IF(AND(J14>0,J14<K14),D14+J14,"n.a."),IF(C14="call",IF(AND(J14>0,J14<K14),D14+J14,"n.a."),IF(AND(K14>J14,2*E14-D14+J14>=0),2*E14-D14+J14,"n.a."))) -> 7020.43 | O14: =IF(B14="Butterfly",IF(AND(J14>0,J14<K14),F14-J14,"n.a."),IF(C14="call",IF(K14>J14,2*E14-D14-J14,"n.a."),IF(AND(J14>0,J14<K14),D14-J14,"n.a."))) -> 7379.57 | P14: =IF(AND(B14="Butterfly",J14>0,J14<K14),L14/J14,"n.a.") -> 8.7895252 | Q14: =J14*'Model inputs'!$B$8 -> 2043 | R14: Indicative only | S14: 272 | T14: 291
A15: 46281 | B15: Butterfly | C15: put | D15: 7000 | E15: 7200 | F15: 7400 | G15: ='Option source'!B771 -> 427.03 | H15: ='Option source'!B790 -> 550.35 | I15: ='Option source'!B809 -> 677.83 | J15: =G15-2*H15+IF(B15="Butterfly",I15,0) -> 4.16 | K15: =ABS(E15-D15) -> 200 | L15: =K15-J15 -> 195.84 | M15: =IF(B15="Butterfly",MAX(J15,0),IF(C15="call","Unlimited",MAX(2*E15-D15+J15,J15,0))) -> 4.16 | N15: =IF(B15="Butterfly",IF(AND(J15>0,J15<K15),D15+J15,"n.a."),IF(C15="call",IF(AND(J15>0,J15<K15),D15+J15,"n.a."),IF(AND(K15>J15,2*E15-D15+J15>=0),2*E15-D15+J15,"n.a."))) -> 7004.16 | O15: =IF(B15="Butterfly",IF(AND(J15>0,J15<K15),F15-J15,"n.a."),IF(C15="call",IF(K15>J15,2*E15-D15-J15,"n.a."),IF(AND(J15>0,J15<K15),D15-J15,"n.a."))) -> 7395.84 | P15: =IF(AND(B15="Butterfly",J15>0,J15<K15),L15/J15,"n.a.") -> 47.076923 | Q15: =J15*'Model inputs'!$B$8 -> 416 | R15: Indicative only | S15: 766 | T15: 785
A16: 46281 | B16: Butterfly | C16: put | D16: 6000 | E16: 6200 | F16: 6400 | G16: ='Option source'!B676 -> 56.82 | H16: ='Option source'!B695 -> 97.41 | I16: ='Option source'!B714 -> 150.25 | J16: =G16-2*H16+IF(B16="Butterfly",I16,0) -> 12.25 | K16: =ABS(E16-D16) -> 200 | L16: =K16-J16 -> 187.75 | M16: =IF(B16="Butterfly",MAX(J16,0),IF(C16="call","Unlimited",MAX(2*E16-D16+J16,J16,0))) -> 12.25 | N16: =IF(B16="Butterfly",IF(AND(J16>0,J16<K16),D16+J16,"n.a."),IF(C16="call",IF(AND(J16>0,J16<K16),D16+J16,"n.a."),IF(AND(K16>J16,2*E16-D16+J16>=0),2*E16-D16+J16,"n.a."))) -> 6012.25 | O16: =IF(B16="Butterfly",IF(AND(J16>0,J16<K16),F16-J16,"n.a."),IF(C16="call",IF(K16>J16,2*E16-D16-J16,"n.a."),IF(AND(J16>0,J16<K16),D16-J16,"n.a."))) -> 6387.75 | P16: =IF(AND(B16="Butterfly",J16>0,J16<K16),L16/J16,"n.a.") -> 15.326531 | Q16: =J16*'Model inputs'!$B$8 -> 1225 | R16: Indicative only | S16: 671 | T16: 690
A17: 46281 | B17: Butterfly | C17: call | D17: 7200 | E17: 7400 | F17: 7600 | G17: ='Option source'!B296 -> 213.18 | H17: ='Option source'!B315 -> 157.14 | I17: ='Option source'!B334 -> 107.66 | J17: =G17-2*H17+IF(B17="Butterfly",I17,0) -> 6.56 | K17: =ABS(E17-D17) -> 200 | L17: =K17-J17 -> 193.44 | M17: =IF(B17="Butterfly",MAX(J17,0),IF(C17="call","Unlimited",MAX(2*E17-D17+J17,J17,0))) -> 6.56 | N17: =IF(B17="Butterfly",IF(AND(J17>0,J17<K17),D17+J17,"n.a."),IF(C17="call",IF(AND(J17>0,J17<K17),D17+J17,"n.a."),IF(AND(K17>J17,2*E17-D17+J17>=0),2*E17-D17+J17,"n.a."))) -> 7206.56 | O17: =IF(B17="Butterfly",IF(AND(J17>0,J17<K17),F17-J17,"n.a."),IF(C17="call",IF(K17>J17,2*E17-D17-J17,"n.a."),IF(AND(J17>0,J17<K17),D17-J17,"n.a."))) -> 7593.44 | P17: =IF(AND(B17="Butterfly",J17>0,J17<K17),L17/J17,"n.a.") -> 29.487805 | Q17: =J17*'Model inputs'!$B$8 -> 656 | R17: Indicative only | S17: 291 | T17: 310
A18: 46281 | B18: Butterfly | C18: put | D18: 7200 | E18: 7400 | F18: 7600 | G18: ='Option source'!B790 -> 550.35 | H18: ='Option source'!B809 -> 677.83 | I18: ='Option source'!B828 -> 857 | J18: =G18-2*H18+IF(B18="Butterfly",I18,0) -> 51.69 | K18: =ABS(E18-D18) -> 200 | L18: =K18-J18 -> 148.31 | M18: =IF(B18="Butterfly",MAX(J18,0),IF(C18="call","Unlimited",MAX(2*E18-D18+J18,J18,0))) -> 51.69 | N18: =IF(B18="Butterfly",IF(AND(J18>0,J18<K18),D18+J18,"n.a."),IF(C18="call",IF(AND(J18>0,J18<K18),D18+J18,"n.a."),IF(AND(K18>J18,2*E18-D18+J18>=0),2*E18-D18+J18,"n.a."))) -> 7251.69 | O18: =IF(B18="Butterfly",IF(AND(J18>0,J18<K18),F18-J18,"n.a."),IF(C18="call",IF(K18>J18,2*E18-D18-J18,"n.a."),IF(AND(J18>0,J18<K18),D18-J18,"n.a."))) -> 7548.31 | P18: =IF(AND(B18="Butterfly",J18>0,J18<K18),L18/J18,"n.a.") -> 2.8692204 | Q18: =J18*'Model inputs'!$B$8 -> 5169 | R18: Indicative only | S18: 785 | T18: 804
A19: 46281 | B19: Butterfly | C19: put | D19: 5800 | E19: 6000 | F19: 6200 | G19: ='Option source'!B657 -> 31.98 | H19: ='Option source'!B676 -> 56.82 | I19: ='Option source'!B695 -> 97.41 | J19: =G19-2*H19+IF(B19="Butterfly",I19,0) -> 15.75 | K19: =ABS(E19-D19) -> 200 | L19: =K19-J19 -> 184.25 | M19: =IF(B19="Butterfly",MAX(J19,0),IF(C19="call","Unlimited",MAX(2*E19-D19+J19,J19,0))) -> 15.75 | N19: =IF(B19="Butterfly",IF(AND(J19>0,J19<K19),D19+J19,"n.a."),IF(C19="call",IF(AND(J19>0,J19<K19),D19+J19,"n.a."),IF(AND(K19>J19,2*E19-D19+J19>=0),2*E19-D19+J19,"n.a."))) -> 5815.75 | O19: =IF(B19="Butterfly",IF(AND(J19>0,J19<K19),F19-J19,"n.a."),IF(C19="call",IF(K19>J19,2*E19-D19-J19,"n.a."),IF(AND(J19>0,J19<K19),D19-J19,"n.a."))) -> 6184.25 | P19: =IF(AND(B19="Butterfly",J19>0,J19<K19),L19/J19,"n.a.") -> 11.698413 | Q19: =J19*'Model inputs'!$B$8 -> 1575 | R19: Indicative only | S19: 652 | T19: 671
A20: 46281 | B20: Butterfly | C20: call | D20: 7400 | E20: 7600 | F20: 7800 | G20: ='Option source'!B315 -> 157.14 | H20: ='Option source'!B334 -> 107.66 | I20: ='Option source'!B353 -> 75.86 | J20: =G20-2*H20+IF(B20="Butterfly",I20,0) -> 17.68 | K20: =ABS(E20-D20) -> 200 | L20: =K20-J20 -> 182.32 | M20: =IF(B20="Butterfly",MAX(J20,0),IF(C20="call","Unlimited",MAX(2*E20-D20+J20,J20,0))) -> 17.68 | N20: =IF(B20="Butterfly",IF(AND(J20>0,J20<K20),D20+J20,"n.a."),IF(C20="call",IF(AND(J20>0,J20<K20),D20+J20,"n.a."),IF(AND(K20>J20,2*E20-D20+J20>=0),2*E20-D20+J20,"n.a."))) -> 7417.68 | O20: =IF(B20="Butterfly",IF(AND(J20>0,J20<K20),F20-J20,"n.a."),IF(C20="call",IF(K20>J20,2*E20-D20-J20,"n.a."),IF(AND(J20>0,J20<K20),D20-J20,"n.a."))) -> 7782.32 | P20: =IF(AND(B20="Butterfly",J20>0,J20<K20),L20/J20,"n.a.") -> 10.312217 | Q20: =J20*'Model inputs'!$B$8 -> 1768 | R20: Indicative only | S20: 310 | T20: 329
A21: 46281 | B21: Butterfly | C21: put | D21: 5600 | E21: 5800 | F21: 6000 | G21: ='Option source'!B638 -> 17.15 | H21: ='Option source'!B657 -> 31.98 | I21: ='Option source'!B676 -> 56.82 | J21: =G21-2*H21+IF(B21="Butterfly",I21,0) -> 10.01 | K21: =ABS(E21-D21) -> 200 | L21: =K21-J21 -> 189.99 | M21: =IF(B21="Butterfly",MAX(J21,0),IF(C21="call","Unlimited",MAX(2*E21-D21+J21,J21,0))) -> 10.01 | N21: =IF(B21="Butterfly",IF(AND(J21>0,J21<K21),D21+J21,"n.a."),IF(C21="call",IF(AND(J21>0,J21<K21),D21+J21,"n.a."),IF(AND(K21>J21,2*E21-D21+J21>=0),2*E21-D21+J21,"n.a."))) -> 5610.01 | O21: =IF(B21="Butterfly",IF(AND(J21>0,J21<K21),F21-J21,"n.a."),IF(C21="call",IF(K21>J21,2*E21-D21-J21,"n.a."),IF(AND(J21>0,J21<K21),D21-J21,"n.a."))) -> 5989.99 | P21: =IF(AND(B21="Butterfly",J21>0,J21<K21),L21/J21,"n.a.") -> 18.98002 | Q21: =J21*'Model inputs'!$B$8 -> 1001 | R21: Indicative only | S21: 633 | T21: 652
A22: 46281 | B22: Butterfly | C22: call | D22: 7600 | E22: 7800 | F22: 8000 | G22: ='Option source'!B334 -> 107.66 | H22: ='Option source'!B353 -> 75.86 | I22: ='Option source'!B372 -> 54.71 | J22: =G22-2*H22+IF(B22="Butterfly",I22,0) -> 10.65 | K22: =ABS(E22-D22) -> 200 | L22: =K22-J22 -> 189.35 | M22: =IF(B22="Butterfly",MAX(J22,0),IF(C22="call","Unlimited",MAX(2*E22-D22+J22,J22,0))) -> 10.65 | N22: =IF(B22="Butterfly",IF(AND(J22>0,J22<K22),D22+J22,"n.a."),IF(C22="call",IF(AND(J22>0,J22<K22),D22+J22,"n.a."),IF(AND(K22>J22,2*E22-D22+J22>=0),2*E22-D22+J22,"n.a."))) -> 7610.65 | O22: =IF(B22="Butterfly",IF(AND(J22>0,J22<K22),F22-J22,"n.a."),IF(C22="call",IF(K22>J22,2*E22-D22-J22,"n.a."),IF(AND(J22>0,J22<K22),D22-J22,"n.a."))) -> 7989.35 | P22: =IF(AND(B22="Butterfly",J22>0,J22<K22),L22/J22,"n.a.") -> 17.779343 | Q22: =J22*'Model inputs'!$B$8 -> 1065 | R22: Indicative only | S22: 329 | T22: 348
A23: 46281 | B23: Butterfly | C23: put | D23: 5400 | E23: 5600 | F23: 5800 | G23: ='Option source'!B619 -> 9.02 | H23: ='Option source'!B638 -> 17.15 | I23: ='Option source'!B657 -> 31.98 | J23: =G23-2*H23+IF(B23="Butterfly",I23,0) -> 6.7 | K23: =ABS(E23-D23) -> 200 | L23: =K23-J23 -> 193.3 | M23: =IF(B23="Butterfly",MAX(J23,0),IF(C23="call","Unlimited",MAX(2*E23-D23+J23,J23,0))) -> 6.7 | N23: =IF(B23="Butterfly",IF(AND(J23>0,J23<K23),D23+J23,"n.a."),IF(C23="call",IF(AND(J23>0,J23<K23),D23+J23,"n.a."),IF(AND(K23>J23,2*E23-D23+J23>=0),2*E23-D23+J23,"n.a."))) -> 5406.7 | O23: =IF(B23="Butterfly",IF(AND(J23>0,J23<K23),F23-J23,"n.a."),IF(C23="call",IF(K23>J23,2*E23-D23-J23,"n.a."),IF(AND(J23>0,J23<K23),D23-J23,"n.a."))) -> 5793.3 | P23: =IF(AND(B23="Butterfly",J23>0,J23<K23),L23/J23,"n.a.") -> 28.850746 | Q23: =J23*'Model inputs'!$B$8 -> 670 | R23: Indicative only | S23: 614 | T23: 633
A24: 46281 | B24: Butterfly | C24: put | D24: 5200 | E24: 5400 | F24: 5600 | G24: ='Option source'!B600 -> 6.01 | H24: ='Option source'!B619 -> 9.02 | I24: ='Option source'!B638 -> 17.15 | J24: =G24-2*H24+IF(B24="Butterfly",I24,0) -> 5.12 | K24: =ABS(E24-D24) -> 200 | L24: =K24-J24 -> 194.88 | M24: =IF(B24="Butterfly",MAX(J24,0),IF(C24="call","Unlimited",MAX(2*E24-D24+J24,J24,0))) -> 5.12 | N24: =IF(B24="Butterfly",IF(AND(J24>0,J24<K24),D24+J24,"n.a."),IF(C24="call",IF(AND(J24>0,J24<K24),D24+J24,"n.a."),IF(AND(K24>J24,2*E24-D24+J24>=0),2*E24-D24+J24,"n.a."))) -> 5205.12 | O24: =IF(B24="Butterfly",IF(AND(J24>0,J24<K24),F24-J24,"n.a."),IF(C24="call",IF(K24>J24,2*E24-D24-J24,"n.a."),IF(AND(J24>0,J24<K24),D24-J24,"n.a."))) -> 5594.88 | P24: =IF(AND(B24="Butterfly",J24>0,J24<K24),L24/J24,"n.a.") -> 38.0625 | Q24: =J24*'Model inputs'!$B$8 -> 512 | R24: Indicative only | S24: 595 | T24: 614
A25: 46281 | B25: Butterfly | C25: call | D25: 8000 | E25: 8300 | F25: 8600 | G25: ='Option source'!B372 -> 54.71 | H25: ='Option source'!B391 -> 32.2 | I25: ='Option source'!B410 -> 17.94 | J25: =G25-2*H25+IF(B25="Butterfly",I25,0) -> 8.25 | K25: =ABS(E25-D25) -> 300 | L25: =K25-J25 -> 291.75 | M25: =IF(B25="Butterfly",MAX(J25,0),IF(C25="call","Unlimited",MAX(2*E25-D25+J25,J25,0))) -> 8.25 | N25: =IF(B25="Butterfly",IF(AND(J25>0,J25<K25),D25+J25,"n.a."),IF(C25="call",IF(AND(J25>0,J25<K25),D25+J25,"n.a."),IF(AND(K25>J25,2*E25-D25+J25>=0),2*E25-D25+J25,"n.a."))) -> 8008.25 | O25: =IF(B25="Butterfly",IF(AND(J25>0,J25<K25),F25-J25,"n.a."),IF(C25="call",IF(K25>J25,2*E25-D25-J25,"n.a."),IF(AND(J25>0,J25<K25),D25-J25,"n.a."))) -> 8591.75 | P25: =IF(AND(B25="Butterfly",J25>0,J25<K25),L25/J25,"n.a.") -> 35.363636 | Q25: =J25*'Model inputs'!$B$8 -> 825 | R25: Indicative only | S25: 367 | T25: 386
A26: 46281 | B26: Butterfly | C26: put | D26: 5000 | E26: 5200 | F26: 5400 | G26: ='Option source'!B581 -> 3.18 | H26: ='Option source'!B600 -> 6.01 | I26: ='Option source'!B619 -> 9.02 | J26: =G26-2*H26+IF(B26="Butterfly",I26,0) -> 0.18 | K26: =ABS(E26-D26) -> 200 | L26: =K26-J26 -> 199.82 | M26: =IF(B26="Butterfly",MAX(J26,0),IF(C26="call","Unlimited",MAX(2*E26-D26+J26,J26,0))) -> 0.18 | N26: =IF(B26="Butterfly",IF(AND(J26>0,J26<K26),D26+J26,"n.a."),IF(C26="call",IF(AND(J26>0,J26<K26),D26+J26,"n.a."),IF(AND(K26>J26,2*E26-D26+J26>=0),2*E26-D26+J26,"n.a."))) -> 5000.18 | O26: =IF(B26="Butterfly",IF(AND(J26>0,J26<K26),F26-J26,"n.a."),IF(C26="call",IF(K26>J26,2*E26-D26-J26,"n.a."),IF(AND(J26>0,J26<K26),D26-J26,"n.a."))) -> 5399.82 | P26: =IF(AND(B26="Butterfly",J26>0,J26<K26),L26/J26,"n.a.") -> 1110.1111 | Q26: =J26*'Model inputs'!$B$8 -> 18 | R26: Indicative only | S26: 576 | T26: 595
A27: 46281 | B27: Butterfly | C27: put | D27: 4800 | E27: 5000 | F27: 5200 | G27: ='Option source'!B562 -> 1.93 | H27: ='Option source'!B581 -> 3.18 | I27: ='Option source'!B600 -> 6.01 | J27: =G27-2*H27+IF(B27="Butterfly",I27,0) -> 1.58 | K27: =ABS(E27-D27) -> 200 | L27: =K27-J27 -> 198.42 | M27: =IF(B27="Butterfly",MAX(J27,0),IF(C27="call","Unlimited",MAX(2*E27-D27+J27,J27,0))) -> 1.58 | N27: =IF(B27="Butterfly",IF(AND(J27>0,J27<K27),D27+J27,"n.a."),IF(C27="call",IF(AND(J27>0,J27<K27),D27+J27,"n.a."),IF(AND(K27>J27,2*E27-D27+J27>=0),2*E27-D27+J27,"n.a."))) -> 4801.58 | O27: =IF(B27="Butterfly",IF(AND(J27>0,J27<K27),F27-J27,"n.a."),IF(C27="call",IF(K27>J27,2*E27-D27-J27,"n.a."),IF(AND(J27>0,J27<K27),D27-J27,"n.a."))) -> 5198.42 | P27: =IF(AND(B27="Butterfly",J27>0,J27<K27),L27/J27,"n.a.") -> 125.58228 | Q27: =J27*'Model inputs'!$B$8 -> 158 | R27: Indicative only | S27: 557 | T27: 576
A28: 46281 | B28: Butterfly | C28: call | D28: 8300 | E28: 8600 | F28: 8900 | G28: ='Option source'!B391 -> 32.2 | H28: ='Option source'!B410 -> 17.94 | I28: ='Option source'!B429 -> 9.99 | J28: =G28-2*H28+IF(B28="Butterfly",I28,0) -> 6.31 | K28: =ABS(E28-D28) -> 300 | L28: =K28-J28 -> 293.69 | M28: =IF(B28="Butterfly",MAX(J28,0),IF(C28="call","Unlimited",MAX(2*E28-D28+J28,J28,0))) -> 6.31 | N28: =IF(B28="Butterfly",IF(AND(J28>0,J28<K28),D28+J28,"n.a."),IF(C28="call",IF(AND(J28>0,J28<K28),D28+J28,"n.a."),IF(AND(K28>J28,2*E28-D28+J28>=0),2*E28-D28+J28,"n.a."))) -> 8306.31 | O28: =IF(B28="Butterfly",IF(AND(J28>0,J28<K28),F28-J28,"n.a."),IF(C28="call",IF(K28>J28,2*E28-D28-J28,"n.a."),IF(AND(J28>0,J28<K28),D28-J28,"n.a."))) -> 8893.69 | P28: =IF(AND(B28="Butterfly",J28>0,J28<K28),L28/J28,"n.a.") -> 46.543582 | Q28: =J28*'Model inputs'!$B$8 -> 631 | R28: Indicative only | S28: 386 | T28: 405
A29: 46281 | B29: Butterfly | C29: put | D29: 4600 | E29: 4800 | F29: 5000 | G29: ='Option source'!B543 -> 1.62 | H29: ='Option source'!B562 -> 1.93 | I29: ='Option source'!B581 -> 3.18 | J29: =G29-2*H29+IF(B29="Butterfly",I29,0) -> 0.94 | K29: =ABS(E29-D29) -> 200 | L29: =K29-J29 -> 199.06 | M29: =IF(B29="Butterfly",MAX(J29,0),IF(C29="call","Unlimited",MAX(2*E29-D29+J29,J29,0))) -> 0.94 | N29: =IF(B29="Butterfly",IF(AND(J29>0,J29<K29),D29+J29,"n.a."),IF(C29="call",IF(AND(J29>0,J29<K29),D29+J29,"n.a."),IF(AND(K29>J29,2*E29-D29+J29>=0),2*E29-D29+J29,"n.a."))) -> 4600.94 | O29: =IF(B29="Butterfly",IF(AND(J29>0,J29<K29),F29-J29,"n.a."),IF(C29="call",IF(K29>J29,2*E29-D29-J29,"n.a."),IF(AND(J29>0,J29<K29),D29-J29,"n.a."))) -> 4999.06 | P29: =IF(AND(B29="Butterfly",J29>0,J29<K29),L29/J29,"n.a.") -> 211.76596 | Q29: =J29*'Model inputs'!$B$8 -> 94 | R29: Indicative only | S29: 538 | T29: 557
A30: 46281 | B30: Butterfly | C30: call | D30: 8600 | E30: 8900 | F30: 9200 | G30: ='Option source'!B410 -> 17.94 | H30: ='Option source'!B429 -> 9.99 | I30: ='Option source'!B448 -> 3.53 | J30: =G30-2*H30+IF(B30="Butterfly",I30,0) -> 1.49 | K30: =ABS(E30-D30) -> 300 | L30: =K30-J30 -> 298.51 | M30: =IF(B30="Butterfly",MAX(J30,0),IF(C30="call","Unlimited",MAX(2*E30-D30+J30,J30,0))) -> 1.49 | N30: =IF(B30="Butterfly",IF(AND(J30>0,J30<K30),D30+J30,"n.a."),IF(C30="call",IF(AND(J30>0,J30<K30),D30+J30,"n.a."),IF(AND(K30>J30,2*E30-D30+J30>=0),2*E30-D30+J30,"n.a."))) -> 8601.49 | O30: =IF(B30="Butterfly",IF(AND(J30>0,J30<K30),F30-J30,"n.a."),IF(C30="call",IF(K30>J30,2*E30-D30-J30,"n.a."),IF(AND(J30>0,J30<K30),D30-J30,"n.a."))) -> 9198.51 | P30: =IF(AND(B30="Butterfly",J30>0,J30<K30),L30/J30,"n.a.") -> 200.34228 | Q30: =J30*'Model inputs'!$B$8 -> 149 | R30: Indicative only | S30: 405 | T30: 424
A31: 46281 | B31: Butterfly | C31: put | D31: 4200 | E31: 4400 | F31: 4600 | G31: ='Option source'!B505 -> 1.21 | H31: ='Option source'!B524 -> 0.91 | I31: ='Option source'!B543 -> 1.62 | J31: =G31-2*H31+IF(B31="Butterfly",I31,0) -> 1.01 | K31: =ABS(E31-D31) -> 200 | L31: =K31-J31 -> 198.99 | M31: =IF(B31="Butterfly",MAX(J31,0),IF(C31="call","Unlimited",MAX(2*E31-D31+J31,J31,0))) -> 1.01 | N31: =IF(B31="Butterfly",IF(AND(J31>0,J31<K31),D31+J31,"n.a."),IF(C31="call",IF(AND(J31>0,J31<K31),D31+J31,"n.a."),IF(AND(K31>J31,2*E31-D31+J31>=0),2*E31-D31+J31,"n.a."))) -> 4201.01 | O31: =IF(B31="Butterfly",IF(AND(J31>0,J31<K31),F31-J31,"n.a."),IF(C31="call",IF(K31>J31,2*E31-D31-J31,"n.a."),IF(AND(J31>0,J31<K31),D31-J31,"n.a."))) -> 4598.99 | P31: =IF(AND(B31="Butterfly",J31>0,J31<K31),L31/J31,"n.a.") -> 197.0198 | Q31: =J31*'Model inputs'!$B$8 -> 101 | R31: Indicative only | S31: 500 | T31: 519
A32: 46281 | B32: Butterfly | C32: call | D32: 8900 | E32: 9200 | F32: 9500 | G32: ='Option source'!B429 -> 9.99 | H32: ='Option source'!B448 -> 3.53 | I32: ='Option source'!B467 -> 3.44 | J32: =G32-2*H32+IF(B32="Butterfly",I32,0) -> 6.37 | K32: =ABS(E32-D32) -> 300 | L32: =K32-J32 -> 293.63 | M32: =IF(B32="Butterfly",MAX(J32,0),IF(C32="call","Unlimited",MAX(2*E32-D32+J32,J32,0))) -> 6.37 | N32: =IF(B32="Butterfly",IF(AND(J32>0,J32<K32),D32+J32,"n.a."),IF(C32="call",IF(AND(J32>0,J32<K32),D32+J32,"n.a."),IF(AND(K32>J32,2*E32-D32+J32>=0),2*E32-D32+J32,"n.a."))) -> 8906.37 | O32: =IF(B32="Butterfly",IF(AND(J32>0,J32<K32),F32-J32,"n.a."),IF(C32="call",IF(K32>J32,2*E32-D32-J32,"n.a."),IF(AND(J32>0,J32<K32),D32-J32,"n.a."))) -> 9493.63 | P32: =IF(AND(B32="Butterfly",J32>0,J32<K32),L32/J32,"n.a.") -> 46.095761 | Q32: =J32*'Model inputs'!$B$8 -> 637 | R32: Indicative only | S32: 424 | T32: 443
A33: 46281 | B33: Butterfly | C33: call | D33: 6200 | E33: 6400 | F33: 6600 | G33: ='Option source'!B201 -> 704.74 | H33: ='Option source'!B220 -> 616.1 | I33: ='Option source'!B239 -> 478.22 | J33: =G33-2*H33+IF(B33="Butterfly",I33,0) -> -49.24 | K33: =ABS(E33-D33) -> 200 | L33: =K33-J33 -> 249.24 | M33: =IF(B33="Butterfly",MAX(J33,0),IF(C33="call","Unlimited",MAX(2*E33-D33+J33,J33,0))) -> 0 | N33: =IF(B33="Butterfly",IF(AND(J33>0,J33<K33),D33+J33,"n.a."),IF(C33="call",IF(AND(J33>0,J33<K33),D33+J33,"n.a."),IF(AND(K33>J33,2*E33-D33+J33>=0),2*E33-D33+J33,"n.a."))) -> n.a. | O33: =IF(B33="Butterfly",IF(AND(J33>0,J33<K33),F33-J33,"n.a."),IF(C33="call",IF(K33>J33,2*E33-D33-J33,"n.a."),IF(AND(J33>0,J33<K33),D33-J33,"n.a."))) -> n.a. | P33: =IF(AND(B33="Butterfly",J33>0,J33<K33),L33/J33,"n.a.") -> n.a. | Q33: =J33*'Model inputs'!$B$8 -> -4924 | R33: Outside standard debit bounds | S33: 196 | T33: 215
A34: 46281 | B34: Butterfly | C34: call | D34: 6000 | E34: 6200 | F34: 6400 | G34: ='Option source'!B182 -> 916.41 | H34: ='Option source'!B201 -> 704.74 | I34: ='Option source'!B220 -> 616.1 | J34: =G34-2*H34+IF(B34="Butterfly",I34,0) -> 123.03 | K34: =ABS(E34-D34) -> 200 | L34: =K34-J34 -> 76.97 | M34: =IF(B34="Butterfly",MAX(J34,0),IF(C34="call","Unlimited",MAX(2*E34-D34+J34,J34,0))) -> 123.03 | N34: =IF(B34="Butterfly",IF(AND(J34>0,J34<K34),D34+J34,"n.a."),IF(C34="call",IF(AND(J34>0,J34<K34),D34+J34,"n.a."),IF(AND(K34>J34,2*E34-D34+J34>=0),2*E34-D34+J34,"n.a."))) -> 6123.03 | O34: =IF(B34="Butterfly",IF(AND(J34>0,J34<K34),F34-J34,"n.a."),IF(C34="call",IF(K34>J34,2*E34-D34-J34,"n.a."),IF(AND(J34>0,J34<K34),D34-J34,"n.a."))) -> 6276.97 | P34: =IF(AND(B34="Butterfly",J34>0,J34<K34),L34/J34,"n.a.") -> 0.62561977 | Q34: =J34*'Model inputs'!$B$8 -> 12303 | R34: Flagged leg data | S34: 177 | T34: 196
A35: 46281 | B35: Butterfly | C35: call | D35: 5800 | E35: 6000 | F35: 6200 | G35: ='Option source'!B163 -> 1049.9 | H35: ='Option source'!B182 -> 916.41 | I35: ='Option source'!B201 -> 704.74 | J35: =G35-2*H35+IF(B35="Butterfly",I35,0) -> -78.18 | K35: =ABS(E35-D35) -> 200 | L35: =K35-J35 -> 278.18 | M35: =IF(B35="Butterfly",MAX(J35,0),IF(C35="call","Unlimited",MAX(2*E35-D35+J35,J35,0))) -> 0 | N35: =IF(B35="Butterfly",IF(AND(J35>0,J35<K35),D35+J35,"n.a."),IF(C35="call",IF(AND(J35>0,J35<K35),D35+J35,"n.a."),IF(AND(K35>J35,2*E35-D35+J35>=0),2*E35-D35+J35,"n.a."))) -> n.a. | O35: =IF(B35="Butterfly",IF(AND(J35>0,J35<K35),F35-J35,"n.a."),IF(C35="call",IF(K35>J35,2*E35-D35-J35,"n.a."),IF(AND(J35>0,J35<K35),D35-J35,"n.a."))) -> n.a. | P35: =IF(AND(B35="Butterfly",J35>0,J35<K35),L35/J35,"n.a.") -> n.a. | Q35: =J35*'Model inputs'!$B$8 -> -7818 | R35: Outside standard debit bounds | S35: 158 | T35: 177
A36: 46281 | B36: Butterfly | C36: put | D36: 7400 | E36: 7600 | F36: 7800 | G36: ='Option source'!B809 -> 677.83 | H36: ='Option source'!B828 -> 857 | I36: ='Option source'!B847 -> 1000 | J36: =G36-2*H36+IF(B36="Butterfly",I36,0) -> -36.17 | K36: =ABS(E36-D36) -> 200 | L36: =K36-J36 -> 236.17 | M36: =IF(B36="Butterfly",MAX(J36,0),IF(C36="call","Unlimited",MAX(2*E36-D36+J36,J36,0))) -> 0 | N36: =IF(B36="Butterfly",IF(AND(J36>0,J36<K36),D36+J36,"n.a."),IF(C36="call",IF(AND(J36>0,J36<K36),D36+J36,"n.a."),IF(AND(K36>J36,2*E36-D36+J36>=0),2*E36-D36+J36,"n.a."))) -> n.a. | O36: =IF(B36="Butterfly",IF(AND(J36>0,J36<K36),F36-J36,"n.a."),IF(C36="call",IF(K36>J36,2*E36-D36-J36,"n.a."),IF(AND(J36>0,J36<K36),D36-J36,"n.a."))) -> n.a. | P36: =IF(AND(B36="Butterfly",J36>0,J36<K36),L36/J36,"n.a.") -> n.a. | Q36: =J36*'Model inputs'!$B$8 -> -3617 | R36: Outside standard debit bounds | S36: 804 | T36: 823
A37: 46281 | B37: Butterfly | C37: call | D37: 5600 | E37: 5800 | F37: 6000 | G37: ='Option source'!B153 -> 1233.13 | H37: ='Option source'!B163 -> 1049.9 | I37: ='Option source'!B182 -> 916.41 | J37: =G37-2*H37+IF(B37="Butterfly",I37,0) -> 49.74 | K37: =ABS(E37-D37) -> 200 | L37: =K37-J37 -> 150.26 | M37: =IF(B37="Butterfly",MAX(J37,0),IF(C37="call","Unlimited",MAX(2*E37-D37+J37,J37,0))) -> 49.74 | N37: =IF(B37="Butterfly",IF(AND(J37>0,J37<K37),D37+J37,"n.a."),IF(C37="call",IF(AND(J37>0,J37<K37),D37+J37,"n.a."),IF(AND(K37>J37,2*E37-D37+J37>=0),2*E37-D37+J37,"n.a."))) -> 5649.74 | O37: =IF(B37="Butterfly",IF(AND(J37>0,J37<K37),F37-J37,"n.a."),IF(C37="call",IF(K37>J37,2*E37-D37-J37,"n.a."),IF(AND(J37>0,J37<K37),D37-J37,"n.a."))) -> 5950.26 | P37: =IF(AND(B37="Butterfly",J37>0,J37<K37),L37/J37,"n.a.") -> 3.0209087 | Q37: =J37*'Model inputs'!$B$8 -> 4974 | R37: Flagged leg data | S37: 148 | T37: 158
A38: 46281 | B38: Butterfly | C38: put | D38: 7600 | E38: 7800 | F38: 8000 | G38: ='Option source'!B828 -> 857 | H38: ='Option source'!B847 -> 1000 | I38: ='Option source'!B866 -> 1230 | J38: =G38-2*H38+IF(B38="Butterfly",I38,0) -> 87 | K38: =ABS(E38-D38) -> 200 | L38: =K38-J38 -> 113 | M38: =IF(B38="Butterfly",MAX(J38,0),IF(C38="call","Unlimited",MAX(2*E38-D38+J38,J38,0))) -> 87 | N38: =IF(B38="Butterfly",IF(AND(J38>0,J38<K38),D38+J38,"n.a."),IF(C38="call",IF(AND(J38>0,J38<K38),D38+J38,"n.a."),IF(AND(K38>J38,2*E38-D38+J38>=0),2*E38-D38+J38,"n.a."))) -> 7687 | O38: =IF(B38="Butterfly",IF(AND(J38>0,J38<K38),F38-J38,"n.a."),IF(C38="call",IF(K38>J38,2*E38-D38-J38,"n.a."),IF(AND(J38>0,J38<K38),D38-J38,"n.a."))) -> 7913 | P38: =IF(AND(B38="Butterfly",J38>0,J38<K38),L38/J38,"n.a.") -> 1.2988506 | Q38: =J38*'Model inputs'!$B$8 -> 8700 | R38: Flagged leg data | S38: 823 | T38: 842
A39: 46281 | B39: Butterfly | C39: call | D39: 5400 | E39: 5600 | F39: 5800 | G39: ='Option source'!B135 -> 1470 | H39: ='Option source'!B153 -> 1233.13 | I39: ='Option source'!B163 -> 1049.9 | J39: =G39-2*H39+IF(B39="Butterfly",I39,0) -> 53.64 | K39: =ABS(E39-D39) -> 200 | L39: =K39-J39 -> 146.36 | M39: =IF(B39="Butterfly",MAX(J39,0),IF(C39="call","Unlimited",MAX(2*E39-D39+J39,J39,0))) -> 53.64 | N39: =IF(B39="Butterfly",IF(AND(J39>0,J39<K39),D39+J39,"n.a."),IF(C39="call",IF(AND(J39>0,J39<K39),D39+J39,"n.a."),IF(AND(K39>J39,2*E39-D39+J39>=0),2*E39-D39+J39,"n.a."))) -> 5453.64 | O39: =IF(B39="Butterfly",IF(AND(J39>0,J39<K39),F39-J39,"n.a."),IF(C39="call",IF(K39>J39,2*E39-D39-J39,"n.a."),IF(AND(J39>0,J39<K39),D39-J39,"n.a."))) -> 5746.36 | P39: =IF(AND(B39="Butterfly",J39>0,J39<K39),L39/J39,"n.a.") -> 2.7285608 | Q39: =J39*'Model inputs'!$B$8 -> 5364 | R39: Flagged leg data | S39: 130 | T39: 148
A40: 46281 | B40: Butterfly | C40: call | D40: 5200 | E40: 5400 | F40: 5600 | G40: ='Option source'!B116 -> 1678.07 | H40: ='Option source'!B135 -> 1470 | I40: ='Option source'!B153 -> 1233.13 | J40: =G40-2*H40+IF(B40="Butterfly",I40,0) -> -28.8 | K40: =ABS(E40-D40) -> 200 | L40: =K40-J40 -> 228.8 | M40: =IF(B40="Butterfly",MAX(J40,0),IF(C40="call","Unlimited",MAX(2*E40-D40+J40,J40,0))) -> 0 | N40: =IF(B40="Butterfly",IF(AND(J40>0,J40<K40),D40+J40,"n.a."),IF(C40="call",IF(AND(J40>0,J40<K40),D40+J40,"n.a."),IF(AND(K40>J40,2*E40-D40+J40>=0),2*E40-D40+J40,"n.a."))) -> n.a. | O40: =IF(B40="Butterfly",IF(AND(J40>0,J40<K40),F40-J40,"n.a."),IF(C40="call",IF(K40>J40,2*E40-D40-J40,"n.a."),IF(AND(J40>0,J40<K40),D40-J40,"n.a."))) -> n.a. | P40: =IF(AND(B40="Butterfly",J40>0,J40<K40),L40/J40,"n.a.") -> n.a. | Q40: =J40*'Model inputs'!$B$8 -> -2880 | R40: Outside standard debit bounds | S40: 111 | T40: 130
A41: 46281 | B41: Butterfly | C41: put | D41: 8000 | E41: 8300 | F41: 8600 | G41: ='Option source'!B866 -> 1230 | H41: ='Option source'!B885 -> 1520 | I41: ='Option source'!B904 -> 1648.65 | J41: =G41-2*H41+IF(B41="Butterfly",I41,0) -> -161.35 | K41: =ABS(E41-D41) -> 300 | L41: =K41-J41 -> 461.35 | M41: =IF(B41="Butterfly",MAX(J41,0),IF(C41="call","Unlimited",MAX(2*E41-D41+J41,J41,0))) -> 0 | N41: =IF(B41="Butterfly",IF(AND(J41>0,J41<K41),D41+J41,"n.a."),IF(C41="call",IF(AND(J41>0,J41<K41),D41+J41,"n.a."),IF(AND(K41>J41,2*E41-D41+J41>=0),2*E41-D41+J41,"n.a."))) -> n.a. | O41: =IF(B41="Butterfly",IF(AND(J41>0,J41<K41),F41-J41,"n.a."),IF(C41="call",IF(K41>J41,2*E41-D41-J41,"n.a."),IF(AND(J41>0,J41<K41),D41-J41,"n.a."))) -> n.a. | P41: =IF(AND(B41="Butterfly",J41>0,J41<K41),L41/J41,"n.a.") -> n.a. | Q41: =J41*'Model inputs'!$B$8 -> -16135 | R41: Outside standard debit bounds | S41: 861 | T41: 880
A42: 46281 | B42: Butterfly | C42: call | D42: 5000 | E42: 5200 | F42: 5400 | G42: ='Option source'!B97 -> 1808.85 | H42: ='Option source'!B116 -> 1678.07 | I42: ='Option source'!B135 -> 1470 | J42: =G42-2*H42+IF(B42="Butterfly",I42,0) -> -77.29 | K42: =ABS(E42-D42) -> 200 | L42: =K42-J42 -> 277.29 | M42: =IF(B42="Butterfly",MAX(J42,0),IF(C42="call","Unlimited",MAX(2*E42-D42+J42,J42,0))) -> 0 | N42: =IF(B42="Butterfly",IF(AND(J42>0,J42<K42),D42+J42,"n.a."),IF(C42="call",IF(AND(J42>0,J42<K42),D42+J42,"n.a."),IF(AND(K42>J42,2*E42-D42+J42>=0),2*E42-D42+J42,"n.a."))) -> n.a. | O42: =IF(B42="Butterfly",IF(AND(J42>0,J42<K42),F42-J42,"n.a."),IF(C42="call",IF(K42>J42,2*E42-D42-J42,"n.a."),IF(AND(J42>0,J42<K42),D42-J42,"n.a."))) -> n.a. | P42: =IF(AND(B42="Butterfly",J42>0,J42<K42),L42/J42,"n.a.") -> n.a. | Q42: =J42*'Model inputs'!$B$8 -> -7729 | R42: Outside standard debit bounds | S42: 92 | T42: 111
A43: 46281 | B43: Butterfly | C43: call | D43: 4800 | E43: 5000 | F43: 5200 | G43: ='Option source'!B80 -> 2084.21 | H43: ='Option source'!B97 -> 1808.85 | I43: ='Option source'!B116 -> 1678.07 | J43: =G43-2*H43+IF(B43="Butterfly",I43,0) -> 144.58 | K43: =ABS(E43-D43) -> 200 | L43: =K43-J43 -> 55.42 | M43: =IF(B43="Butterfly",MAX(J43,0),IF(C43="call","Unlimited",MAX(2*E43-D43+J43,J43,0))) -> 144.58 | N43: =IF(B43="Butterfly",IF(AND(J43>0,J43<K43),D43+J43,"n.a."),IF(C43="call",IF(AND(J43>0,J43<K43),D43+J43,"n.a."),IF(AND(K43>J43,2*E43-D43+J43>=0),2*E43-D43+J43,"n.a."))) -> 4944.58 | O43: =IF(B43="Butterfly",IF(AND(J43>0,J43<K43),F43-J43,"n.a."),IF(C43="call",IF(K43>J43,2*E43-D43-J43,"n.a."),IF(AND(J43>0,J43<K43),D43-J43,"n.a."))) -> 5055.42 | P43: =IF(AND(B43="Butterfly",J43>0,J43<K43),L43/J43,"n.a.") -> 0.38331719 | Q43: =J43*'Model inputs'!$B$8 -> 14458 | R43: Flagged leg data | S43: 75 | T43: 92
A44: 46281 | B44: Butterfly | C44: put | D44: 8300 | E44: 8600 | F44: 8900 | G44: ='Option source'!B885 -> 1520 | H44: ='Option source'!B904 -> 1648.65 | I44: ='Option source'!B919 -> 2022.5 | J44: =G44-2*H44+IF(B44="Butterfly",I44,0) -> 245.2 | K44: =ABS(E44-D44) -> 300 | L44: =K44-J44 -> 54.8 | M44: =IF(B44="Butterfly",MAX(J44,0),IF(C44="call","Unlimited",MAX(2*E44-D44+J44,J44,0))) -> 245.2 | N44: =IF(B44="Butterfly",IF(AND(J44>0,J44<K44),D44+J44,"n.a."),IF(C44="call",IF(AND(J44>0,J44<K44),D44+J44,"n.a."),IF(AND(K44>J44,2*E44-D44+J44>=0),2*E44-D44+J44,"n.a."))) -> 8545.2 | O44: =IF(B44="Butterfly",IF(AND(J44>0,J44<K44),F44-J44,"n.a."),IF(C44="call",IF(K44>J44,2*E44-D44-J44,"n.a."),IF(AND(J44>0,J44<K44),D44-J44,"n.a."))) -> 8654.8 | P44: =IF(AND(B44="Butterfly",J44>0,J44<K44),L44/J44,"n.a.") -> 0.22349103 | Q44: =J44*'Model inputs'!$B$8 -> 24520 | R44: Flagged leg data | S44: 880 | T44: 899
A45: 46281 | B45: Butterfly | C45: call | D45: 4600 | E45: 4800 | F45: 5000 | G45: ='Option source'!B63 -> 2280.1 | H45: ='Option source'!B80 -> 2084.21 | I45: ='Option source'!B97 -> 1808.85 | J45: =G45-2*H45+IF(B45="Butterfly",I45,0) -> -79.47 | K45: =ABS(E45-D45) -> 200 | L45: =K45-J45 -> 279.47 | M45: =IF(B45="Butterfly",MAX(J45,0),IF(C45="call","Unlimited",MAX(2*E45-D45+J45,J45,0))) -> 0 | N45: =IF(B45="Butterfly",IF(AND(J45>0,J45<K45),D45+J45,"n.a."),IF(C45="call",IF(AND(J45>0,J45<K45),D45+J45,"n.a."),IF(AND(K45>J45,2*E45-D45+J45>=0),2*E45-D45+J45,"n.a."))) -> n.a. | O45: =IF(B45="Butterfly",IF(AND(J45>0,J45<K45),F45-J45,"n.a."),IF(C45="call",IF(K45>J45,2*E45-D45-J45,"n.a."),IF(AND(J45>0,J45<K45),D45-J45,"n.a."))) -> n.a. | P45: =IF(AND(B45="Butterfly",J45>0,J45<K45),L45/J45,"n.a.") -> n.a. | Q45: =J45*'Model inputs'!$B$8 -> -7947 | R45: Outside standard debit bounds | S45: 58 | T45: 75
A46: 46281 | B46: Butterfly | C46: put | D46: 8600 | E46: 8900 | F46: 9200 | G46: ='Option source'!B904 -> 1648.65 | H46: ='Option source'!B919 -> 2022.5 | I46: ='Option source'!B926 -> 2268.51 | J46: =G46-2*H46+IF(B46="Butterfly",I46,0) -> -127.84 | K46: =ABS(E46-D46) -> 300 | L46: =K46-J46 -> 427.84 | M46: =IF(B46="Butterfly",MAX(J46,0),IF(C46="call","Unlimited",MAX(2*E46-D46+J46,J46,0))) -> 0 | N46: =IF(B46="Butterfly",IF(AND(J46>0,J46<K46),D46+J46,"n.a."),IF(C46="call",IF(AND(J46>0,J46<K46),D46+J46,"n.a."),IF(AND(K46>J46,2*E46-D46+J46>=0),2*E46-D46+J46,"n.a."))) -> n.a. | O46: =IF(B46="Butterfly",IF(AND(J46>0,J46<K46),F46-J46,"n.a."),IF(C46="call",IF(K46>J46,2*E46-D46-J46,"n.a."),IF(AND(J46>0,J46<K46),D46-J46,"n.a."))) -> n.a. | P46: =IF(AND(B46="Butterfly",J46>0,J46<K46),L46/J46,"n.a.") -> n.a. | Q46: =J46*'Model inputs'!$B$8 -> -12784 | R46: Outside standard debit bounds | S46: 899 | T46: 914
A47: 46281 | B47: Butterfly | C47: call | D47: 4400 | E47: 4600 | F47: 4800 | G47: ='Option source'!B44 -> 2422 | H47: ='Option source'!B63 -> 2280.1 | I47: ='Option source'!B80 -> 2084.21 | J47: =G47-2*H47+IF(B47="Butterfly",I47,0) -> -53.99 | K47: =ABS(E47-D47) -> 200 | L47: =K47-J47 -> 253.99 | M47: =IF(B47="Butterfly",MAX(J47,0),IF(C47="call","Unlimited",MAX(2*E47-D47+J47,J47,0))) -> 0 | N47: =IF(B47="Butterfly",IF(AND(J47>0,J47<K47),D47+J47,"n.a."),IF(C47="call",IF(AND(J47>0,J47<K47),D47+J47,"n.a."),IF(AND(K47>J47,2*E47-D47+J47>=0),2*E47-D47+J47,"n.a."))) -> n.a. | O47: =IF(B47="Butterfly",IF(AND(J47>0,J47<K47),F47-J47,"n.a."),IF(C47="call",IF(K47>J47,2*E47-D47-J47,"n.a."),IF(AND(J47>0,J47<K47),D47-J47,"n.a."))) -> n.a. | P47: =IF(AND(B47="Butterfly",J47>0,J47<K47),L47/J47,"n.a.") -> n.a. | Q47: =J47*'Model inputs'!$B$8 -> -5399 | R47: Outside standard debit bounds | S47: 39 | T47: 58
A48: 46281 | B48: Butterfly | C48: put | D48: 4400 | E48: 4600 | F48: 4800 | G48: ='Option source'!B524 -> 0.91 | H48: ='Option source'!B543 -> 1.62 | I48: ='Option source'!B562 -> 1.93 | J48: =G48-2*H48+IF(B48="Butterfly",I48,0) -> -0.4 | K48: =ABS(E48-D48) -> 200 | L48: =K48-J48 -> 200.4 | M48: =IF(B48="Butterfly",MAX(J48,0),IF(C48="call","Unlimited",MAX(2*E48-D48+J48,J48,0))) -> 0 | N48: =IF(B48="Butterfly",IF(AND(J48>0,J48<K48),D48+J48,"n.a."),IF(C48="call",IF(AND(J48>0,J48<K48),D48+J48,"n.a."),IF(AND(K48>J48,2*E48-D48+J48>=0),2*E48-D48+J48,"n.a."))) -> n.a. | O48: =IF(B48="Butterfly",IF(AND(J48>0,J48<K48),F48-J48,"n.a."),IF(C48="call",IF(K48>J48,2*E48-D48-J48,"n.a."),IF(AND(J48>0,J48<K48),D48-J48,"n.a."))) -> n.a. | P48: =IF(AND(B48="Butterfly",J48>0,J48<K48),L48/J48,"n.a.") -> n.a. | Q48: =J48*'Model inputs'!$B$8 -> -40 | R48: Outside standard debit bounds | S48: 519 | T48: 538
A49: 46281 | B49: Butterfly | C49: call | D49: 4200 | E49: 4400 | F49: 4600 | G49: ='Option source'!B25 -> 2587.49 | H49: ='Option source'!B44 -> 2422 | I49: ='Option source'!B63 -> 2280.1 | J49: =G49-2*H49+IF(B49="Butterfly",I49,0) -> 23.59 | K49: =ABS(E49-D49) -> 200 | L49: =K49-J49 -> 176.41 | M49: =IF(B49="Butterfly",MAX(J49,0),IF(C49="call","Unlimited",MAX(2*E49-D49+J49,J49,0))) -> 23.59 | N49: =IF(B49="Butterfly",IF(AND(J49>0,J49<K49),D49+J49,"n.a."),IF(C49="call",IF(AND(J49>0,J49<K49),D49+J49,"n.a."),IF(AND(K49>J49,2*E49-D49+J49>=0),2*E49-D49+J49,"n.a."))) -> 4223.59 | O49: =IF(B49="Butterfly",IF(AND(J49>0,J49<K49),F49-J49,"n.a."),IF(C49="call",IF(K49>J49,2*E49-D49-J49,"n.a."),IF(AND(J49>0,J49<K49),D49-J49,"n.a."))) -> 4576.41 | P49: =IF(AND(B49="Butterfly",J49>0,J49<K49),L49/J49,"n.a.") -> 7.4781687 | Q49: =J49*'Model inputs'!$B$8 -> 2359 | R49: Flagged leg data | S49: 20 | T49: 39
A50: 46281 | B50: 1x2 ratio | C50: call | D50: 6600 | E50: 6800 | G50: ='Option source'!B239 -> 478.22 | H50: ='Option source'!B258 -> 376.43 | J50: =G50-2*H50+IF(B50="Butterfly",I50,0) -> -274.64 | K50: =ABS(E50-D50) -> 200 | L50: =K50-J50 -> 474.64 | M50: =IF(B50="Butterfly",MAX(J50,0),IF(C50="call","Unlimited",MAX(2*E50-D50+J50,J50,0))) -> Unlimited | N50: =IF(B50="Butterfly",IF(AND(J50>0,J50<K50),D50+J50,"n.a."),IF(C50="call",IF(AND(J50>0,J50<K50),D50+J50,"n.a."),IF(AND(K50>J50,2*E50-D50+J50>=0),2*E50-D50+J50,"n.a."))) -> n.a. | O50: =IF(B50="Butterfly",IF(AND(J50>0,J50<K50),F50-J50,"n.a."),IF(C50="call",IF(K50>J50,2*E50-D50-J50,"n.a."),IF(AND(J50>0,J50<K50),D50-J50,"n.a."))) -> 7274.64 | P50: =IF(AND(B50="Butterfly",J50>0,J50<K50),L50/J50,"n.a.") -> n.a. | Q50: =J50*'Model inputs'!$B$8 -> -27464 | R50: Indicative only | S50: 234 | T50: 253
A51: 46281 | B51: 1x2 ratio | C51: put | D51: 7000 | E51: 6800 | G51: ='Option source'!B771 -> 427.03 | H51: ='Option source'!B752 -> 312.15 | J51: =G51-2*H51+IF(B51="Butterfly",I51,0) -> -197.27 | K51: =ABS(E51-D51) -> 200 | L51: =K51-J51 -> 397.27 | M51: =IF(B51="Butterfly",MAX(J51,0),IF(C51="call","Unlimited",MAX(2*E51-D51+J51,J51,0))) -> 6402.73 | N51: =IF(B51="Butterfly",IF(AND(J51>0,J51<K51),D51+J51,"n.a."),IF(C51="call",IF(AND(J51>0,J51<K51),D51+J51,"n.a."),IF(AND(K51>J51,2*E51-D51+J51>=0),2*E51-D51+J51,"n.a."))) -> 6402.73 | O51: =IF(B51="Butterfly",IF(AND(J51>0,J51<K51),F51-J51,"n.a."),IF(C51="call",IF(K51>J51,2*E51-D51-J51,"n.a."),IF(AND(J51>0,J51<K51),D51-J51,"n.a."))) -> n.a. | P51: =IF(AND(B51="Butterfly",J51>0,J51<K51),L51/J51,"n.a.") -> n.a. | Q51: =J51*'Model inputs'!$B$8 -> -19727 | R51: Indicative only | S51: 766 | T51: 747
A52: 46281 | B52: 1x2 ratio | C52: call | D52: 6400 | E52: 6600 | G52: ='Option source'!B220 -> 616.1 | H52: ='Option source'!B239 -> 478.22 | J52: =G52-2*H52+IF(B52="Butterfly",I52,0) -> -340.34 | K52: =ABS(E52-D52) -> 200 | L52: =K52-J52 -> 540.34 | M52: =IF(B52="Butterfly",MAX(J52,0),IF(C52="call","Unlimited",MAX(2*E52-D52+J52,J52,0))) -> Unlimited | N52: =IF(B52="Butterfly",IF(AND(J52>0,J52<K52),D52+J52,"n.a."),IF(C52="call",IF(AND(J52>0,J52<K52),D52+J52,"n.a."),IF(AND(K52>J52,2*E52-D52+J52>=0),2*E52-D52+J52,"n.a."))) -> n.a. | O52: =IF(B52="Butterfly",IF(AND(J52>0,J52<K52),F52-J52,"n.a."),IF(C52="call",IF(K52>J52,2*E52-D52-J52,"n.a."),IF(AND(J52>0,J52<K52),D52-J52,"n.a."))) -> 7140.34 | P52: =IF(AND(B52="Butterfly",J52>0,J52<K52),L52/J52,"n.a.") -> n.a. | Q52: =J52*'Model inputs'!$B$8 -> -34034 | R52: Indicative only | S52: 215 | T52: 234
A53: 46281 | B53: 1x2 ratio | C53: put | D53: 6800 | E53: 6600 | G53: ='Option source'!B752 -> 312.15 | H53: ='Option source'!B733 -> 222.45 | J53: =G53-2*H53+IF(B53="Butterfly",I53,0) -> -132.75 | K53: =ABS(E53-D53) -> 200 | L53: =K53-J53 -> 332.75 | M53: =IF(B53="Butterfly",MAX(J53,0),IF(C53="call","Unlimited",MAX(2*E53-D53+J53,J53,0))) -> 6267.25 | N53: =IF(B53="Butterfly",IF(AND(J53>0,J53<K53),D53+J53,"n.a."),IF(C53="call",IF(AND(J53>0,J53<K53),D53+J53,"n.a."),IF(AND(K53>J53,2*E53-D53+J53>=0),2*E53-D53+J53,"n.a."))) -> 6267.25 | O53: =IF(B53="Butterfly",IF(AND(J53>0,J53<K53),F53-J53,"n.a."),IF(C53="call",IF(K53>J53,2*E53-D53-J53,"n.a."),IF(AND(J53>0,J53<K53),D53-J53,"n.a."))) -> n.a. | P53: =IF(AND(B53="Butterfly",J53>0,J53<K53),L53/J53,"n.a.") -> n.a. | Q53: =J53*'Model inputs'!$B$8 -> -13275 | R53: Indicative only | S53: 747 | T53: 728
A54: 46281 | B54: 1x2 ratio | C54: call | D54: 6800 | E54: 7000 | G54: ='Option source'!B258 -> 376.43 | H54: ='Option source'!B277 -> 289.65 | J54: =G54-2*H54+IF(B54="Butterfly",I54,0) -> -202.87 | K54: =ABS(E54-D54) -> 200 | L54: =K54-J54 -> 402.87 | M54: =IF(B54="Butterfly",MAX(J54,0),IF(C54="call","Unlimited",MAX(2*E54-D54+J54,J54,0))) -> Unlimited | N54: =IF(B54="Butterfly",IF(AND(J54>0,J54<K54),D54+J54,"n.a."),IF(C54="call",IF(AND(J54>0,J54<K54),D54+J54,"n.a."),IF(AND(K54>J54,2*E54-D54+J54>=0),2*E54-D54+J54,"n.a."))) -> n.a. | O54: =IF(B54="Butterfly",IF(AND(J54>0,J54<K54),F54-J54,"n.a."),IF(C54="call",IF(K54>J54,2*E54-D54-J54,"n.a."),IF(AND(J54>0,J54<K54),D54-J54,"n.a."))) -> 7402.87 | P54: =IF(AND(B54="Butterfly",J54>0,J54<K54),L54/J54,"n.a.") -> n.a. | Q54: =J54*'Model inputs'!$B$8 -> -20287 | R54: Indicative only | S54: 253 | T54: 272
A55: 46281 | B55: 1x2 ratio | C55: put | D55: 7200 | E55: 7000 | G55: ='Option source'!B790 -> 550.35 | H55: ='Option source'!B771 -> 427.03 | J55: =G55-2*H55+IF(B55="Butterfly",I55,0) -> -303.71 | K55: =ABS(E55-D55) -> 200 | L55: =K55-J55 -> 503.71 | M55: =IF(B55="Butterfly",MAX(J55,0),IF(C55="call","Unlimited",MAX(2*E55-D55+J55,J55,0))) -> 6496.29 | N55: =IF(B55="Butterfly",IF(AND(J55>0,J55<K55),D55+J55,"n.a."),IF(C55="call",IF(AND(J55>0,J55<K55),D55+J55,"n.a."),IF(AND(K55>J55,2*E55-D55+J55>=0),2*E55-D55+J55,"n.a."))) -> 6496.29 | O55: =IF(B55="Butterfly",IF(AND(J55>0,J55<K55),F55-J55,"n.a."),IF(C55="call",IF(K55>J55,2*E55-D55-J55,"n.a."),IF(AND(J55>0,J55<K55),D55-J55,"n.a."))) -> n.a. | P55: =IF(AND(B55="Butterfly",J55>0,J55<K55),L55/J55,"n.a.") -> n.a. | Q55: =J55*'Model inputs'!$B$8 -> -30371 | R55: Indicative only | S55: 785 | T55: 766
A56: 46281 | B56: 1x2 ratio | C56: put | D56: 6600 | E56: 6400 | G56: ='Option source'!B733 -> 222.45 | H56: ='Option source'!B714 -> 150.25 | J56: =G56-2*H56+IF(B56="Butterfly",I56,0) -> -78.05 | K56: =ABS(E56-D56) -> 200 | L56: =K56-J56 -> 278.05 | M56: =IF(B56="Butterfly",MAX(J56,0),IF(C56="call","Unlimited",MAX(2*E56-D56+J56,J56,0))) -> 6121.95 | N56: =IF(B56="Butterfly",IF(AND(J56>0,J56<K56),D56+J56,"n.a."),IF(C56="call",IF(AND(J56>0,J56<K56),D56+J56,"n.a."),IF(AND(K56>J56,2*E56-D56+J56>=0),2*E56-D56+J56,"n.a."))) -> 6121.95 | O56: =IF(B56="Butterfly",IF(AND(J56>0,J56<K56),F56-J56,"n.a."),IF(C56="call",IF(K56>J56,2*E56-D56-J56,"n.a."),IF(AND(J56>0,J56<K56),D56-J56,"n.a."))) -> n.a. | P56: =IF(AND(B56="Butterfly",J56>0,J56<K56),L56/J56,"n.a.") -> n.a. | Q56: =J56*'Model inputs'!$B$8 -> -7805 | R56: Indicative only | S56: 728 | T56: 709
A57: 46281 | B57: 1x2 ratio | C57: call | D57: 7000 | E57: 7200 | G57: ='Option source'!B277 -> 289.65 | H57: ='Option source'!B296 -> 213.18 | J57: =G57-2*H57+IF(B57="Butterfly",I57,0) -> -136.71 | K57: =ABS(E57-D57) -> 200 | L57: =K57-J57 -> 336.71 | M57: =IF(B57="Butterfly",MAX(J57,0),IF(C57="call","Unlimited",MAX(2*E57-D57+J57,J57,0))) -> Unlimited | N57: =IF(B57="Butterfly",IF(AND(J57>0,J57<K57),D57+J57,"n.a."),IF(C57="call",IF(AND(J57>0,J57<K57),D57+J57,"n.a."),IF(AND(K57>J57,2*E57-D57+J57>=0),2*E57-D57+J57,"n.a."))) -> n.a. | O57: =IF(B57="Butterfly",IF(AND(J57>0,J57<K57),F57-J57,"n.a."),IF(C57="call",IF(K57>J57,2*E57-D57-J57,"n.a."),IF(AND(J57>0,J57<K57),D57-J57,"n.a."))) -> 7536.71 | P57: =IF(AND(B57="Butterfly",J57>0,J57<K57),L57/J57,"n.a.") -> n.a. | Q57: =J57*'Model inputs'!$B$8 -> -13671 | R57: Indicative only | S57: 272 | T57: 291
A58: 46281 | B58: 1x2 ratio | C58: put | D58: 7400 | E58: 7200 | G58: ='Option source'!B809 -> 677.83 | H58: ='Option source'!B790 -> 550.35 | J58: =G58-2*H58+IF(B58="Butterfly",I58,0) -> -422.87 | K58: =ABS(E58-D58) -> 200 | L58: =K58-J58 -> 622.87 | M58: =IF(B58="Butterfly",MAX(J58,0),IF(C58="call","Unlimited",MAX(2*E58-D58+J58,J58,0))) -> 6577.13 | N58: =IF(B58="Butterfly",IF(AND(J58>0,J58<K58),D58+J58,"n.a."),IF(C58="call",IF(AND(J58>0,J58<K58),D58+J58,"n.a."),IF(AND(K58>J58,2*E58-D58+J58>=0),2*E58-D58+J58,"n.a."))) -> 6577.13 | O58: =IF(B58="Butterfly",IF(AND(J58>0,J58<K58),F58-J58,"n.a."),IF(C58="call",IF(K58>J58,2*E58-D58-J58,"n.a."),IF(AND(J58>0,J58<K58),D58-J58,"n.a."))) -> n.a. | P58: =IF(AND(B58="Butterfly",J58>0,J58<K58),L58/J58,"n.a.") -> n.a. | Q58: =J58*'Model inputs'!$B$8 -> -42287 | R58: Indicative only | S58: 804 | T58: 785
A59: 46281 | B59: 1x2 ratio | C59: put | D59: 6400 | E59: 6200 | G59: ='Option source'!B714 -> 150.25 | H59: ='Option source'!B695 -> 97.41 | J59: =G59-2*H59+IF(B59="Butterfly",I59,0) -> -44.57 | K59: =ABS(E59-D59) -> 200 | L59: =K59-J59 -> 244.57 | M59: =IF(B59="Butterfly",MAX(J59,0),IF(C59="call","Unlimited",MAX(2*E59-D59+J59,J59,0))) -> 5955.43 | N59: =IF(B59="Butterfly",IF(AND(J59>0,J59<K59),D59+J59,"n.a."),IF(C59="call",IF(AND(J59>0,J59<K59),D59+J59,"n.a."),IF(AND(K59>J59,2*E59-D59+J59>=0),2*E59-D59+J59,"n.a."))) -> 5955.43 | O59: =IF(B59="Butterfly",IF(AND(J59>0,J59<K59),F59-J59,"n.a."),IF(C59="call",IF(K59>J59,2*E59-D59-J59,"n.a."),IF(AND(J59>0,J59<K59),D59-J59,"n.a."))) -> n.a. | P59: =IF(AND(B59="Butterfly",J59>0,J59<K59),L59/J59,"n.a.") -> n.a. | Q59: =J59*'Model inputs'!$B$8 -> -4457 | R59: Indicative only | S59: 709 | T59: 690
A60: 46281 | B60: 1x2 ratio | C60: call | D60: 7200 | E60: 7400 | G60: ='Option source'!B296 -> 213.18 | H60: ='Option source'!B315 -> 157.14 | J60: =G60-2*H60+IF(B60="Butterfly",I60,0) -> -101.1 | K60: =ABS(E60-D60) -> 200 | L60: =K60-J60 -> 301.1 | M60: =IF(B60="Butterfly",MAX(J60,0),IF(C60="call","Unlimited",MAX(2*E60-D60+J60,J60,0))) -> Unlimited | N60: =IF(B60="Butterfly",IF(AND(J60>0,J60<K60),D60+J60,"n.a."),IF(C60="call",IF(AND(J60>0,J60<K60),D60+J60,"n.a."),IF(AND(K60>J60,2*E60-D60+J60>=0),2*E60-D60+J60,"n.a."))) -> n.a. | O60: =IF(B60="Butterfly",IF(AND(J60>0,J60<K60),F60-J60,"n.a."),IF(C60="call",IF(K60>J60,2*E60-D60-J60,"n.a."),IF(AND(J60>0,J60<K60),D60-J60,"n.a."))) -> 7701.1 | P60: =IF(AND(B60="Butterfly",J60>0,J60<K60),L60/J60,"n.a.") -> n.a. | Q60: =J60*'Model inputs'!$B$8 -> -10110 | R60: Indicative only | S60: 291 | T60: 310
A61: 46281 | B61: 1x2 ratio | C61: put | D61: 7600 | E61: 7400 | G61: ='Option source'!B828 -> 857 | H61: ='Option source'!B809 -> 677.83 | J61: =G61-2*H61+IF(B61="Butterfly",I61,0) -> -498.66 | K61: =ABS(E61-D61) -> 200 | L61: =K61-J61 -> 698.66 | M61: =IF(B61="Butterfly",MAX(J61,0),IF(C61="call","Unlimited",MAX(2*E61-D61+J61,J61,0))) -> 6701.34 | N61: =IF(B61="Butterfly",IF(AND(J61>0,J61<K61),D61+J61,"n.a."),IF(C61="call",IF(AND(J61>0,J61<K61),D61+J61,"n.a."),IF(AND(K61>J61,2*E61-D61+J61>=0),2*E61-D61+J61,"n.a."))) -> 6701.34 | O61: =IF(B61="Butterfly",IF(AND(J61>0,J61<K61),F61-J61,"n.a."),IF(C61="call",IF(K61>J61,2*E61-D61-J61,"n.a."),IF(AND(J61>0,J61<K61),D61-J61,"n.a."))) -> n.a. | P61: =IF(AND(B61="Butterfly",J61>0,J61<K61),L61/J61,"n.a.") -> n.a. | Q61: =J61*'Model inputs'!$B$8 -> -49866 | R61: Indicative only | S61: 823 | T61: 804
A62: 46281 | B62: 1x2 ratio | C62: put | D62: 6200 | E62: 6000 | G62: ='Option source'!B695 -> 97.41 | H62: ='Option source'!B676 -> 56.82 | J62: =G62-2*H62+IF(B62="Butterfly",I62,0) -> -16.23 | K62: =ABS(E62-D62) -> 200 | L62: =K62-J62 -> 216.23 | M62: =IF(B62="Butterfly",MAX(J62,0),IF(C62="call","Unlimited",MAX(2*E62-D62+J62,J62,0))) -> 5783.77 | N62: =IF(B62="Butterfly",IF(AND(J62>0,J62<K62),D62+J62,"n.a."),IF(C62="call",IF(AND(J62>0,J62<K62),D62+J62,"n.a."),IF(AND(K62>J62,2*E62-D62+J62>=0),2*E62-D62+J62,"n.a."))) -> 5783.77 | O62: =IF(B62="Butterfly",IF(AND(J62>0,J62<K62),F62-J62,"n.a."),IF(C62="call",IF(K62>J62,2*E62-D62-J62,"n.a."),IF(AND(J62>0,J62<K62),D62-J62,"n.a."))) -> n.a. | P62: =IF(AND(B62="Butterfly",J62>0,J62<K62),L62/J62,"n.a.") -> n.a. | Q62: =J62*'Model inputs'!$B$8 -> -1623 | R62: Indicative only | S62: 690 | T62: 671
A63: 46281 | B63: 1x2 ratio | C63: call | D63: 7400 | E63: 7600 | G63: ='Option source'!B315 -> 157.14 | H63: ='Option source'!B334 -> 107.66 | J63: =G63-2*H63+IF(B63="Butterfly",I63,0) -> -58.18 | K63: =ABS(E63-D63) -> 200 | L63: =K63-J63 -> 258.18 | M63: =IF(B63="Butterfly",MAX(J63,0),IF(C63="call","Unlimited",MAX(2*E63-D63+J63,J63,0))) -> Unlimited | N63: =IF(B63="Butterfly",IF(AND(J63>0,J63<K63),D63+J63,"n.a."),IF(C63="call",IF(AND(J63>0,J63<K63),D63+J63,"n.a."),IF(AND(K63>J63,2*E63-D63+J63>=0),2*E63-D63+J63,"n.a."))) -> n.a. | O63: =IF(B63="Butterfly",IF(AND(J63>0,J63<K63),F63-J63,"n.a."),IF(C63="call",IF(K63>J63,2*E63-D63-J63,"n.a."),IF(AND(J63>0,J63<K63),D63-J63,"n.a."))) -> 7858.18 | P63: =IF(AND(B63="Butterfly",J63>0,J63<K63),L63/J63,"n.a.") -> n.a. | Q63: =J63*'Model inputs'!$B$8 -> -5818 | R63: Indicative only | S63: 310 | T63: 329
A64: 46281 | B64: 1x2 ratio | C64: put | D64: 6000 | E64: 5800 | G64: ='Option source'!B676 -> 56.82 | H64: ='Option source'!B657 -> 31.98 | J64: =G64-2*H64+IF(B64="Butterfly",I64,0) -> -7.14 | K64: =ABS(E64-D64) -> 200 | L64: =K64-J64 -> 207.14 | M64: =IF(B64="Butterfly",MAX(J64,0),IF(C64="call","Unlimited",MAX(2*E64-D64+J64,J64,0))) -> 5592.86 | N64: =IF(B64="Butterfly",IF(AND(J64>0,J64<K64),D64+J64,"n.a."),IF(C64="call",IF(AND(J64>0,J64<K64),D64+J64,"n.a."),IF(AND(K64>J64,2*E64-D64+J64>=0),2*E64-D64+J64,"n.a."))) -> 5592.86 | O64: =IF(B64="Butterfly",IF(AND(J64>0,J64<K64),F64-J64,"n.a."),IF(C64="call",IF(K64>J64,2*E64-D64-J64,"n.a."),IF(AND(J64>0,J64<K64),D64-J64,"n.a."))) -> n.a. | P64: =IF(AND(B64="Butterfly",J64>0,J64<K64),L64/J64,"n.a.") -> n.a. | Q64: =J64*'Model inputs'!$B$8 -> -714 | R64: Indicative only | S64: 671 | T64: 652
A65: 46281 | B65: 1x2 ratio | C65: call | D65: 7600 | E65: 7800 | G65: ='Option source'!B334 -> 107.66 | H65: ='Option source'!B353 -> 75.86 | J65: =G65-2*H65+IF(B65="Butterfly",I65,0) -> -44.06 | K65: =ABS(E65-D65) -> 200 | L65: =K65-J65 -> 244.06 | M65: =IF(B65="Butterfly",MAX(J65,0),IF(C65="call","Unlimited",MAX(2*E65-D65+J65,J65,0))) -> Unlimited | N65: =IF(B65="Butterfly",IF(AND(J65>0,J65<K65),D65+J65,"n.a."),IF(C65="call",IF(AND(J65>0,J65<K65),D65+J65,"n.a."),IF(AND(K65>J65,2*E65-D65+J65>=0),2*E65-D65+J65,"n.a."))) -> n.a. | O65: =IF(B65="Butterfly",IF(AND(J65>0,J65<K65),F65-J65,"n.a."),IF(C65="call",IF(K65>J65,2*E65-D65-J65,"n.a."),IF(AND(J65>0,J65<K65),D65-J65,"n.a."))) -> 8044.06 | P65: =IF(AND(B65="Butterfly",J65>0,J65<K65),L65/J65,"n.a.") -> n.a. | Q65: =J65*'Model inputs'!$B$8 -> -4406 | R65: Indicative only | S65: 329 | T65: 348
A66: 46281 | B66: 1x2 ratio | C66: put | D66: 5800 | E66: 5600 | G66: ='Option source'!B657 -> 31.98 | H66: ='Option source'!B638 -> 17.15 | J66: =G66-2*H66+IF(B66="Butterfly",I66,0) -> -2.32 | K66: =ABS(E66-D66) -> 200 | L66: =K66-J66 -> 202.32 | M66: =IF(B66="Butterfly",MAX(J66,0),IF(C66="call","Unlimited",MAX(2*E66-D66+J66,J66,0))) -> 5397.68 | N66: =IF(B66="Butterfly",IF(AND(J66>0,J66<K66),D66+J66,"n.a."),IF(C66="call",IF(AND(J66>0,J66<K66),D66+J66,"n.a."),IF(AND(K66>J66,2*E66-D66+J66>=0),2*E66-D66+J66,"n.a."))) -> 5397.68 | O66: =IF(B66="Butterfly",IF(AND(J66>0,J66<K66),F66-J66,"n.a."),IF(C66="call",IF(K66>J66,2*E66-D66-J66,"n.a."),IF(AND(J66>0,J66<K66),D66-J66,"n.a."))) -> n.a. | P66: =IF(AND(B66="Butterfly",J66>0,J66<K66),L66/J66,"n.a.") -> n.a. | Q66: =J66*'Model inputs'!$B$8 -> -232 | R66: Indicative only | S66: 652 | T66: 633
A67: 46281 | B67: 1x2 ratio | C67: call | D67: 7800 | E67: 8000 | G67: ='Option source'!B353 -> 75.86 | H67: ='Option source'!B372 -> 54.71 | J67: =G67-2*H67+IF(B67="Butterfly",I67,0) -> -33.56 | K67: =ABS(E67-D67) -> 200 | L67: =K67-J67 -> 233.56 | M67: =IF(B67="Butterfly",MAX(J67,0),IF(C67="call","Unlimited",MAX(2*E67-D67+J67,J67,0))) -> Unlimited | N67: =IF(B67="Butterfly",IF(AND(J67>0,J67<K67),D67+J67,"n.a."),IF(C67="call",IF(AND(J67>0,J67<K67),D67+J67,"n.a."),IF(AND(K67>J67,2*E67-D67+J67>=0),2*E67-D67+J67,"n.a."))) -> n.a. | O67: =IF(B67="Butterfly",IF(AND(J67>0,J67<K67),F67-J67,"n.a."),IF(C67="call",IF(K67>J67,2*E67-D67-J67,"n.a."),IF(AND(J67>0,J67<K67),D67-J67,"n.a."))) -> 8233.56 | P67: =IF(AND(B67="Butterfly",J67>0,J67<K67),L67/J67,"n.a.") -> n.a. | Q67: =J67*'Model inputs'!$B$8 -> -3356 | R67: Indicative only | S67: 348 | T67: 367
A68: 46281 | B68: 1x2 ratio | C68: put | D68: 5600 | E68: 5400 | G68: ='Option source'!B638 -> 17.15 | H68: ='Option source'!B619 -> 9.02 | J68: =G68-2*H68+IF(B68="Butterfly",I68,0) -> -0.89 | K68: =ABS(E68-D68) -> 200 | L68: =K68-J68 -> 200.89 | M68: =IF(B68="Butterfly",MAX(J68,0),IF(C68="call","Unlimited",MAX(2*E68-D68+J68,J68,0))) -> 5199.11 | N68: =IF(B68="Butterfly",IF(AND(J68>0,J68<K68),D68+J68,"n.a."),IF(C68="call",IF(AND(J68>0,J68<K68),D68+J68,"n.a."),IF(AND(K68>J68,2*E68-D68+J68>=0),2*E68-D68+J68,"n.a."))) -> 5199.11 | O68: =IF(B68="Butterfly",IF(AND(J68>0,J68<K68),F68-J68,"n.a."),IF(C68="call",IF(K68>J68,2*E68-D68-J68,"n.a."),IF(AND(J68>0,J68<K68),D68-J68,"n.a."))) -> n.a. | P68: =IF(AND(B68="Butterfly",J68>0,J68<K68),L68/J68,"n.a.") -> n.a. | Q68: =J68*'Model inputs'!$B$8 -> -89 | R68: Indicative only | S68: 633 | T68: 614
A69: 46281 | B69: 1x2 ratio | C69: call | D69: 8000 | E69: 8300 | G69: ='Option source'!B372 -> 54.71 | H69: ='Option source'!B391 -> 32.2 | J69: =G69-2*H69+IF(B69="Butterfly",I69,0) -> -9.69 | K69: =ABS(E69-D69) -> 300 | L69: =K69-J69 -> 309.69 | M69: =IF(B69="Butterfly",MAX(J69,0),IF(C69="call","Unlimited",MAX(2*E69-D69+J69,J69,0))) -> Unlimited | N69: =IF(B69="Butterfly",IF(AND(J69>0,J69<K69),D69+J69,"n.a."),IF(C69="call",IF(AND(J69>0,J69<K69),D69+J69,"n.a."),IF(AND(K69>J69,2*E69-D69+J69>=0),2*E69-D69+J69,"n.a."))) -> n.a. | O69: =IF(B69="Butterfly",IF(AND(J69>0,J69<K69),F69-J69,"n.a."),IF(C69="call",IF(K69>J69,2*E69-D69-J69,"n.a."),IF(AND(J69>0,J69<K69),D69-J69,"n.a."))) -> 8609.69 | P69: =IF(AND(B69="Butterfly",J69>0,J69<K69),L69/J69,"n.a.") -> n.a. | Q69: =J69*'Model inputs'!$B$8 -> -969 | R69: Indicative only | S69: 367 | T69: 386
A70: 46281 | B70: 1x2 ratio | C70: put | D70: 5400 | E70: 5200 | G70: ='Option source'!B619 -> 9.02 | H70: ='Option source'!B600 -> 6.01 | J70: =G70-2*H70+IF(B70="Butterfly",I70,0) -> -3 | K70: =ABS(E70-D70) -> 200 | L70: =K70-J70 -> 203 | M70: =IF(B70="Butterfly",MAX(J70,0),IF(C70="call","Unlimited",MAX(2*E70-D70+J70,J70,0))) -> 4997 | N70: =IF(B70="Butterfly",IF(AND(J70>0,J70<K70),D70+J70,"n.a."),IF(C70="call",IF(AND(J70>0,J70<K70),D70+J70,"n.a."),IF(AND(K70>J70,2*E70-D70+J70>=0),2*E70-D70+J70,"n.a."))) -> 4997 | O70: =IF(B70="Butterfly",IF(AND(J70>0,J70<K70),F70-J70,"n.a."),IF(C70="call",IF(K70>J70,2*E70-D70-J70,"n.a."),IF(AND(J70>0,J70<K70),D70-J70,"n.a."))) -> n.a. | P70: =IF(AND(B70="Butterfly",J70>0,J70<K70),L70/J70,"n.a.") -> n.a. | Q70: =J70*'Model inputs'!$B$8 -> -300 | R70: Indicative only | S70: 614 | T70: 595
A71: 46281 | B71: 1x2 ratio | C71: put | D71: 5200 | E71: 5000 | G71: ='Option source'!B600 -> 6.01 | H71: ='Option source'!B581 -> 3.18 | J71: =G71-2*H71+IF(B71="Butterfly",I71,0) -> -0.35 | K71: =ABS(E71-D71) -> 200 | L71: =K71-J71 -> 200.35 | M71: =IF(B71="Butterfly",MAX(J71,0),IF(C71="call","Unlimited",MAX(2*E71-D71+J71,J71,0))) -> 4799.65 | N71: =IF(B71="Butterfly",IF(AND(J71>0,J71<K71),D71+J71,"n.a."),IF(C71="call",IF(AND(J71>0,J71<K71),D71+J71,"n.a."),IF(AND(K71>J71,2*E71-D71+J71>=0),2*E71-D71+J71,"n.a."))) -> 4799.65 | O71: =IF(B71="Butterfly",IF(AND(J71>0,J71<K71),F71-J71,"n.a."),IF(C71="call",IF(K71>J71,2*E71-D71-J71,"n.a."),IF(AND(J71>0,J71<K71),D71-J71,"n.a."))) -> n.a. | P71: =IF(AND(B71="Butterfly",J71>0,J71<K71),L71/J71,"n.a.") -> n.a. | Q71: =J71*'Model inputs'!$B$8 -> -35 | R71: Indicative only | S71: 595 | T71: 576
A72: 46281 | B72: 1x2 ratio | C72: call | D72: 8300 | E72: 8600 | G72: ='Option source'!B391 -> 32.2 | H72: ='Option source'!B410 -> 17.94 | J72: =G72-2*H72+IF(B72="Butterfly",I72,0) -> -3.68 | K72: =ABS(E72-D72) -> 300 | L72: =K72-J72 -> 303.68 | M72: =IF(B72="Butterfly",MAX(J72,0),IF(C72="call","Unlimited",MAX(2*E72-D72+J72,J72,0))) -> Unlimited | N72: =IF(B72="Butterfly",IF(AND(J72>0,J72<K72),D72+J72,"n.a."),IF(C72="call",IF(AND(J72>0,J72<K72),D72+J72,"n.a."),IF(AND(K72>J72,2*E72-D72+J72>=0),2*E72-D72+J72,"n.a."))) -> n.a. | O72: =IF(B72="Butterfly",IF(AND(J72>0,J72<K72),F72-J72,"n.a."),IF(C72="call",IF(K72>J72,2*E72-D72-J72,"n.a."),IF(AND(J72>0,J72<K72),D72-J72,"n.a."))) -> 8903.68 | P72: =IF(AND(B72="Butterfly",J72>0,J72<K72),L72/J72,"n.a.") -> n.a. | Q72: =J72*'Model inputs'!$B$8 -> -368 | R72: Indicative only | S72: 386 | T72: 405
A73: 46281 | B73: 1x2 ratio | C73: put | D73: 5000 | E73: 4800 | G73: ='Option source'!B581 -> 3.18 | H73: ='Option source'!B562 -> 1.93 | J73: =G73-2*H73+IF(B73="Butterfly",I73,0) -> -0.68 | K73: =ABS(E73-D73) -> 200 | L73: =K73-J73 -> 200.68 | M73: =IF(B73="Butterfly",MAX(J73,0),IF(C73="call","Unlimited",MAX(2*E73-D73+J73,J73,0))) -> 4599.32 | N73: =IF(B73="Butterfly",IF(AND(J73>0,J73<K73),D73+J73,"n.a."),IF(C73="call",IF(AND(J73>0,J73<K73),D73+J73,"n.a."),IF(AND(K73>J73,2*E73-D73+J73>=0),2*E73-D73+J73,"n.a."))) -> 4599.32 | O73: =IF(B73="Butterfly",IF(AND(J73>0,J73<K73),F73-J73,"n.a."),IF(C73="call",IF(K73>J73,2*E73-D73-J73,"n.a."),IF(AND(J73>0,J73<K73),D73-J73,"n.a."))) -> n.a. | P73: =IF(AND(B73="Butterfly",J73>0,J73<K73),L73/J73,"n.a.") -> n.a. | Q73: =J73*'Model inputs'!$B$8 -> -68 | R73: Indicative only | S73: 576 | T73: 557
A74: 46281 | B74: 1x2 ratio | C74: call | D74: 8600 | E74: 8900 | G74: ='Option source'!B410 -> 17.94 | H74: ='Option source'!B429 -> 9.99 | J74: =G74-2*H74+IF(B74="Butterfly",I74,0) -> -2.04 | K74: =ABS(E74-D74) -> 300 | L74: =K74-J74 -> 302.04 | M74: =IF(B74="Butterfly",MAX(J74,0),IF(C74="call","Unlimited",MAX(2*E74-D74+J74,J74,0))) -> Unlimited | N74: =IF(B74="Butterfly",IF(AND(J74>0,J74<K74),D74+J74,"n.a."),IF(C74="call",IF(AND(J74>0,J74<K74),D74+J74,"n.a."),IF(AND(K74>J74,2*E74-D74+J74>=0),2*E74-D74+J74,"n.a."))) -> n.a. | O74: =IF(B74="Butterfly",IF(AND(J74>0,J74<K74),F74-J74,"n.a."),IF(C74="call",IF(K74>J74,2*E74-D74-J74,"n.a."),IF(AND(J74>0,J74<K74),D74-J74,"n.a."))) -> 9202.04 | P74: =IF(AND(B74="Butterfly",J74>0,J74<K74),L74/J74,"n.a.") -> n.a. | Q74: =J74*'Model inputs'!$B$8 -> -204 | R74: Indicative only | S74: 405 | T74: 424
A75: 46281 | B75: 1x2 ratio | C75: put | D75: 4800 | E75: 4600 | G75: ='Option source'!B562 -> 1.93 | H75: ='Option source'!B543 -> 1.62 | J75: =G75-2*H75+IF(B75="Butterfly",I75,0) -> -1.31 | K75: =ABS(E75-D75) -> 200 | L75: =K75-J75 -> 201.31 | M75: =IF(B75="Butterfly",MAX(J75,0),IF(C75="call","Unlimited",MAX(2*E75-D75+J75,J75,0))) -> 4398.69 | N75: =IF(B75="Butterfly",IF(AND(J75>0,J75<K75),D75+J75,"n.a."),IF(C75="call",IF(AND(J75>0,J75<K75),D75+J75,"n.a."),IF(AND(K75>J75,2*E75-D75+J75>=0),2*E75-D75+J75,"n.a."))) -> 4398.69 | O75: =IF(B75="Butterfly",IF(AND(J75>0,J75<K75),F75-J75,"n.a."),IF(C75="call",IF(K75>J75,2*E75-D75-J75,"n.a."),IF(AND(J75>0,J75<K75),D75-J75,"n.a."))) -> n.a. | P75: =IF(AND(B75="Butterfly",J75>0,J75<K75),L75/J75,"n.a.") -> n.a. | Q75: =J75*'Model inputs'!$B$8 -> -131 | R75: Indicative only | S75: 557 | T75: 538
A76: 46281 | B76: 1x2 ratio | C76: put | D76: 4600 | E76: 4400 | G76: ='Option source'!B543 -> 1.62 | H76: ='Option source'!B524 -> 0.91 | J76: =G76-2*H76+IF(B76="Butterfly",I76,0) -> -0.2 | K76: =ABS(E76-D76) -> 200 | L76: =K76-J76 -> 200.2 | M76: =IF(B76="Butterfly",MAX(J76,0),IF(C76="call","Unlimited",MAX(2*E76-D76+J76,J76,0))) -> 4199.8 | N76: =IF(B76="Butterfly",IF(AND(J76>0,J76<K76),D76+J76,"n.a."),IF(C76="call",IF(AND(J76>0,J76<K76),D76+J76,"n.a."),IF(AND(K76>J76,2*E76-D76+J76>=0),2*E76-D76+J76,"n.a."))) -> 4199.8 | O76: =IF(B76="Butterfly",IF(AND(J76>0,J76<K76),F76-J76,"n.a."),IF(C76="call",IF(K76>J76,2*E76-D76-J76,"n.a."),IF(AND(J76>0,J76<K76),D76-J76,"n.a."))) -> n.a. | P76: =IF(AND(B76="Butterfly",J76>0,J76<K76),L76/J76,"n.a.") -> n.a. | Q76: =J76*'Model inputs'!$B$8 -> -20 | R76: Indicative only | S76: 538 | T76: 519
A77: 46281 | B77: 1x2 ratio | C77: call | D77: 8900 | E77: 9200 | G77: ='Option source'!B429 -> 9.99 | H77: ='Option source'!B448 -> 3.53 | J77: =G77-2*H77+IF(B77="Butterfly",I77,0) -> 2.93 | K77: =ABS(E77-D77) -> 300 | L77: =K77-J77 -> 297.07 | M77: =IF(B77="Butterfly",MAX(J77,0),IF(C77="call","Unlimited",MAX(2*E77-D77+J77,J77,0))) -> Unlimited | N77: =IF(B77="Butterfly",IF(AND(J77>0,J77<K77),D77+J77,"n.a."),IF(C77="call",IF(AND(J77>0,J77<K77),D77+J77,"n.a."),IF(AND(K77>J77,2*E77-D77+J77>=0),2*E77-D77+J77,"n.a."))) -> 8902.93 | O77: =IF(B77="Butterfly",IF(AND(J77>0,J77<K77),F77-J77,"n.a."),IF(C77="call",IF(K77>J77,2*E77-D77-J77,"n.a."),IF(AND(J77>0,J77<K77),D77-J77,"n.a."))) -> 9497.07 | P77: =IF(AND(B77="Butterfly",J77>0,J77<K77),L77/J77,"n.a.") -> n.a. | Q77: =J77*'Model inputs'!$B$8 -> 293 | R77: Indicative only | S77: 424 | T77: 443
A78: 46281 | B78: 1x2 ratio | C78: put | D78: 4400 | E78: 4200 | G78: ='Option source'!B524 -> 0.91 | H78: ='Option source'!B505 -> 1.21 | J78: =G78-2*H78+IF(B78="Butterfly",I78,0) -> -1.51 | K78: =ABS(E78-D78) -> 200 | L78: =K78-J78 -> 201.51 | M78: =IF(B78="Butterfly",MAX(J78,0),IF(C78="call","Unlimited",MAX(2*E78-D78+J78,J78,0))) -> 3998.49 | N78: =IF(B78="Butterfly",IF(AND(J78>0,J78<K78),D78+J78,"n.a."),IF(C78="call",IF(AND(J78>0,J78<K78),D78+J78,"n.a."),IF(AND(K78>J78,2*E78-D78+J78>=0),2*E78-D78+J78,"n.a."))) -> 3998.49 | O78: =IF(B78="Butterfly",IF(AND(J78>0,J78<K78),F78-J78,"n.a."),IF(C78="call",IF(K78>J78,2*E78-D78-J78,"n.a."),IF(AND(J78>0,J78<K78),D78-J78,"n.a."))) -> n.a. | P78: =IF(AND(B78="Butterfly",J78>0,J78<K78),L78/J78,"n.a.") -> n.a. | Q78: =J78*'Model inputs'!$B$8 -> -151 | R78: Indicative only | S78: 519 | T78: 500
A79: 46281 | B79: 1x2 ratio | C79: call | D79: 9200 | E79: 9500 | G79: ='Option source'!B448 -> 3.53 | H79: ='Option source'!B467 -> 3.44 | J79: =G79-2*H79+IF(B79="Butterfly",I79,0) -> -3.35 | K79: =ABS(E79-D79) -> 300 | L79: =K79-J79 -> 303.35 | M79: =IF(B79="Butterfly",MAX(J79,0),IF(C79="call","Unlimited",MAX(2*E79-D79+J79,J79,0))) -> Unlimited | N79: =IF(B79="Butterfly",IF(AND(J79>0,J79<K79),D79+J79,"n.a."),IF(C79="call",IF(AND(J79>0,J79<K79),D79+J79,"n.a."),IF(AND(K79>J79,2*E79-D79+J79>=0),2*E79-D79+J79,"n.a."))) -> n.a. | O79: =IF(B79="Butterfly",IF(AND(J79>0,J79<K79),F79-J79,"n.a."),IF(C79="call",IF(K79>J79,2*E79-D79-J79,"n.a."),IF(AND(J79>0,J79<K79),D79-J79,"n.a."))) -> 9803.35 | P79: =IF(AND(B79="Butterfly",J79>0,J79<K79),L79/J79,"n.a.") -> n.a. | Q79: =J79*'Model inputs'!$B$8 -> -335 | R79: Indicative only | S79: 443 | T79: 462
A80: 46281 | B80: 1x2 ratio | C80: call | D80: 9500 | E80: 9900 | G80: ='Option source'!B467 -> 3.44 | H80: ='Option source'!B486 -> 2.06 | J80: =G80-2*H80+IF(B80="Butterfly",I80,0) -> -0.68 | K80: =ABS(E80-D80) -> 400 | L80: =K80-J80 -> 400.68 | M80: =IF(B80="Butterfly",MAX(J80,0),IF(C80="call","Unlimited",MAX(2*E80-D80+J80,J80,0))) -> Unlimited | N80: =IF(B80="Butterfly",IF(AND(J80>0,J80<K80),D80+J80,"n.a."),IF(C80="call",IF(AND(J80>0,J80<K80),D80+J80,"n.a."),IF(AND(K80>J80,2*E80-D80+J80>=0),2*E80-D80+J80,"n.a."))) -> n.a. | O80: =IF(B80="Butterfly",IF(AND(J80>0,J80<K80),F80-J80,"n.a."),IF(C80="call",IF(K80>J80,2*E80-D80-J80,"n.a."),IF(AND(J80>0,J80<K80),D80-J80,"n.a."))) -> 10300.68 | P80: =IF(AND(B80="Butterfly",J80>0,J80<K80),L80/J80,"n.a.") -> n.a. | Q80: =J80*'Model inputs'!$B$8 -> -68 | R80: Indicative only | S80: 462 | T80: 481
A81: 46281 | B81: 1x2 ratio | C81: call | D81: 6200 | E81: 6400 | G81: ='Option source'!B201 -> 704.74 | H81: ='Option source'!B220 -> 616.1 | J81: =G81-2*H81+IF(B81="Butterfly",I81,0) -> -527.46 | K81: =ABS(E81-D81) -> 200 | L81: =K81-J81 -> 727.46 | M81: =IF(B81="Butterfly",MAX(J81,0),IF(C81="call","Unlimited",MAX(2*E81-D81+J81,J81,0))) -> Unlimited | N81: =IF(B81="Butterfly",IF(AND(J81>0,J81<K81),D81+J81,"n.a."),IF(C81="call",IF(AND(J81>0,J81<K81),D81+J81,"n.a."),IF(AND(K81>J81,2*E81-D81+J81>=0),2*E81-D81+J81,"n.a."))) -> n.a. | O81: =IF(B81="Butterfly",IF(AND(J81>0,J81<K81),F81-J81,"n.a."),IF(C81="call",IF(K81>J81,2*E81-D81-J81,"n.a."),IF(AND(J81>0,J81<K81),D81-J81,"n.a."))) -> 7127.46 | P81: =IF(AND(B81="Butterfly",J81>0,J81<K81),L81/J81,"n.a.") -> n.a. | Q81: =J81*'Model inputs'!$B$8 -> -52746 | R81: Flagged leg data | S81: 196 | T81: 215
A82: 46281 | B82: 1x2 ratio | C82: call | D82: 6000 | E82: 6200 | G82: ='Option source'!B182 -> 916.41 | H82: ='Option source'!B201 -> 704.74 | J82: =G82-2*H82+IF(B82="Butterfly",I82,0) -> -493.07 | K82: =ABS(E82-D82) -> 200 | L82: =K82-J82 -> 693.07 | M82: =IF(B82="Butterfly",MAX(J82,0),IF(C82="call","Unlimited",MAX(2*E82-D82+J82,J82,0))) -> Unlimited | N82: =IF(B82="Butterfly",IF(AND(J82>0,J82<K82),D82+J82,"n.a."),IF(C82="call",IF(AND(J82>0,J82<K82),D82+J82,"n.a."),IF(AND(K82>J82,2*E82-D82+J82>=0),2*E82-D82+J82,"n.a."))) -> n.a. | O82: =IF(B82="Butterfly",IF(AND(J82>0,J82<K82),F82-J82,"n.a."),IF(C82="call",IF(K82>J82,2*E82-D82-J82,"n.a."),IF(AND(J82>0,J82<K82),D82-J82,"n.a."))) -> 6893.07 | P82: =IF(AND(B82="Butterfly",J82>0,J82<K82),L82/J82,"n.a.") -> n.a. | Q82: =J82*'Model inputs'!$B$8 -> -49307 | R82: Flagged leg data | S82: 177 | T82: 196
A83: 46281 | B83: 1x2 ratio | C83: call | D83: 5800 | E83: 6000 | G83: ='Option source'!B163 -> 1049.9 | H83: ='Option source'!B182 -> 916.41 | J83: =G83-2*H83+IF(B83="Butterfly",I83,0) -> -782.92 | K83: =ABS(E83-D83) -> 200 | L83: =K83-J83 -> 982.92 | M83: =IF(B83="Butterfly",MAX(J83,0),IF(C83="call","Unlimited",MAX(2*E83-D83+J83,J83,0))) -> Unlimited | N83: =IF(B83="Butterfly",IF(AND(J83>0,J83<K83),D83+J83,"n.a."),IF(C83="call",IF(AND(J83>0,J83<K83),D83+J83,"n.a."),IF(AND(K83>J83,2*E83-D83+J83>=0),2*E83-D83+J83,"n.a."))) -> n.a. | O83: =IF(B83="Butterfly",IF(AND(J83>0,J83<K83),F83-J83,"n.a."),IF(C83="call",IF(K83>J83,2*E83-D83-J83,"n.a."),IF(AND(J83>0,J83<K83),D83-J83,"n.a."))) -> 6982.92 | P83: =IF(AND(B83="Butterfly",J83>0,J83<K83),L83/J83,"n.a.") -> n.a. | Q83: =J83*'Model inputs'!$B$8 -> -78292 | R83: Flagged leg data | S83: 158 | T83: 177
A84: 46281 | B84: 1x2 ratio | C84: put | D84: 7800 | E84: 7600 | G84: ='Option source'!B847 -> 1000 | H84: ='Option source'!B828 -> 857 | J84: =G84-2*H84+IF(B84="Butterfly",I84,0) -> -714 | K84: =ABS(E84-D84) -> 200 | L84: =K84-J84 -> 914 | M84: =IF(B84="Butterfly",MAX(J84,0),IF(C84="call","Unlimited",MAX(2*E84-D84+J84,J84,0))) -> 6686 | N84: =IF(B84="Butterfly",IF(AND(J84>0,J84<K84),D84+J84,"n.a."),IF(C84="call",IF(AND(J84>0,J84<K84),D84+J84,"n.a."),IF(AND(K84>J84,2*E84-D84+J84>=0),2*E84-D84+J84,"n.a."))) -> 6686 | O84: =IF(B84="Butterfly",IF(AND(J84>0,J84<K84),F84-J84,"n.a."),IF(C84="call",IF(K84>J84,2*E84-D84-J84,"n.a."),IF(AND(J84>0,J84<K84),D84-J84,"n.a."))) -> n.a. | P84: =IF(AND(B84="Butterfly",J84>0,J84<K84),L84/J84,"n.a.") -> n.a. | Q84: =J84*'Model inputs'!$B$8 -> -71400 | R84: Flagged leg data | S84: 842 | T84: 823
A85: 46281 | B85: 1x2 ratio | C85: call | D85: 5600 | E85: 5800 | G85: ='Option source'!B153 -> 1233.13 | H85: ='Option source'!B163 -> 1049.9 | J85: =G85-2*H85+IF(B85="Butterfly",I85,0) -> -866.67 | K85: =ABS(E85-D85) -> 200 | L85: =K85-J85 -> 1066.67 | M85: =IF(B85="Butterfly",MAX(J85,0),IF(C85="call","Unlimited",MAX(2*E85-D85+J85,J85,0))) -> Unlimited | N85: =IF(B85="Butterfly",IF(AND(J85>0,J85<K85),D85+J85,"n.a."),IF(C85="call",IF(AND(J85>0,J85<K85),D85+J85,"n.a."),IF(AND(K85>J85,2*E85-D85+J85>=0),2*E85-D85+J85,"n.a."))) -> n.a. | O85: =IF(B85="Butterfly",IF(AND(J85>0,J85<K85),F85-J85,"n.a."),IF(C85="call",IF(K85>J85,2*E85-D85-J85,"n.a."),IF(AND(J85>0,J85<K85),D85-J85,"n.a."))) -> 6866.67 | P85: =IF(AND(B85="Butterfly",J85>0,J85<K85),L85/J85,"n.a.") -> n.a. | Q85: =J85*'Model inputs'!$B$8 -> -86667 | R85: Flagged leg data | S85: 148 | T85: 158
A86: 46281 | B86: 1x2 ratio | C86: put | D86: 8000 | E86: 7800 | G86: ='Option source'!B866 -> 1230 | H86: ='Option source'!B847 -> 1000 | J86: =G86-2*H86+IF(B86="Butterfly",I86,0) -> -770 | K86: =ABS(E86-D86) -> 200 | L86: =K86-J86 -> 970 | M86: =IF(B86="Butterfly",MAX(J86,0),IF(C86="call","Unlimited",MAX(2*E86-D86+J86,J86,0))) -> 6830 | N86: =IF(B86="Butterfly",IF(AND(J86>0,J86<K86),D86+J86,"n.a."),IF(C86="call",IF(AND(J86>0,J86<K86),D86+J86,"n.a."),IF(AND(K86>J86,2*E86-D86+J86>=0),2*E86-D86+J86,"n.a."))) -> 6830 | O86: =IF(B86="Butterfly",IF(AND(J86>0,J86<K86),F86-J86,"n.a."),IF(C86="call",IF(K86>J86,2*E86-D86-J86,"n.a."),IF(AND(J86>0,J86<K86),D86-J86,"n.a."))) -> n.a. | P86: =IF(AND(B86="Butterfly",J86>0,J86<K86),L86/J86,"n.a.") -> n.a. | Q86: =J86*'Model inputs'!$B$8 -> -77000 | R86: Flagged leg data | S86: 861 | T86: 842
A87: 46281 | B87: 1x2 ratio | C87: call | D87: 5400 | E87: 5600 | G87: ='Option source'!B135 -> 1470 | H87: ='Option source'!B153 -> 1233.13 | J87: =G87-2*H87+IF(B87="Butterfly",I87,0) -> -996.26 | K87: =ABS(E87-D87) -> 200 | L87: =K87-J87 -> 1196.26 | M87: =IF(B87="Butterfly",MAX(J87,0),IF(C87="call","Unlimited",MAX(2*E87-D87+J87,J87,0))) -> Unlimited | N87: =IF(B87="Butterfly",IF(AND(J87>0,J87<K87),D87+J87,"n.a."),IF(C87="call",IF(AND(J87>0,J87<K87),D87+J87,"n.a."),IF(AND(K87>J87,2*E87-D87+J87>=0),2*E87-D87+J87,"n.a."))) -> n.a. | O87: =IF(B87="Butterfly",IF(AND(J87>0,J87<K87),F87-J87,"n.a."),IF(C87="call",IF(K87>J87,2*E87-D87-J87,"n.a."),IF(AND(J87>0,J87<K87),D87-J87,"n.a."))) -> 6796.26 | P87: =IF(AND(B87="Butterfly",J87>0,J87<K87),L87/J87,"n.a.") -> n.a. | Q87: =J87*'Model inputs'!$B$8 -> -99626 | R87: Flagged leg data | S87: 130 | T87: 148
A88: 46281 | B88: 1x2 ratio | C88: put | D88: 8300 | E88: 8000 | G88: ='Option source'!B885 -> 1520 | H88: ='Option source'!B866 -> 1230 | J88: =G88-2*H88+IF(B88="Butterfly",I88,0) -> -940 | K88: =ABS(E88-D88) -> 300 | L88: =K88-J88 -> 1240 | M88: =IF(B88="Butterfly",MAX(J88,0),IF(C88="call","Unlimited",MAX(2*E88-D88+J88,J88,0))) -> 6760 | N88: =IF(B88="Butterfly",IF(AND(J88>0,J88<K88),D88+J88,"n.a."),IF(C88="call",IF(AND(J88>0,J88<K88),D88+J88,"n.a."),IF(AND(K88>J88,2*E88-D88+J88>=0),2*E88-D88+J88,"n.a."))) -> 6760 | O88: =IF(B88="Butterfly",IF(AND(J88>0,J88<K88),F88-J88,"n.a."),IF(C88="call",IF(K88>J88,2*E88-D88-J88,"n.a."),IF(AND(J88>0,J88<K88),D88-J88,"n.a."))) -> n.a. | P88: =IF(AND(B88="Butterfly",J88>0,J88<K88),L88/J88,"n.a.") -> n.a. | Q88: =J88*'Model inputs'!$B$8 -> -94000 | R88: Flagged leg data | S88: 880 | T88: 861
A89: 46281 | B89: 1x2 ratio | C89: call | D89: 5200 | E89: 5400 | G89: ='Option source'!B116 -> 1678.07 | H89: ='Option source'!B135 -> 1470 | J89: =G89-2*H89+IF(B89="Butterfly",I89,0) -> -1261.93 | K89: =ABS(E89-D89) -> 200 | L89: =K89-J89 -> 1461.93 | M89: =IF(B89="Butterfly",MAX(J89,0),IF(C89="call","Unlimited",MAX(2*E89-D89+J89,J89,0))) -> Unlimited | N89: =IF(B89="Butterfly",IF(AND(J89>0,J89<K89),D89+J89,"n.a."),IF(C89="call",IF(AND(J89>0,J89<K89),D89+J89,"n.a."),IF(AND(K89>J89,2*E89-D89+J89>=0),2*E89-D89+J89,"n.a."))) -> n.a. | O89: =IF(B89="Butterfly",IF(AND(J89>0,J89<K89),F89-J89,"n.a."),IF(C89="call",IF(K89>J89,2*E89-D89-J89,"n.a."),IF(AND(J89>0,J89<K89),D89-J89,"n.a."))) -> 6861.93 | P89: =IF(AND(B89="Butterfly",J89>0,J89<K89),L89/J89,"n.a.") -> n.a. | Q89: =J89*'Model inputs'!$B$8 -> -126193 | R89: Flagged leg data | S89: 111 | T89: 130
A90: 46281 | B90: 1x2 ratio | C90: put | D90: 8600 | E90: 8300 | G90: ='Option source'!B904 -> 1648.65 | H90: ='Option source'!B885 -> 1520 | J90: =G90-2*H90+IF(B90="Butterfly",I90,0) -> -1391.35 | K90: =ABS(E90-D90) -> 300 | L90: =K90-J90 -> 1691.35 | M90: =IF(B90="Butterfly",MAX(J90,0),IF(C90="call","Unlimited",MAX(2*E90-D90+J90,J90,0))) -> 6608.65 | N90: =IF(B90="Butterfly",IF(AND(J90>0,J90<K90),D90+J90,"n.a."),IF(C90="call",IF(AND(J90>0,J90<K90),D90+J90,"n.a."),IF(AND(K90>J90,2*E90-D90+J90>=0),2*E90-D90+J90,"n.a."))) -> 6608.65 | O90: =IF(B90="Butterfly",IF(AND(J90>0,J90<K90),F90-J90,"n.a."),IF(C90="call",IF(K90>J90,2*E90-D90-J90,"n.a."),IF(AND(J90>0,J90<K90),D90-J90,"n.a."))) -> n.a. | P90: =IF(AND(B90="Butterfly",J90>0,J90<K90),L90/J90,"n.a.") -> n.a. | Q90: =J90*'Model inputs'!$B$8 -> -139135 | R90: Flagged leg data | S90: 899 | T90: 880
A91: 46281 | B91: 1x2 ratio | C91: call | D91: 5000 | E91: 5200 | G91: ='Option source'!B97 -> 1808.85 | H91: ='Option source'!B116 -> 1678.07 | J91: =G91-2*H91+IF(B91="Butterfly",I91,0) -> -1547.29 | K91: =ABS(E91-D91) -> 200 | L91: =K91-J91 -> 1747.29 | M91: =IF(B91="Butterfly",MAX(J91,0),IF(C91="call","Unlimited",MAX(2*E91-D91+J91,J91,0))) -> Unlimited | N91: =IF(B91="Butterfly",IF(AND(J91>0,J91<K91),D91+J91,"n.a."),IF(C91="call",IF(AND(J91>0,J91<K91),D91+J91,"n.a."),IF(AND(K91>J91,2*E91-D91+J91>=0),2*E91-D91+J91,"n.a."))) -> n.a. | O91: =IF(B91="Butterfly",IF(AND(J91>0,J91<K91),F91-J91,"n.a."),IF(C91="call",IF(K91>J91,2*E91-D91-J91,"n.a."),IF(AND(J91>0,J91<K91),D91-J91,"n.a."))) -> 6947.29 | P91: =IF(AND(B91="Butterfly",J91>0,J91<K91),L91/J91,"n.a.") -> n.a. | Q91: =J91*'Model inputs'!$B$8 -> -154729 | R91: Flagged leg data | S91: 92 | T91: 111
A92: 46281 | B92: 1x2 ratio | C92: call | D92: 4800 | E92: 5000 | G92: ='Option source'!B80 -> 2084.21 | H92: ='Option source'!B97 -> 1808.85 | J92: =G92-2*H92+IF(B92="Butterfly",I92,0) -> -1533.49 | K92: =ABS(E92-D92) -> 200 | L92: =K92-J92 -> 1733.49 | M92: =IF(B92="Butterfly",MAX(J92,0),IF(C92="call","Unlimited",MAX(2*E92-D92+J92,J92,0))) -> Unlimited | N92: =IF(B92="Butterfly",IF(AND(J92>0,J92<K92),D92+J92,"n.a."),IF(C92="call",IF(AND(J92>0,J92<K92),D92+J92,"n.a."),IF(AND(K92>J92,2*E92-D92+J92>=0),2*E92-D92+J92,"n.a."))) -> n.a. | O92: =IF(B92="Butterfly",IF(AND(J92>0,J92<K92),F92-J92,"n.a."),IF(C92="call",IF(K92>J92,2*E92-D92-J92,"n.a."),IF(AND(J92>0,J92<K92),D92-J92,"n.a."))) -> 6733.49 | P92: =IF(AND(B92="Butterfly",J92>0,J92<K92),L92/J92,"n.a.") -> n.a. | Q92: =J92*'Model inputs'!$B$8 -> -153349 | R92: Flagged leg data | S92: 75 | T92: 92
A93: 46281 | B93: 1x2 ratio | C93: put | D93: 8900 | E93: 8600 | G93: ='Option source'!B919 -> 2022.5 | H93: ='Option source'!B904 -> 1648.65 | J93: =G93-2*H93+IF(B93="Butterfly",I93,0) -> -1274.8 | K93: =ABS(E93-D93) -> 300 | L93: =K93-J93 -> 1574.8 | M93: =IF(B93="Butterfly",MAX(J93,0),IF(C93="call","Unlimited",MAX(2*E93-D93+J93,J93,0))) -> 7025.2 | N93: =IF(B93="Butterfly",IF(AND(J93>0,J93<K93),D93+J93,"n.a."),IF(C93="call",IF(AND(J93>0,J93<K93),D93+J93,"n.a."),IF(AND(K93>J93,2*E93-D93+J93>=0),2*E93-D93+J93,"n.a."))) -> 7025.2 | O93: =IF(B93="Butterfly",IF(AND(J93>0,J93<K93),F93-J93,"n.a."),IF(C93="call",IF(K93>J93,2*E93-D93-J93,"n.a."),IF(AND(J93>0,J93<K93),D93-J93,"n.a."))) -> n.a. | P93: =IF(AND(B93="Butterfly",J93>0,J93<K93),L93/J93,"n.a.") -> n.a. | Q93: =J93*'Model inputs'!$B$8 -> -127480 | R93: Flagged leg data | S93: 914 | T93: 899
A94: 46281 | B94: 1x2 ratio | C94: call | D94: 4600 | E94: 4800 | G94: ='Option source'!B63 -> 2280.1 | H94: ='Option source'!B80 -> 2084.21 | J94: =G94-2*H94+IF(B94="Butterfly",I94,0) -> -1888.32 | K94: =ABS(E94-D94) -> 200 | L94: =K94-J94 -> 2088.32 | M94: =IF(B94="Butterfly",MAX(J94,0),IF(C94="call","Unlimited",MAX(2*E94-D94+J94,J94,0))) -> Unlimited | N94: =IF(B94="Butterfly",IF(AND(J94>0,J94<K94),D94+J94,"n.a."),IF(C94="call",IF(AND(J94>0,J94<K94),D94+J94,"n.a."),IF(AND(K94>J94,2*E94-D94+J94>=0),2*E94-D94+J94,"n.a."))) -> n.a. | O94: =IF(B94="Butterfly",IF(AND(J94>0,J94<K94),F94-J94,"n.a."),IF(C94="call",IF(K94>J94,2*E94-D94-J94,"n.a."),IF(AND(J94>0,J94<K94),D94-J94,"n.a."))) -> 6888.32 | P94: =IF(AND(B94="Butterfly",J94>0,J94<K94),L94/J94,"n.a.") -> n.a. | Q94: =J94*'Model inputs'!$B$8 -> -188832 | R94: Flagged leg data | S94: 58 | T94: 75
A95: 46281 | B95: 1x2 ratio | C95: put | D95: 9200 | E95: 8900 | G95: ='Option source'!B926 -> 2268.51 | H95: ='Option source'!B919 -> 2022.5 | J95: =G95-2*H95+IF(B95="Butterfly",I95,0) -> -1776.49 | K95: =ABS(E95-D95) -> 300 | L95: =K95-J95 -> 2076.49 | M95: =IF(B95="Butterfly",MAX(J95,0),IF(C95="call","Unlimited",MAX(2*E95-D95+J95,J95,0))) -> 6823.51 | N95: =IF(B95="Butterfly",IF(AND(J95>0,J95<K95),D95+J95,"n.a."),IF(C95="call",IF(AND(J95>0,J95<K95),D95+J95,"n.a."),IF(AND(K95>J95,2*E95-D95+J95>=0),2*E95-D95+J95,"n.a."))) -> 6823.51 | O95: =IF(B95="Butterfly",IF(AND(J95>0,J95<K95),F95-J95,"n.a."),IF(C95="call",IF(K95>J95,2*E95-D95-J95,"n.a."),IF(AND(J95>0,J95<K95),D95-J95,"n.a."))) -> n.a. | P95: =IF(AND(B95="Butterfly",J95>0,J95<K95),L95/J95,"n.a.") -> n.a. | Q95: =J95*'Model inputs'!$B$8 -> -177649 | R95: Flagged leg data | S95: 921 | T95: 914
A96: 46281 | B96: 1x2 ratio | C96: call | D96: 4400 | E96: 4600 | G96: ='Option source'!B44 -> 2422 | H96: ='Option source'!B63 -> 2280.1 | J96: =G96-2*H96+IF(B96="Butterfly",I96,0) -> -2138.2 | K96: =ABS(E96-D96) -> 200 | L96: =K96-J96 -> 2338.2 | M96: =IF(B96="Butterfly",MAX(J96,0),IF(C96="call","Unlimited",MAX(2*E96-D96+J96,J96,0))) -> Unlimited | N96: =IF(B96="Butterfly",IF(AND(J96>0,J96<K96),D96+J96,"n.a."),IF(C96="call",IF(AND(J96>0,J96<K96),D96+J96,"n.a."),IF(AND(K96>J96,2*E96-D96+J96>=0),2*E96-D96+J96,"n.a."))) -> n.a. | O96: =IF(B96="Butterfly",IF(AND(J96>0,J96<K96),F96-J96,"n.a."),IF(C96="call",IF(K96>J96,2*E96-D96-J96,"n.a."),IF(AND(J96>0,J96<K96),D96-J96,"n.a."))) -> 6938.2 | P96: =IF(AND(B96="Butterfly",J96>0,J96<K96),L96/J96,"n.a.") -> n.a. | Q96: =J96*'Model inputs'!$B$8 -> -213820 | R96: Flagged leg data | S96: 39 | T96: 58
A97: 46281 | B97: 1x2 ratio | C97: call | D97: 4200 | E97: 4400 | G97: ='Option source'!B25 -> 2587.49 | H97: ='Option source'!B44 -> 2422 | J97: =G97-2*H97+IF(B97="Butterfly",I97,0) -> -2256.51 | K97: =ABS(E97-D97) -> 200 | L97: =K97-J97 -> 2456.51 | M97: =IF(B97="Butterfly",MAX(J97,0),IF(C97="call","Unlimited",MAX(2*E97-D97+J97,J97,0))) -> Unlimited | N97: =IF(B97="Butterfly",IF(AND(J97>0,J97<K97),D97+J97,"n.a."),IF(C97="call",IF(AND(J97>0,J97<K97),D97+J97,"n.a."),IF(AND(K97>J97,2*E97-D97+J97>=0),2*E97-D97+J97,"n.a."))) -> n.a. | O97: =IF(B97="Butterfly",IF(AND(J97>0,J97<K97),F97-J97,"n.a."),IF(C97="call",IF(K97>J97,2*E97-D97-J97,"n.a."),IF(AND(J97>0,J97<K97),D97-J97,"n.a."))) -> 6856.51 | P97: =IF(AND(B97="Butterfly",J97>0,J97<K97),L97/J97,"n.a.") -> n.a. | Q97: =J97*'Model inputs'!$B$8 -> -225651 | R97: Flagged leg data | S97: 20 | T97: 39
A98: 46280 | B98: Butterfly | C98: call | D98: 6600 | E98: 6800 | F98: 7000 | G98: ='Option source'!B238 -> 490 | H98: ='Option source'!B257 -> 380.09 | I98: ='Option source'!B276 -> 277.07 | J98: =G98-2*H98+IF(B98="Butterfly",I98,0) -> 6.89 | K98: =ABS(E98-D98) -> 200 | L98: =K98-J98 -> 193.11 | M98: =IF(B98="Butterfly",MAX(J98,0),IF(C98="call","Unlimited",MAX(2*E98-D98+J98,J98,0))) -> 6.89 | N98: =IF(B98="Butterfly",IF(AND(J98>0,J98<K98),D98+J98,"n.a."),IF(C98="call",IF(AND(J98>0,J98<K98),D98+J98,"n.a."),IF(AND(K98>J98,2*E98-D98+J98>=0),2*E98-D98+J98,"n.a."))) -> 6606.89 | O98: =IF(B98="Butterfly",IF(AND(J98>0,J98<K98),F98-J98,"n.a."),IF(C98="call",IF(K98>J98,2*E98-D98-J98,"n.a."),IF(AND(J98>0,J98<K98),D98-J98,"n.a."))) -> 6993.11 | P98: =IF(AND(B98="Butterfly",J98>0,J98<K98),L98/J98,"n.a.") -> 28.027576 | Q98: =J98*'Model inputs'!$B$8 -> 689 | R98: Indicative only | S98: 233 | T98: 252
A99: 46280 | B99: Butterfly | C99: put | D99: 6600 | E99: 6800 | F99: 7000 | G99: ='Option source'!B732 -> 220.68 | H99: ='Option source'!B751 -> 311.72 | I99: ='Option source'!B770 -> 418.29 | J99: =G99-2*H99+IF(B99="Butterfly",I99,0) -> 15.53 | K99: =ABS(E99-D99) -> 200 | L99: =K99-J99 -> 184.47 | M99: =IF(B99="Butterfly",MAX(J99,0),IF(C99="call","Unlimited",MAX(2*E99-D99+J99,J99,0))) -> 15.53 | N99: =IF(B99="Butterfly",IF(AND(J99>0,J99<K99),D99+J99,"n.a."),IF(C99="call",IF(AND(J99>0,J99<K99),D99+J99,"n.a."),IF(AND(K99>J99,2*E99-D99+J99>=0),2*E99-D99+J99,"n.a."))) -> 6615.53 | O99: =IF(B99="Butterfly",IF(AND(J99>0,J99<K99),F99-J99,"n.a."),IF(C99="call",IF(K99>J99,2*E99-D99-J99,"n.a."),IF(AND(J99>0,J99<K99),D99-J99,"n.a."))) -> 6984.47 | P99: =IF(AND(B99="Butterfly",J99>0,J99<K99),L99/J99,"n.a.") -> 11.8783 | Q99: =J99*'Model inputs'!$B$8 -> 1553 | R99: Indicative only | S99: 727 | T99: 746
A100: 46280 | B100: Butterfly | C100: call | D100: 6400 | E100: 6600 | F100: 6800 | G100: ='Option source'!B219 -> 600.2 | H100: ='Option source'!B238 -> 490 | I100: ='Option source'!B257 -> 380.09 | J100: =G100-2*H100+IF(B100="Butterfly",I100,0) -> 0.29 | K100: =ABS(E100-D100) -> 200 | L100: =K100-J100 -> 199.71 | M100: =IF(B100="Butterfly",MAX(J100,0),IF(C100="call","Unlimited",MAX(2*E100-D100+J100,J100,0))) -> 0.29 | N100: =IF(B100="Butterfly",IF(AND(J100>0,J100<K100),D100+J100,"n.a."),IF(C100="call",IF(AND(J100>0,J100<K100),D100+J100,"n.a."),IF(AND(K100>J100,2*E100-D100+J100>=0),2*E100-D100+J100,"n.a."))) -> 6400.29 | O100: =IF(B100="Butterfly",IF(AND(J100>0,J100<K100),F100-J100,"n.a."),IF(C100="call",IF(K100>J100,2*E100-D100-J100,"n.a."),IF(AND(J100>0,J100<K100),D100-J100,"n.a."))) -> 6799.71 | P100: =IF(AND(B100="Butterfly",J100>0,J100<K100),L100/J100,"n.a.") -> 688.65517 | Q100: =J100*'Model inputs'!$B$8 -> 29 | R100: Indicative only | S100: 214 | T100: 233
A101: 46280 | B101: Butterfly | C101: put | D101: 6400 | E101: 6600 | F101: 6800 | G101: ='Option source'!B713 -> 151.43 | H101: ='Option source'!B732 -> 220.68 | I101: ='Option source'!B751 -> 311.72 | J101: =G101-2*H101+IF(B101="Butterfly",I101,0) -> 21.79 | K101: =ABS(E101-D101) -> 200 | L101: =K101-J101 -> 178.21 | M101: =IF(B101="Butterfly",MAX(J101,0),IF(C101="call","Unlimited",MAX(2*E101-D101+J101,J101,0))) -> 21.79 | N101: =IF(B101="Butterfly",IF(AND(J101>0,J101<K101),D101+J101,"n.a."),IF(C101="call",IF(AND(J101>0,J101<K101),D101+J101,"n.a."),IF(AND(K101>J101,2*E101-D101+J101>=0),2*E101-D101+J101,"n.a."))) -> 6421.79 | O101: =IF(B101="Butterfly",IF(AND(J101>0,J101<K101),F101-J101,"n.a."),IF(C101="call",IF(K101>J101,2*E101-D101-J101,"n.a."),IF(AND(J101>0,J101<K101),D101-J101,"n.a."))) -> 6778.21 | P101: =IF(AND(B101="Butterfly",J101>0,J101<K101),L101/J101,"n.a.") -> 8.1785223 | Q101: =J101*'Model inputs'!$B$8 -> 2179 | R101: Indicative only | S101: 708 | T101: 727
A102: 46280 | B102: Butterfly | C102: call | D102: 6800 | E102: 7000 | F102: 7200 | G102: ='Option source'!B257 -> 380.09 | H102: ='Option source'!B276 -> 277.07 | I102: ='Option source'!B295 -> 205.53 | J102: =G102-2*H102+IF(B102="Butterfly",I102,0) -> 31.48 | K102: =ABS(E102-D102) -> 200 | L102: =K102-J102 -> 168.52 | M102: =IF(B102="Butterfly",MAX(J102,0),IF(C102="call","Unlimited",MAX(2*E102-D102+J102,J102,0))) -> 31.48 | N102: =IF(B102="Butterfly",IF(AND(J102>0,J102<K102),D102+J102,"n.a."),IF(C102="call",IF(AND(J102>0,J102<K102),D102+J102,"n.a."),IF(AND(K102>J102,2*E102-D102+J102>=0),2*E102-D102+J102,"n.a."))) -> 6831.48 | O102: =IF(B102="Butterfly",IF(AND(J102>0,J102<K102),F102-J102,"n.a."),IF(C102="call",IF(K102>J102,2*E102-D102-J102,"n.a."),IF(AND(J102>0,J102<K102),D102-J102,"n.a."))) -> 7168.52 | P102: =IF(AND(B102="Butterfly",J102>0,J102<K102),L102/J102,"n.a.") -> 5.3532402 | Q102: =J102*'Model inputs'!$B$8 -> 3148 | R102: Indicative only | S102: 252 | T102: 271
A103: 46280 | B103: Butterfly | C103: put | D103: 6800 | E103: 7000 | F103: 7200 | G103: ='Option source'!B751 -> 311.72 | H103: ='Option source'!B770 -> 418.29 | I103: ='Option source'!B789 -> 542 | J103: =G103-2*H103+IF(B103="Butterfly",I103,0) -> 17.14 | K103: =ABS(E103-D103) -> 200 | L103: =K103-J103 -> 182.86 | M103: =IF(B103="Butterfly",MAX(J103,0),IF(C103="call","Unlimited",MAX(2*E103-D103+J103,J103,0))) -> 17.14 | N103: =IF(B103="Butterfly",IF(AND(J103>0,J103<K103),D103+J103,"n.a."),IF(C103="call",IF(AND(J103>0,J103<K103),D103+J103,"n.a."),IF(AND(K103>J103,2*E103-D103+J103>=0),2*E103-D103+J103,"n.a."))) -> 6817.14 | O103: =IF(B103="Butterfly",IF(AND(J103>0,J103<K103),F103-J103,"n.a."),IF(C103="call",IF(K103>J103,2*E103-D103-J103,"n.a."),IF(AND(J103>0,J103<K103),D103-J103,"n.a."))) -> 7182.86 | P103: =IF(AND(B103="Butterfly",J103>0,J103<K103),L103/J103,"n.a.") -> 10.668611 | Q103: =J103*'Model inputs'!$B$8 -> 1714 | R103: Indicative only | S103: 746 | T103: 765
...

Sheet Option source
A2: Original PPI option observations
A4: Source: options_data.xlsx / Sheet1. The added Closing price column is not used in the analysis.
A5: Session date preserves the calendar date of the original PPI timestamp (UTC−03:00).
A6: Session date | B6: price (PPI) | C6: volume (PPI) | D6: openingPrice | E6: Closing price (cached) | F6: max | G6: min | H6: previousClose | I6: marketChange | J6: marketChangePercent | K6: ticker | L6: Closing price formula
A7: 46255 | B7: 2544.61 | C7: 97648600 | D7: 2544.61 | E7: 2550 | F7: 2594.68 | G7: 2529.59 | H7: 0 | I7: 0 | K7: GFGC4200OC | L7: =+D3
A8: 46258 | B8: 2844.35 | C8: 96763072 | D8: 2550 | E8: 2800 | F8: 2839.36 | G8: 2550 | H8: 0 | I8: 0 | K8: GFGC4200OC | L8: =+D4
A9: 46259 | B9: 2865.46 | C9: 3405823 | D9: 2800 | E9: 2929.59 | F9: 2874.05 | G9: 2800 | H9: 0 | I9: 0 | K9: GFGC4200OC | L9: =+D5
A10: 46260 | B10: 2914.64 | C10: 1761738 | D10: 2929.59 | E10: 2957.26 | F10: 2964.46 | G10: 2929.59 | H10: 0 | I10: 0 | K10: GFGC4200OC | L10: =+D6
A11: 46261 | B11: 2815 | C11: 3711634 | D11: 2957.26 | E11: 2728.37 | F11: 2957.26 | G11: 2777.9 | H11: 0 | I11: 0 | K11: GFGC4200OC | L11: =+D7
A12: 46262 | B12: 2666.16 | C12: 19534206 | D12: 2728.37 | E12: 2853.68 | F12: 2728.37 | G12: 2623.86 | H12: 0 | I12: 0 | K12: GFGC4200OC | L12: =+D8
A13: 46265 | B13: 2933.39 | C13: 4581830 | D13: 2853.68 | E13: 2946.11 | F13: 2853.68 | G13: 2853.68 | H13: 0 | I13: 0 | K13: GFGC4200OC | L13: =+D9
A14: 46266 | B14: 3017.35 | C14: 890957 | D14: 2946.11 | E14: 2946.11 | F14: 2946.11 | G14: 2946.11 | H14: 0 | I14: 0 | K14: GFGC4200OC | L14: =+D10
A15: 46267 | B15: 3017.35 | C15: 0 | D15: 2946.11 | E15: 3039.57 | F15: 2946.11 | G15: 2946.11 | H15: 0 | I15: 0 | K15: GFGC4200OC | L15: =+D11
A16: 46268 | B16: 2964.84 | C16: 3574248 | D16: 3039.57 | E16: 3039.57 | F16: 3039.57 | G16: 2979.78 | H16: 0 | I16: 0 | K16: GFGC4200OC | L16: =+D12
A17: 46269 | B17: 2964.84 | C17: 0 | D17: 3039.57 | E17: 2813.9 | F17: 3039.57 | G17: 2979.78 | H17: 0 | I17: 0 | K17: GFGC4200OC | L17: =+D13
A18: 46272 | B18: 2871.76 | C18: 2302020 | D18: 2813.9 | E18: 2938.68 | F18: 2889.09 | G18: 2813.9 | H18: 0 | I18: 0 | K18: GFGC4200OC | L18: =+D14
... A925: 46280 | B925: 2041.57 | C925: 0 | D925: 2041.57 | E925: 2168.75 | F925: 2041.57 | G925: 2041.57 | H925: 0 | I925: 0 | K925: GFGV9200OC | L925: =+D921
A926: 46281 | B926: 2268.51 | C926: 660601 | D926: 2168.75 | F926: 2168.75 | G926: 2168.75 | H926: 0 | I926: 0 | K926: GFGV9200OC | L926: '

Sheet Model inputs
A2: Inputs and interpretation
A5: Expiry | B5: 46311 | D5: Matched to saved BYMA September 7 option metadata.
A6: Rate used | B6: 0.3 | D6: 30% annual continuous rate, illustrative constant; not an observed funding curve.
A7: Dividend yield used | B7: 0 | D7: q = 0 assumption; no verified forward dividend schedule.
A8: Shares per contract | B8: 100 | D8: Standard BYMA share-option lot. Check extraordinary corporate adjustments.
A9: Day-count basis | B9: 365 | D9: Actual calendar days / 365.
A10: Annualization sessions | B10: 252 | D10: Realized volatility uses sample standard deviation of daily log returns.
A11: Low/high rate checks | B11: 20% / 40% | D11: Illustrative rate sensitivity; same model, spot and option price.
A12: Call IV engine | B12: Black-Scholes, q=0 | D12: Equivalent to American call under the stated non-dividend assumption.
A13: Put IV engine | B13: American CRR, 200 steps | D13: 29 bisections, bounded 0–500% IV; rejects unstable/intrinsic-bound prices.
A14: Strike mapping | B14: Numeric ticker strike | D14: No security-master strike adjustments verified. All outputs conditional on this mapping.
A15: Price basis | B15: PPI price as reported | D15: No use of next-row opening price as a close. No bid/ask spread information.
A16: Volume basis | B16: Unverified raw field | D16: P/C raw-volume ratio is NOT a verified contract-count ratio. May be monetary turnover.
A17: IV screening | B17: Volume > 0; price in range | D17: Also rejects below-intrinsic prices and model-bound violations. Not proof of a fresh quote.
A18: IV / Greeks refresh | B18: Externally calculated snapshot | D18: Re-run analysis after changing inputs. Editing assumptions here does not recompute IV.
A19: Delta / vega | B19: European BS diagnostics | D19: Using estimated IV. Vega is ARS per share per 1 percentage-point IV change.
A20: ATM series | B20: Nearest paired strike within 8% | D20: Average call/put IV at that strike. Strike can change; tenor declines. Not constant maturity.
A21: 25-delta skew | B21: Put IV minus call IV | D21: Linear interpolation by BS delta, no extrapolation. American-put delta is approximated.
A22: Volatility butterfly | B22: (25d call + 25d put)/2 − ATM | D22: Smile curvature, distinct from the 1:-2:1 price strategy.
... A28: Sources | B28: PPI API and user workbook | D28: Stock: MarketData/Search, GGAL, ACCIONES, A-24HS, June 1–September 16, 2026.
A29: BYMA contract rules | D29: https://www.byma.com.ar/productos/productos-financieros/opciones
A30: Butterfly reference | D30: https://www.optionseducation.org/strategies/all-strategies/long-call-butterfly
A31: Ratio reference | D31: https://www.optionseducation.org/strategies/all-strategies/short-ratio-call-spread
A35: Date | B35: GGAL price | C35: Open | D35: High | E35: Low | F35: Raw volume
A36: 46174 | B36: 7640 | C36: 7490 | D36: 7725 | E36: 7405 | F36: 28360044544
A37: 46175 | B37: 7585 | C37: 7645 | D37: 7645 | E37: 7425 | F37: 22263787520
A38: 46176 | B38: 7350 | C38: 7520 | D38: 7575 | E38: 7310 | F38: 17648420864
A39: 46177 | B39: 7340 | C39: 7350 | D39: 7485 | E39: 7265 | F39: 18536675328
A40: 46178 | B40: 7205 | C40: 7340 | D40: 7400 | E40: 7135 | F40: 23260377088
A41: 46181 | B41: 7340 | C41: 7300 | D41: 7460 | E41: 7150 | F41: 27055659008
A42: 46182 | B42: 7545 | C42: 7350 | D42: 7650 | E42: 7310 | F42: 41855709184
A43: 46183 | B43: 7485 | C43: 7540 | D43: 7635 | E43: 7435 | F43: 28395188224
A44: 46184 | B44: 8270 | C44: 7680 | D44: 8320 | E44: 7680 | F44: 89861103616
A45: 46185 | B45: 8210 | C45: 8300 | D45: 8450 | E45: 8170 | F45: 46344859648
A46: 46189 | B46: 8160 | C46: 8230 | D46: 8400 | E46: 8105 | F46: 28046338048
A47: 46190 | B47: 8365 | C47: 8160 | D47: 8715 | E47: 8140 | F47: 42074746880
... A110: 46281 | B110: 6760 | C110: 6705 | D110: 6830 | E110: 6660 | F110: 6813778432

Sheet Ratio explorer
A2: Ratio explorer
P3: Selection lists
A4: Change the four amber cells. Buy one option at the long strike and sell the chosen quantity at the short strike.
P5: Call strikes | Q5: Put strikes
A6: Option type | B6: call | D6: =IF(OR(B6="",B7="",B8="",B9=""),"Choose all four inputs",IF(AND(B6<>"call",B6<>"put"),"Choose call or put",IF(AND(B9<>"1:1",B9<>"1:2"),"Choose 1:1 or 1:2",IF(OR(NOT(ISNUMBER(B7)),NOT(ISNUMBER(B8))),"Choose numeric strikes",IF(B7=B8,"Choose two different strikes",IF(OR(COUNTIFS('IV history'!$C$7:$C$926,B6,'IV history'!$D$7:$D$926,B7)=0,COUNTIFS('IV history'!$C$7:$C$926,B6,'IV history'!$D$7:$D$926,B8)=0),"Strike unavailable for this type","Ready")))))) -> Ready | P6: 4200 | Q6: 4200
A7: Long strike | B7: 6800 | P7: 4400 | Q7: 4400
A8: Short strike | B8: 7000 | D8: Latest date | E8: =A56 -> 46281 | G8: Cost / share | H8: =IF(ISNUMBER(D56),D56,"n.a.") -> 86.78 | J8: Cost / contract set | L8: =IF(ISNUMBER(E56),E56,"n.a.") -> 8678 | P8: 4600 | Q8: 4600
A9: Long : short ratio | B9: 1:1 | P9: 4800 | Q9: 4800
A10: Short quantity | B10: =IF(B9="1:1",1,IF(B9="1:2",2,"")) -> 1 | D10: Long-leg IV | E10: =IF(ISNUMBER(F56),F56,"n.a.") -> 0.4043901 | G10: Short-leg IV | H10: =IF(ISNUMBER(G56),G56,"n.a.") -> 0.41615491 | P10: 5000 | Q10: 5000
A11: Shares per contract | B11: ='Model inputs'!B8 -> 100 | P11: 5200 | Q11: 5200
A12: Expiry | B12: ='Model inputs'!B5 -> 46311 | D12: =IF(D6<>"Ready","Select valid contracts to populate the charts.",IF(B9="1:1","1:1 spread: long premium minus short premium.",IF(B6="call","1:2 calls: uncovered upside exposure, with unlimited potential loss.","1:2 puts: substantial downside exposure if GGAL falls."))) -> 1:1 spread: long premium minus short premium. | P12: 5400 | Q12: 5400
P13: 5600 | Q13: 5600
A14: Positive cost = debit. Negative cost = credit. ARS per share, before fees and slippage. | P14: 5800 | Q14: 5800
A15: Costs include flagged prices. IV assumptions: 30% rate, zero dividends. Gaps mean unavailable IV. | P15: 6000 | Q15: 6000
P16: 6200 | Q16: 6200
P17: 6400 | Q17: 6400
P18: 6600 | Q18: 6600
P19: 6800 | Q19: 6800
P20: 7000 | Q20: 7000
P21: 7200 | Q21: 7200
P22: 7400 | Q22: 7400
P23: 7600 | Q23: 7600
P24: 7800 | Q24: 7800
P25: 8000 | Q25: 8000
P26: 8300 | Q26: 8300
P27: 8600 | Q27: 8600
... P29: 9200 | Q29: 9200
P30: 9500
P31: 9900
S34: Chart helpers: #N/A means a deliberate gap, never a zero.
A37: Date | B37: Long premium | C37: Short premium | D37: Cost / share | E37: Cost / set | F37: Long IV | G37: Short IV | H37: IV gap (pp) | I37: Long data | J37: Short data | K37: Long rows | L37: Short rows | M37: Long IV count | N37: Short IV count | S37: Date | T37: Historical cost | U37: Long-leg IV | V37: Short-leg IV
A38: ='Daily volatility'!A7 -> 46255 | B38: =IF(K38<>1,"",SUMIFS('IV history'!$E$7:$E$926,'IV history'!$A$7:$A$926,A38,'IV history'!$C$7:$C$926,$B$6,'IV history'!$D$7:$D$926,$B$7)) -> 520 | C38: =IF(L38<>1,"",SUMIFS('IV history'!$E$7:$E$926,'IV history'!$A$7:$A$926,A38,'IV history'!$C$7:$C$926,$B$6,'IV history'!$D$7:$D$926,$B$8)) -> 419.73 | D38: =IF(AND(ISNUMBER(B38),ISNUMBER(C38)),B38-$B$10*C38,"") -> 100.27 | E38: =IF(ISNUMBER(D38),D38*$B$11,"") -> 10027 | F38: =IF(M38<>1,"",SUMIFS('IV history'!$K$7:$K$926,'IV history'!$A$7:$A$926,A38,'IV history'!$C$7:$C$926,$B$6,'IV history'!$D$7:$D$926,$B$7)) -> 0.44393323 | G38: =IF(N38<>1,"",SUMIFS('IV history'!$K$7:$K$926,'IV history'!$A$7:$A$926,A38,'IV history'!$C$7:$C$926,$B$6,'IV history'!$D$7:$D$926,$B$8)) -> 0.43488738 | H38: =IF(AND(ISNUMBER(F38),ISNUMBER(G38)),100*(F38-G38),"") -> 0.90458578 | I38: =IF($D$6<>"Ready","Check selection",IF(K38=0,"No observation",IF(K38>1,"Duplicate observations",IF(M38=0,"Flagged; IV unavailable","Screen passed")))) -> Screen passed | J38: =IF($D$6<>"Ready","Check selection",IF(L38=0,"No observation",IF(L38>1,"Duplicate observations",IF(N38=0,"Flagged; IV unavailable","Screen passed")))) -> Screen passed | K38: =IF($D$6<>"Ready","",COUNTIFS('IV history'!$A$7:$A$926,A38,'IV history'!$C$7:$C$926,$B$6,'IV history'!$D$7:$D$926,$B$7)) -> 1 | L38: =IF($D$6<>"Ready","",COUNTIFS('IV history'!$A$7:$A$926,A38,'IV history'!$C$7:$C$926,$B$6,'IV history'!$D$7:$D$926,$B$8)) -> 1 | M38: =IF(K38<>1,"",COUNTIFS('IV history'!$A$7:$A$926,A38,'IV history'!$C$7:$C$926,$B$6,'IV history'!$D$7:$D$926,$B$7,'IV history'!$K$7:$K$926,">0")) -> 1 | N38: =IF(L38<>1,"",COUNTIFS('IV history'!$A$7:$A$926,A38,'IV history'!$C$7:$C$926,$B$6,'IV history'!$D$7:$D$926,$B$8,'IV history'!$K$7:$K$926,">0")) -> 1 | S38: =TEXT(A38,"dd-mmm") -> 21-ago | T38: =IF(ISNUMBER(D38),D38,NA()) -> 100.27 | U38: =IF(ISNUMBER(F38),F38,NA()) -> 0.44393323 | V38: =IF(ISNUMBER(G38),G38,NA()) -> 0.43488738
A39: ='Daily volatility'!A8 -> 46258 | B39: =IF(K39<>1,"",SUMIFS('IV history'!$E$7:$E$926,'IV history'!$A$7:$A$926,A39,'IV history'!$C$7:$C$926,$B$6,'IV history'!$D$7:$D$926,$B$7)) -> 686.77 | C39: =IF(L39<>1,"",SUMIFS('IV history'!$E$7:$E$926,'IV history'!$A$7:$A$926,A39,'IV history'!$C$7:$C$926,$B$6,'IV history'!$D$7:$D$926,$B$8)) -> 579.21 | D39: =IF(AND(ISNUMBER(B39),ISNUMBER(C39)),B39-$B$10*C39,"") -> 107.56 | E39: =IF(ISNUMBER(D39),D39*$B$11,"") -> 10756 | F39: =IF(M39<>1,"",SUMIFS('IV history'!$K$7:$K$926,'IV history'!$A$7:$A$926,A39,'IV history'!$C$7:$C$926,$B$6,'IV history'!$D$7:$D$926,$B$7)) -> 0.42251204 | G39: =IF(N39<>1,"",SUMIFS('IV history'!$K$7:$K$926,'IV history'!$A$7:$A$926,A39,'IV history'!$C$7:$C$926,$B$6,'IV history'!$D$7:$D$926,$B$8)) -> 0.42841322 | H39: =IF(AND(ISNUMBER(F39),ISNUMBER(G39)),100*(F39-G39),"") -> -0.59011758 | I39: =IF($D$6<>"Ready","Check selection",IF(K39=0,"No observation",IF(K39>1,"Duplicate observations",IF(M39=0,"Flagged; IV unavailable","Screen passed")))) -> Screen passed | J39: =IF($D$6<>"Ready","Check selection",IF(L39=0,"No observation",IF(L39>1,"Duplicate observations",IF(N39=0,"Flagged; IV unavailable","Screen passed")))) -> Screen passed | K39: =IF($D$6<>"Ready","",COUNTIFS('IV history'!$A$7:$A$926,A39,'IV history'!$C$7:$C$926,$B$6,'IV history'!$D$7:$D$926,$B$7)) -> 1 | L39: =IF($D$6<>"Ready","",COUNTIFS('IV history'!$A$7:$A$926,A39,'IV history'!$C$7:$C$926,$B$6,'IV history'!$D$7:$D$926,$B$8)) -> 1 | M39: =IF(K39<>1,"",COUNTIFS('IV history'!$A$7:$A$926,A39,'IV history'!$C$7:$C$926,$B$6,'IV history'!$D$7:$D$926,$B$7,'IV history'!$K$7:$K$926,">0")) -> 1 | N39: =IF(L39<>1,"",COUNTIFS('IV history'!$A$7:$A$926,A39,'IV history'!$C$7:$C$926,$B$6,'IV history'!$D$7:$D$926,$B$8,'IV history'!$K$7:$K$926,">0")) -> 1 | S39: =TEXT(A39,"dd-mmm") -> 24-ago | T39: =IF(ISNUMBER(D39),D39,NA()) -> 107.56 | U39: =IF(ISNUMBER(F39),F39,NA()) -> 0.42251204 | V39: =IF(ISNUMBER(G39),G39,NA()) -> 0.42841322
A40: ='Daily volatility'!A9 -> 46259 | B40: =IF(K40<>1,"",SUMIFS('IV history'!$E$7:$E$926,'IV history'!$A$7:$A$926,A40,'IV history'!$C$7:$C$926,$B$6,'IV history'!$D$7:$D$926,$B$7)) -> 720.8 | C40: =IF(L40<>1,"",SUMIFS('IV history'!$E$7:$E$926,'IV history'!$A$7:$A$926,A40,'IV history'!$C$7:$C$926,$B$6,'IV history'!$D$7:$D$926,$B$8)) -> 604.66 | D40: =IF(AND(ISNUMBER(B40),ISNUMBER(C40)),B40-$B$10*C40,"") -> 116.14 | E40: =IF(ISNUMBER(D40),D40*$B$11,"") -> 11614 | F40: =IF(M40<>1,"",SUMIFS('IV history'!$K$7:$K$926,'IV history'!$A$7:$A$926,A40,'IV history'!$C$7:$C$926,$B$6,'IV history'!$D$7:$D$926,$B$7)) -> 0.36875437 | G40: =IF(N40<>1,"",SUMIFS('IV history'!$K$7:$K$926,'IV history'!$A$7:$A$926,A40,'IV history'!$C$7:$C$926,$B$6,'IV history'!$D$7:$D$926,$B$8)) -> 0.37980973 | H40: =IF(AND(ISNUMBER(F40),ISNUMBER(G40)),100*(F40-G40),"") -> -1.1055359 | I40: =IF($D$6<>"Ready","Check selection",IF(K40=0,"No observation",IF(K40>1,"Duplicate observations",IF(M40=0,"Flagged; IV unavailable","Screen passed")))) -> Screen passed | J40: =IF($D$6<>"Ready","Check selection",IF(L40=0,"No observation",IF(L40>1,"Duplicate observations",IF(N40=0,"Flagged; IV unavailable","Screen passed")))) -> Screen passed | K40: =IF($D$6<>"Ready","",COUNTIFS('IV history'!$A$7:$A$926,A40,'IV history'!$C$7:$C$926,$B$6,'IV history'!$D$7:$D$926,$B$7)) -> 1 | L40: =IF($D$6<>"Ready","",COUNTIFS('IV history'!$A$7:$A$926,A40,'IV history'!$C$7:$C$926,$B$6,'IV history'!$D$7:$D$926,$B$8)) -> 1 | M40: =IF(K40<>1,"",COUNTIFS('IV history'!$A$7:$A$926,A40,'IV history'!$C$7:$C$926,$B$6,'IV history'!$D$7:$D$926,$B$7,'IV history'!$K$7:$K$926,">0")) -> 1 | N40: =IF(L40<>1,"",COUNTIFS('IV history'!$A$7:$A$926,A40,'IV history'!$C$7:$C$926,$B$6,'IV history'!$D$7:$D$926,$B$8,'IV history'!$K$7:$K$926,">0")) -> 1 | S40: =TEXT(A40,"dd-mmm") -> 25-ago | T40: =IF(ISNUMBER(D40),D40,NA()) -> 116.14 | U40: =IF(ISNUMBER(F40),F40,NA()) -> 0.36875437 | V40: =IF(ISNUMBER(G40),G40,NA()) -> 0.37980973
A41: ='Daily volatility'!A10 -> 46260 | B41: =IF(K41<>1,"",SUMIFS('IV history'!$E$7:$E$926,'IV history'!$A$7:$A$926,A41,'IV history'!$C$7:$C$926,$B$6,'IV history'!$D$7:$D$926,$B$7)) -> 690.84 | C41: =IF(L41<>1,"",SUMIFS('IV history'!$E$7:$E$926,'IV history'!$A$7:$A$926,A41,'IV history'!$C$7:$C$926,$B$6,'IV history'!$D$7:$D$926,$B$8)) -> 565.7 | D41: =IF(AND(ISNUMBER(B41),ISNUMBER(C41)),B41-$B$10*C41,"") -> 125.14 | E41: =IF(ISNUMBER(D41),D41*$B$11,"") -> 12514 | F41: =IF(M41<>1,"",SUMIFS('IV history'!$K$7:$K$926,'IV history'!$A$7:$A$926,A41,'IV history'!$C$7:$C$926,$B$6,'IV history'!$D$7:$D$926,$B$7)) -> 0.36765775 | G41: =IF(N41<>1,"",SUMIFS('IV history'!$K$7:$K$926,'IV history'!$A$7:$A$926,A41,'IV history'!$C$7:$C$926,$B$6,'IV history'!$D$7:$D$926,$B$8)) -> 0.36729783 | H41: =IF(AND(ISNUMBER(F41),ISNUMBER(G41)),100*(F41-G41),"") -> 0.035992406 | I41: =IF($D$6<>"Ready","Check selection",IF(K41=0,"No observation",IF(K41>1,"Duplicate observations",IF(M41=0,"Flagged; IV unavailable","Screen passed")))) -> Screen passed | J41: =IF($D$6<>"Ready","Check selection",IF(L41=0,"No observation",IF(L41>1,"Duplicate observations",IF(N41=0,"Flagged; IV unavailable","Screen passed")))) -> Screen passed | K41: =IF($D$6<>"Ready","",COUNTIFS('IV history'!$A$7:$A$926,A41,'IV history'!$C$7:$C$926,$B$6,'IV history'!$D$7:$D$926,$B$7)) -> 1 | L41: =IF($D$6<>"Ready","",COUNTIFS('IV history'!$A$7:$A$926,A41,'IV history'!$C$7:$C$926,$B$6,'IV history'!$D$7:$D$926,$B$8)) -> 1 | M41: =IF(K41<>1,"",COUNTIFS('IV history'!$A$7:$A$926,A41,'IV history'!$C$7:$C$926,$B$6,'IV history'!$D$7:$D$926,$B$7,'IV history'!$K$7:$K$926,">0")) -> 1 | N41: =IF(L41<>1,"",COUNTIFS('IV history'!$A$7:$A$926,A41,'IV history'!$C$7:$C$926,$B$6,'IV history'!$D$7:$D$926,$B$8,'IV history'!$K$7:$K$926,">0")) -> 1 | S41: =TEXT(A41,"dd-mmm") -> 26-ago | T41: =IF(ISNUMBER(D41),D41,NA()) -> 125.14 | U41: =IF(ISNUMBER(F41),F41,NA()) -> 0.36765775 | V41: =IF(ISNUMBER(G41),G41,NA()) -> 0.36729783
A42: ='Daily volatility'!A11 -> 46261 | B42: =IF(K42<>1,"",SUMIFS('IV history'!$E$7:$E$926,'IV history'!$A$7:$A$926,A42,'IV history'!$C$7:$C$926,$B$6,'IV history'!$D$7:$D$926,$B$7)) -> 587.6 | C42: =IF(L42<>1,"",SUMIFS('IV history'!$E$7:$E$926,'IV history'!$A$7:$A$926,A42,'IV history'!$C$7:$C$926,$B$6,'IV history'!$D$7:$D$926,$B$8)) -> 484.8 | D42: =IF(AND(ISNUMBER(B42),ISNUMBER(C42)),B42-$B$10*C42,"") -> 102.8 | E42: =IF(ISNUMBER(D42),D42*$B$11,"") -> 10280 | F42: =IF(M42<>1,"",SUMIFS('IV history'!$K$7:$K$926,'IV history'!$A$7:$A$926,A42,'IV history'!$C$7:$C$926,$B$6,'IV history'!$D$7:$D$926,$B$7)) -> 0.38954597 | G42: =IF(N42<>1,"",SUMIFS('IV history'!$K$7:$K$926,'IV history'!$A$7:$A$926,A42,'IV history'!$C$7:$C$926,$B$6,'IV history'!$D$7:$D$926,$B$8)) -> 0.39748351 | H42: =IF(AND(ISNUMBER(F42),ISNUMBER(G42)),100*(F42-G42),"") -> -0.79375434 | I42: =IF($D$6<>"Ready","Check selection",IF(K42=0,"No observation",IF(K42>1,"Duplicate observations",IF(M42=0,"Flagged; IV unavailable","Screen passed")))) -> Screen passed | J42: =IF($D$6<>"Ready","Check selection",IF(L42=0,"No observation",IF(L42>1,"Duplicate observations",IF(N42=0,"Flagged; IV unavailable","Screen passed")))) -> Screen passed | K42: =IF($D$6<>"Ready","",COUNTIFS('IV history'!$A$7:$A$926,A42,'IV history'!$C$7:$C$926,$B$6,'IV history'!$D$7:$D$926,$B$7)) -> 1 | L42: =IF($D$6<>"Ready","",COUNTIFS('IV history'!$A$7:$A$926,A42,'IV history'!$C$7:$C$926,$B$6,'IV history'!$D$7:$D$926,$B$8)) -> 1 | M42: =IF(K42<>1,"",COUNTIFS('IV history'!$A$7:$A$926,A42,'IV history'!$C$7:$C$926,$B$6,'IV history'!$D$7:$D$926,$B$7,'IV history'!$K$7:$K$926,">0")) -> 1 | N42: =IF(L42<>1,"",COUNTIFS('IV history'!$A$7:$A$926,A42,'IV history'!$C$7:$C$926,$B$6,'IV history'!$D$7:$D$926,$B$8,'IV history'!$K$7:$K$926,">0")) -> 1 | S42: =TEXT(A42,"dd-mmm") -> 27-ago | T42: =IF(ISNUMBER(D42),D42,NA()) -> 102.8 | U42: =IF(ISNUMBER(F42),F42,NA()) -> 0.38954597 | V42: =IF(ISNUMBER(G42),G42,NA()) -> 0.39748351
A43: ='Daily volatility'!A12 -> 46262 | B43: =IF(K43<>1,"",SUMIFS('IV history'!$E$7:$E$926,'IV history'!$A$7:$A$926,A43,'IV history'!$C$7:$C$926,$B$6,'IV history'!$D$7:$D$926,$B$7)) -> 532.71 | C43: =IF(L43<>1,"",SUMIFS('IV history'!$E$7:$E$926,'IV history'!$A$7:$A$926,A43,'IV history'!$C$7:$C$926,$B$6,'IV history'!$D$7:$D$926,$B$8)) -> 438.78 | D43: =IF(AND(ISNUMBER(B43),ISNUMBER(C43)),B43-$B$10*C43,"") -> 93.93 | E43: =IF(ISNUMBER(D43),D43*$B$11,"") -> 9393 | F43: =IF(M43<>1,"",SUMIFS('IV history'!$K$7:$K$926,'IV history'!$A$7:$A$926,A43,'IV history'!$C$7:$C$926,$B$6,'IV history'!$D$7:$D$926,$B$7)) -> 0.38728894 | G43: =IF(N43<>1,"",SUMIFS('IV history'!$K$7:$K$926,'IV history'!$A$7:$A$926,A43,'IV history'!$C$7:$C$926,$B$6,'IV history'!$D$7:$D$926,$B$8)) -> 0.39881475 | H43: =IF(AND(ISNUMBER(F43),ISNUMBER(G43)),100*(F43-G43),"") -> -1.1525809 | I43: =IF($D$6<>"Ready","Check selection",IF(K43=0,"No observation",IF(K43>1,"Duplicate observations",IF(M43=0,"Flagged; IV unavailable","Screen passed")))) -> Screen passed | J43: =IF($D$6<>"Ready","Check selection",IF(L43=0,"No observation",IF(L43>1,"Duplicate observations",IF(N43=0,"Flagged; IV unavailable","Screen passed")))) -> Screen passed | K43: =IF($D$6<>"Ready","",COUNTIFS('IV history'!$A$7:$A$926,A43,'IV history'!$C$7:$C$926,$B$6,'IV history'!$D$7:$D$926,$B$7)) -> 1 | L43: =IF($D$6<>"Ready","",COUNTIFS('IV history'!$A$7:$A$926,A43,'IV history'!$C$7:$C$926,$B$6,'IV history'!$D$7:$D$926,$B$8)) -> 1 | M43: =IF(K43<>1,"",COUNTIFS('IV history'!$A$7:$A$926,A43,'IV history'!$C$7:$C$926,$B$6,'IV history'!$D$7:$D$926,$B$7,'IV history'!$K$7:$K$926,">0")) -> 1 | N43: =IF(L43<>1,"",COUNTIFS('IV history'!$A$7:$A$926,A43,'IV history'!$C$7:$C$926,$B$6,'IV history'!$D$7:$D$926,$B$8,'IV history'!$K$7:$K$926,">0")) -> 1 | S43: =TEXT(A43,"dd-mmm") -> 28-ago | T43: =IF(ISNUMBER(D43),D43,NA()) -> 93.93 | U43: =IF(ISNUMBER(F43),F43,NA()) -> 0.38728894 | V43: =IF(ISNUMBER(G43),G43,NA()) -> 0.39881475
A44: ='Daily volatility'!A13 -> 46265 | B44: =IF(K44<>1,"",SUMIFS('IV history'!$E$7:$E$926,'IV history'!$A$7:$A$926,A44,'IV history'!$C$7:$C$926,$B$6,'IV history'!$D$7:$D$926,$B$7)) -> 661.02 | C44: =IF(L44<>1,"",SUMIFS('IV history'!$E$7:$E$926,'IV history'!$A$7:$A$926,A44,'IV history'!$C$7:$C$926,$B$6,'IV history'!$D$7:$D$926,$B$8)) -> 552.7 | D44: =IF(AND(ISNUMBER(B44),ISNUMBER(C44)),B44-$B$10*C44,"") -> 108.32 | E44: =IF(ISNUMBER(D44),D44*$B$11,"") -> 10832 | F44: =IF(M44<>1,"",SUMIFS('IV history'!$K$7:$K$926,'IV history'!$A$7:$A$926,A44,'IV history'!$C$7:$C$926,$B$6,'IV history'!$D$7:$D$926,$B$7)) -> 0.39913219 | G44: =IF(N44<>1,"",SUMIFS('IV history'!$K$7:$K$926,'IV history'!$A$7:$A$926,A44,'IV history'!$C$7:$C$926,$B$6,'IV history'!$D$7:$D$926,$B$8)) -> 0.41152443 | H44: =IF(AND(ISNUMBER(F44),ISNUMBER(G44)),100*(F44-G44),"") -> -1.2392233 | I44: =IF($D$6<>"Ready","Check selection",IF(K44=0,"No observation",IF(K44>1,"Duplicate observations",IF(M44=0,"Flagged; IV unavailable","Screen passed")))) -> Screen passed | J44: =IF($D$6<>"Ready","Check selection",IF(L44=0,"No observation",IF(L44>1,"Duplicate observations",IF(N44=0,"Flagged; IV unavailable","Screen passed")))) -> Screen passed | K44: =IF($D$6<>"Ready","",COUNTIFS('IV history'!$A$7:$A$926,A44,'IV history'!$C$7:$C$926,$B$6,'IV history'!$D$7:$D$926,$B$7)) -> 1 | L44: =IF($D$6<>"Ready","",COUNTIFS('IV history'!$A$7:$A$926,A44,'IV history'!$C$7:$C$926,$B$6,'IV history'!$D$7:$D$926,$B$8)) -> 1 | M44: =IF(K44<>1,"",COUNTIFS('IV history'!$A$7:$A$926,A44,'IV history'!$C$7:$C$926,$B$6,'IV history'!$D$7:$D$926,$B$7,'IV history'!$K$7:$K$926,">0")) -> 1 | N44: =IF(L44<>1,"",COUNTIFS('IV history'!$A$7:$A$926,A44,'IV history'!$C$7:$C$926,$B$6,'IV history'!$D$7:$D$926,$B$8,'IV history'!$K$7:$K$926,">0")) -> 1 | S44: =TEXT(A44,"dd-mmm") -> 31-ago | T44: =IF(ISNUMBER(D44),D44,NA()) -> 108.32 | U44: =IF(ISNUMBER(F44),F44,NA()) -> 0.39913219 | V44: =IF(ISNUMBER(G44),G44,NA()) -> 0.41152443
A45: ='Daily volatility'!A14 -> 46266 | B45: =IF(K45<>1,"",SUMIFS('IV history'!$E$7:$E$926,'IV history'!$A$7:$A$926,A45,'IV history'!$C$7:$C$926,$B$6,'IV history'!$D$7:$D$926,$B$7)) -> 688.81 | C45: =IF(L45<>1,"",SUMIFS('IV history'!$E$7:$E$926,'IV history'!$A$7:$A$926,A45,'IV history'!$C$7:$C$926,$B$6,'IV history'!$D$7:$D$926,$B$8)) -> 562.73 | D45: =IF(AND(ISNUMBER(B45),ISNUMBER(C45)),B45-$B$10*C45,"") -> 126.08 | E45: =IF(ISNUMBER(D45),D45*$B$11,"") -> 12608 | F45: =IF(M45<>1,"",SUMIFS('IV history'!$K$7:$K$926,'IV history'!$A$7:$A$926,A45,'IV history'!$C$7:$C$926,$B$6,'IV history'!$D$7:$D$926,$B$7)) -> 0.40242664 | G45: =IF(N45<>1,"",SUMIFS('IV history'!$K$7:$K$926,'IV history'!$A$7:$A$926,A45,'IV history'!$C$7:$C$926,$B$6,'IV history'!$D$7:$D$926,$B$8)) -> 0.3990126 | H45: =IF(AND(ISNUMBER(F45),ISNUMBER(G45)),100*(F45-G45),"") -> 0.34140474 | I45: =IF($D$6<>"Ready","Check selection",IF(K45=0,"No observation",IF(K45>1,"Duplicate observations",IF(M45=0,"Flagged; IV unavailable","Screen passed")))) -> Screen passed | J45: =IF($D$6<>"Ready","Check selection",IF(L45=0,"No observation",IF(L45>1,"Duplicate observations",IF(N45=0,"Flagged; IV unavailable","Screen passed")))) -> Screen passed | K45: =IF($D$6<>"Ready","",COUNTIFS('IV history'!$A$7:$A$926,A45,'IV history'!$C$7:$C$926,$B$6,'IV history'!$D$7:$D$926,$B$7)) -> 1 | L45: =IF($D$6<>"Ready","",COUNTIFS('IV history'!$A$7:$A$926,A45,'IV history'!$C$7:$C$926,$B$6,'IV history'!$D$7:$D$926,$B$8)) -> 1 | M45: =IF(K45<>1,"",COUNTIFS('IV history'!$A$7:$A$926,A45,'IV history'!$C$7:$C$926,$B$6,'IV history'!$D$7:$D$926,$B$7,'IV history'!$K$7:$K$926,">0")) -> 1 | N45: =IF(L45<>1,"",COUNTIFS('IV history'!$A$7:$A$926,A45,'IV history'!$C$7:$C$926,$B$6,'IV history'!$D$7:$D$926,$B$8,'IV history'!$K$7:$K$926,">0")) -> 1 | S45: =TEXT(A45,"dd-mmm") -> 01-sep | T45: =IF(ISNUMBER(D45),D45,NA()) -> 126.08 | U45: =IF(ISNUMBER(F45),F45,NA()) -> 0.40242664 | V45: =IF(ISNUMBER(G45),G45,NA()) -> 0.3990126
A46: ='Daily volatility'!A15 -> 46267 | B46: =IF(K46<>1,"",SUMIFS('IV history'!$E$7:$E$926,'IV history'!$A$7:$A$926,A46,'IV history'!$C$7:$C$926,$B$6,'IV history'!$D$7:$D$926,$B$7)) -> 745.47 | C46: =IF(L46<>1,"",SUMIFS('IV history'!$E$7:$E$926,'IV history'!$A$7:$A$926,A46,'IV history'!$C$7:$C$926,$B$6,'IV history'!$D$7:$D$926,$B$8)) -> 617.88 | D46: =IF(AND(ISNUMBER(B46),ISNUMBER(C46)),B46-$B$10*C46,"") -> 127.59 | E46: =IF(ISNUMBER(D46),D46*$B$11,"") -> 12759 | F46: =IF(M46<>1,"",SUMIFS('IV history'!$K$7:$K$926,'IV history'!$A$7:$A$926,A46,'IV history'!$C$7:$C$926,$B$6,'IV history'!$D$7:$D$926,$B$7)) -> 0.37924934 | G46: =IF(N46<>1,"",SUMIFS('IV history'!$K$7:$K$926,'IV history'!$A$7:$A$926,A46,'IV history'!$C$7:$C$926,$B$6,'IV history'!$D$7:$D$926,$B$8)) -> 0.38588835 | H46: =IF(AND(ISNUMBER(F46),ISNUMBER(G46)),100*(F46-G46),"") -> -0.66390105 | I46: =IF($D$6<>"Ready","Check selection",IF(K46=0,"No observation",IF(K46>1,"Duplicate observations",IF(M46=0,"Flagged; IV unavailable","Screen passed")))) -> Screen passed | J46: =IF($D$6<>"Ready","Check selection",IF(L46=0,"No observation",IF(L46>1,"Duplicate observations",IF(N46=0,"Flagged; IV unavailable","Screen passed")))) -> Screen passed | K46: =IF($D$6<>"Ready","",COUNTIFS('IV history'!$A$7:$A$926,A46,'IV history'!$C$7:$C$926,$B$6,'IV history'!$D$7:$D$926,$B$7)) -> 1 | L46: =IF($D$6<>"Ready","",COUNTIFS('IV history'!$A$7:$A$926,A46,'IV history'!$C$7:$C$926,$B$6,'IV history'!$D$7:$D$926,$B$8)) -> 1 | M46: =IF(K46<>1,"",COUNTIFS('IV history'!$A$7:$A$926,A46,'IV history'!$C$7:$C$926,$B$6,'IV history'!$D$7:$D$926,$B$7,'IV history'!$K$7:$K$926,">0")) -> 1 | N46: =IF(L46<>1,"",COUNTIFS('IV history'!$A$7:$A$926,A46,'IV history'!$C$7:$C$926,$B$6,'IV history'!$D$7:$D$926,$B$8,'IV history'!$K$7:$K$926,">0")) -> 1 | S46: =TEXT(A46,"dd-mmm") -> 02-sep | T46: =IF(ISNUMBER(D46),D46,NA()) -> 127.59 | U46: =IF(ISNUMBER(F46),F46,NA()) -> 0.37924934 | V46: =IF(ISNUMBER(G46),G46,NA()) -> 0.38588835
A47: ='Daily volatility'!A16 -> 46268 | B47: =IF(K47<>1,"",SUMIFS('IV history'!$E$7:$E$926,'IV history'!$A$7:$A$926,A47,'IV history'!$C$7:$C$926,$B$6,'IV history'!$D$7:$D$926,$B$7)) -> 665.11 | C47: =IF(L47<>1,"",SUMIFS('IV history'!$E$7:$E$926,'IV history'!$A$7:$A$926,A47,'IV history'!$C$7:$C$926,$B$6,'IV history'!$D$7:$D$926,$B$8)) -> 547.83 | D47: =IF(AND(ISNUMBER(B47),ISNUMBER(C47)),B47-$B$10*C47,"") -> 117.28 | E47: =IF(ISNUMBER(D47),D47*$B$11,"") -> 11728 | F47: =IF(M47<>1,"",SUMIFS('IV history'!$K$7:$K$926,'IV history'!$A$7:$A$926,A47,'IV history'!$C$7:$C$926,$B$6,'IV history'!$D$7:$D$926,$B$7)) -> 0.37750234 | G47: =IF(N47<>1,"",SUMIFS('IV history'!$K$7:$K$926,'IV history'!$A$7:$A$926,A47,'IV history'!$C$7:$C$926,$B$6,'IV history'!$D$7:$D$926,$B$8)) -> 0.38797271 | H47: =IF(AND(ISNUMBER(F47),ISNUMBER(G47)),100*(F47-G47),"") -> -1.0470365 | I47: =IF($D$6<>"Ready","Check selection",IF(K47=0,"No observation",IF(K47>1,"Duplicate observations",IF(M47=0,"Flagged; IV unavailable","Screen passed")))) -> Screen passed | J47: =IF($D$6<>"Ready","Check selection",IF(L47=0,"No observation",IF(L47>1,"Duplicate observations",IF(N47=0,"Flagged; IV unavailable","Screen passed")))) -> Screen passed | K47: =IF($D$6<>"Ready","",COUNTIFS('IV history'!$A$7:$A$926,A47,'IV history'!$C$7:$C$926,$B$6,'IV history'!$D$7:$D$926,$B$7)) -> 1 | L47: =IF($D$6<>"Ready","",COUNTIFS('IV history'!$A$7:$A$926,A47,'IV history'!$C$7:$C$926,$B$6,'IV history'!$D$7:$D$926,$B$8)) -> 1 | M47: =IF(K47<>1,"",COUNTIFS('IV history'!$A$7:$A$926,A47,'IV history'!$C$7:$C$926,$B$6,'IV history'!$D$7:$D$926,$B$7,'IV history'!$K$7:$K$926,">0")) -> 1 | N47: =IF(L47<>1,"",COUNTIFS('IV history'!$A$7:$A$926,A47,'IV history'!$C$7:$C$926,$B$6,'IV history'!$D$7:$D$926,$B$8,'IV history'!$K$7:$K$926,">0")) -> 1 | S47: =TEXT(A47,"dd-mmm") -> 03-sep | T47: =IF(ISNUMBER(D47),D47,NA()) -> 117.28 | U47: =IF(ISNUMBER(F47),F47,NA()) -> 0.37750234 | V47: =IF(ISNUMBER(G47),G47,NA()) -> 0.38797271
A48: ='Daily volatility'!A17 -> 46269 | B48: =IF(K48<>1,"",SUMIFS('IV history'!$E$7:$E$926,'IV history'!$A$7:$A$926,A48,'IV history'!$C$7:$C$926,$B$6,'IV history'!$D$7:$D$926,$B$7)) -> 616.63 | C48: =IF(L48<>1,"",SUMIFS('IV history'!$E$7:$E$926,'IV history'!$A$7:$A$926,A48,'IV history'!$C$7:$C$926,$B$6,'IV history'!$D$7:$D$926,$B$8)) -> 501.55 | D48: =IF(AND(ISNUMBER(B48),ISNUMBER(C48)),B48-$B$10*C48,"") -> 115.08 | E48: =IF(ISNUMBER(D48),D48*$B$11,"") -> 11508 | F48: =IF(M48<>1,"",SUMIFS('IV history'!$K$7:$K$926,'IV history'!$A$7:$A$926,A48,'IV history'!$C$7:$C$926,$B$6,'IV history'!$D$7:$D$926,$B$7)) -> 0.38941375 | G48: =IF(N48<>1,"",SUMIFS('IV history'!$K$7:$K$926,'IV history'!$A$7:$A$926,A48,'IV history'!$C$7:$C$926,$B$6,'IV history'!$D$7:$D$926,$B$8)) -> 0.39497486 | H48: =IF(AND(ISNUMBER(F48),ISNUMBER(G48)),100*(F48-G48),"") -> -0.55611091 | I48: =IF($D$6<>"Ready","Check selection",IF(K48=0,"No observation",IF(K48>1,"Duplicate observations",IF(M48=0,"Flagged; IV unavailable","Screen passed")))) -> Screen passed | J48: =IF($D$6<>"Ready","Check selection",IF(L48=0,"No observation",IF(L48>1,"Duplicate observations",IF(N48=0,"Flagged; IV unavailable","Screen passed")))) -> Screen passed | K48: =IF($D$6<>"Ready","",COUNTIFS('IV history'!$A$7:$A$926,A48,'IV history'!$C$7:$C$926,$B$6,'IV history'!$D$7:$D$926,$B$7)) -> 1 | L48: =IF($D$6<>"Ready","",COUNTIFS('IV history'!$A$7:$A$926,A48,'IV history'!$C$7:$C$926,$B$6,'IV history'!$D$7:$D$926,$B$8)) -> 1 | M48: =IF(K48<>1,"",COUNTIFS('IV history'!$A$7:$A$926,A48,'IV history'!$C$7:$C$926,$B$6,'IV history'!$D$7:$D$926,$B$7,'IV history'!$K$7:$K$926,">0")) -> 1 | N48: =IF(L48<>1,"",COUNTIFS('IV history'!$A$7:$A$926,A48,'IV history'!$C$7:$C$926,$B$6,'IV history'!$D$7:$D$926,$B$8,'IV history'!$K$7:$K$926,">0")) -> 1 | S48: =TEXT(A48,"dd-mmm") -> 04-sep | T48: =IF(ISNUMBER(D48),D48,NA()) -> 115.08 | U48: =IF(ISNUMBER(F48),F48,NA()) -> 0.38941375 | V48: =IF(ISNUMBER(G48),G48,NA()) -> 0.39497486
A49: ='Daily volatility'!A18 -> 46272 | B49: =IF(K49<>1,"",SUMIFS('IV history'!$E$7:$E$926,'IV history'!$A$7:$A$926,A49,'IV history'!$C$7:$C$926,$B$6,'IV history'!$D$7:$D$926,$B$7)) -> 567 | C49: =IF(L49<>1,"",SUMIFS('IV history'!$E$7:$E$926,'IV history'!$A$7:$A$926,A49,'IV history'!$C$7:$C$926,$B$6,'IV history'!$D$7:$D$926,$B$8)) -> 460.71 | D49: =IF(AND(ISNUMBER(B49),ISNUMBER(C49)),B49-$B$10*C49,"") -> 106.29 | E49: =IF(ISNUMBER(D49),D49*$B$11,"") -> 10629 | F49: =IF(M49<>1,"",SUMIFS('IV history'!$K$7:$K$926,'IV history'!$A$7:$A$926,A49,'IV history'!$C$7:$C$926,$B$6,'IV history'!$D$7:$D$926,$B$7)) -> 0.41557605 | G49: =IF(N49<>1,"",SUMIFS('IV history'!$K$7:$K$926,'IV history'!$A$7:$A$926,A49,'IV history'!$C$7:$C$926,$B$6,'IV history'!$D$7:$D$926,$B$8)) -> 0.42273407 | H49: =IF(AND(ISNUMBER(F49),ISNUMBER(G49)),100*(F49-G49),"") -> -0.71580201 | I49: =IF($D$6<>"Ready","Check selection",IF(K49=0,"No observation",IF(K49>1,"Duplicate observations",IF(M49=0,"Flagged; IV unavailable","Screen passed")))) -> Screen passed | J49: =IF($D$6<>"Ready","Check selection",IF(L49=0,"No observation",IF(L49>1,"Duplicate observations",IF(N49=0,"Flagged; IV unavailable","Screen passed")))) -> Screen passed | K49: =IF($D$6<>"Ready","",COUNTIFS('IV history'!$A$7:$A$926,A49,'IV history'!$C$7:$C$926,$B$6,'IV history'!$D$7:$D$926,$B$7)) -> 1 | L49: =IF($D$6<>"Ready","",COUNTIFS('IV history'!$A$7:$A$926,A49,'IV history'!$C$7:$C$926,$B$6,'IV history'!$D$7:$D$926,$B$8)) -> 1 | M49: =IF(K49<>1,"",COUNTIFS('IV history'!$A$7:$A$926,A49,'IV history'!$C$7:$C$926,$B$6,'IV history'!$D$7:$D$926,$B$7,'IV history'!$K$7:$K$926,">0")) -> 1 | N49: =IF(L49<>1,"",COUNTIFS('IV history'!$A$7:$A$926,A49,'IV history'!$C$7:$C$926,$B$6,'IV history'!$D$7:$D$926,$B$8,'IV history'!$K$7:$K$926,">0")) -> 1 | S49: =TEXT(A49,"dd-mmm") -> 07-sep | T49: =IF(ISNUMBER(D49),D49,NA()) -> 106.29 | U49: =IF(ISNUMBER(F49),F49,NA()) -> 0.41557605 | V49: =IF(ISNUMBER(G49),G49,NA()) -> 0.42273407
... A56: ='Daily volatility'!A25 -> 46281 | B56: =IF(K56<>1,"",SUMIFS('IV history'!$E$7:$E$926,'IV history'!$A$7:$A$926,A56,'IV history'!$C$7:$C$926,$B$6,'IV history'!$D$7:$D$926,$B$7)) -> 376.43 | C56: =IF(L56<>1,"",SUMIFS('IV history'!$E$7:$E$926,'IV history'!$A$7:$A$926,A56,'IV history'!$C$7:$C$926,$B$6,'IV history'!$D$7:$D$926,$B$8)) -> 289.65 | D56: =IF(AND(ISNUMBER(B56),ISNUMBER(C56)),B56-$B$10*C56,"") -> 86.78 | E56: =IF(ISNUMBER(D56),D56*$B$11,"") -> 8678 | F56: =IF(M56<>1,"",SUMIFS('IV history'!$K$7:$K$926,'IV history'!$A$7:$A$926,A56,'IV history'!$C$7:$C$926,$B$6,'IV history'!$D$7:$D$926,$B$7)) -> 0.4043901 | G56: =IF(N56<>1,"",SUMIFS('IV history'!$K$7:$K$926,'IV history'!$A$7:$A$926,A56,'IV history'!$C$7:$C$926,$B$6,'IV history'!$D$7:$D$926,$B$8)) -> 0.41615491 | H56: =IF(AND(ISNUMBER(F56),ISNUMBER(G56)),100*(F56-G56),"") -> -1.1764812 | I56: =IF($D$6<>"Ready","Check selection",IF(K56=0,"No observation",IF(K56>1,"Duplicate observations",IF(M56=0,"Flagged; IV unavailable","Screen passed")))) -> Screen passed | J56: =IF($D$6<>"Ready","Check selection",IF(L56=0,"No observation",IF(L56>1,"Duplicate observations",IF(N56=0,"Flagged; IV unavailable","Screen passed")))) -> Screen passed | K56: =IF($D$6<>"Ready","",COUNTIFS('IV history'!$A$7:$A$926,A56,'IV history'!$C$7:$C$926,$B$6,'IV history'!$D$7:$D$926,$B$7)) -> 1 | L56: =IF($D$6<>"Ready","",COUNTIFS('IV history'!$A$7:$A$926,A56,'IV history'!$C$7:$C$926,$B$6,'IV history'!$D$7:$D$926,$B$8)) -> 1 | M56: =IF(K56<>1,"",COUNTIFS('IV history'!$A$7:$A$926,A56,'IV history'!$C$7:$C$926,$B$6,'IV history'!$D$7:$D$926,$B$7,'IV history'!$K$7:$K$926,">0")) -> 1 | N56: =IF(L56<>1,"",COUNTIFS('IV history'!$A$7:$A$926,A56,'IV history'!$C$7:$C$926,$B$6,'IV history'!$D$7:$D$926,$B$8,'IV history'!$K$7:$K$926,">0")) -> 1 | S56: =TEXT(A56,"dd-mmm") -> 16-sep | T56: =IF(ISNUMBER(D56),D56,NA()) -> 86.78 | U56: =IF(ISNUMBER(F56),F56,NA()) -> 0.4043901 | V56: =IF(ISNUMBER(G56),G56,NA()) -> 0.41615491
A58: Changing the ratio changes cost, not either leg’s IV. IV gap = long IV minus short IV, in percentage points.
A59: Coverage: 21 Aug–16 Sep 2026. Fixed October expiry. Flags and original observations remain in IV history.
